Workbook
Name de: 'Dana Eks + PKS'!$E$5:$E$71
Name duplikasi: PI!$E$6:$E$231
Name index: Master!$F$10:$F$11
Name jdn: Master!$G$34:$G$35
Name jnjg: Master!$C$50:$C$53
Name jnski: Master!$A$10:$A$14
Name jnsolehan: Master!$C$34:$C$36
Name jnspi: Master!$A$17:$A$20
Name jnspwrp: Master!$C$25:$C$29
Name kelris: Master!$A$61:$A$68
Name ki: #REF!
Name mtr: Master!$J$25:$J$26
Name nmperiset: 'Rekap Capaian Individu'!$C$6:$C$119
Name outputdana: Master!$A$45:$A$47
Name periodestamp: Master!$A$70:$A$81
Name psv: Master!$E$50:$E$51
Name publikasi: PN!$E$6:$E$199
Name publikasi: PWRP!$E$6:$E$53
Name publikasi: PI!$E$6:$E$231
Name reppi: Master!$C$17:$C$20
Name reppn: Master!$F$17:$F$18
Name satuan: Master!$L$50:$L$52
Name smbrdana: Master!$A$34:$A$41
Name statki: Master!$A$2:$A$5
Name statpi: Master!$A$25:$A$30
Name statuskelris: Master!$C$70:$C$71
Name stspwrp: Master!$G$25:$G$31
Name stssdm: Master!$A$50:$A$55
Name stsupload: Master!$C$10:$C$11
Name vol: Master!$I$50:$I$52

Sheet PI
A1: PUBLIKASI INTERNASIONAL
A4: DIISI OLEH PJ MONEV | E4: PUSAT RISET SAINS DATA DAN INFORMASI | G4: PENULIS (SIVITAS PRSDI) | W4: JENIS DAKUNG
A5: NO | B5: Periode Input | C5: Periode Stamp | D5: Validasi KR | E5: JUDUL | F5: KELOMPOK RISET | G5: 1 | H5: 2 | I5: 3 | J5: 4 | K5: 5 | L5: 6 | M5: 7 | N5: 8 | O5: 9 | P5: 10 | Q5: NON SIVITAS PRSDI | R5: JENIS | S5: STATUS | T5: NAMA JURNAL/PROSIDING | U5: TERINDEX SCOPUS | V5: REPUTASI | W5: UPLOAD GDRIVE | X5: URL | Y5: DOI/SCOPUS (Wajib Jika status Published) | Z5: CATATAN
A6: 1 | B6: =IF(OR(E6<>"",F6<>""),IF(B6="",NOW(),B6),"") -> 45722.401 | E6: Analysis of alternatives methodology for large-scale information system implementation | F6: Temu Kembali Informasi (Information Retrieval) | G6: Andria Arisal, M. Eng. | Q6: Bambang Setiadi, Ichwanul Muslim | R6: Jurnal | S6: Published | T6: Bulletin of Electrical Engineering and Informatics | U6: Ya | V6: Q2 | W6: PI | X6: https://www.scopus.com/record/display.uri?eid=2-s2.0-85210507847&origin=resultslist | Y6: https://doi.org/10.11591/eei.v14i1.7800 | Z6: Sudah diklaim 2024 | AB6: Generate fuzzy string-matching to build self attention on Indonesian medical-chatbot | AC6: Published | AD6: https://doi.org/10.11591/ijece.v14i1.pp819-829 | AE6: PRSDI
A7: 2 | B7: =IF(OR(E7<>"",F7<>""),IF(B7="",NOW(),B7),"") -> 45722.401 | C7: Triwulan I | E7: Analysis of TRISO failure fraction in PeLUIt reactor with increasing power | F7: Rekayasa Pengetahuan dan Data (Knowledge and Data Engineering) | G7: Dr. Arya Adhyaksa Waskita, M.Si | Q7: Fitria Miftasani, Steven Wijaya, Nina Widiawati, Anni Nuril Hidayati, Dany Mulyana, Hakimul Wafda, Anik Purwaningsih, Fajar Al Afghani, Muhammad Ilham Bayquni, Topan Setiadipura | R7: Jurnal | S7: Published | T7: Nuclear Engineering and Design | U7: Ya | V7: Q2 | W7: PI | X7: https://www.scopus.com/record/display.uri?eid=2-s2.0-85214489294&origin=resultslist | Y7: https://doi.org/10.1016/j.nucengdes.2025.113842 | AB7: UAV-assisted heavy metal tracking in oil palm plantations: present applications and future prospects | AC7: Published | AD7: https://doi.org/10.1080/2150704X.2023.2299268
A8: 3 | B8: =IF(OR(E8<>"",F8<>""),IF(B8="",NOW(),B8),"") -> 45722.401 | C8: Triwulan I | E8: A Literature Review of Virtual Reality Exergames for Older Adults: Enhancing Physical, Cognitive, and Social Health | F8: Interaksi Manusia-Komputer dan Visualisasi (Human Computer Interaction and Visualisation) | G8: M. Yudhi Rezaldi, Ph.D | Q8: Xiacheng Song, Nazlena Mohamad Ali, Mohamad Hidir Mhd Salim | R8: Jurnal | S8: Published | T8: Applied Sciences (Switzerland) | U8: Ya | V8: Q2 | W8: PI | X8: https://www.scopus.com/record/display.uri?eid=2-s2.0-85214446910&origin=resultslist | Y8: https://doi.org/10.3390/app15010351 | AB8: Decision support system for fish quarantine measures in Indonesia | AC8: Published | AD8: https://doi.org/10.1108/VJIKMS-08-2021-0144
A9: 4 | B9: =IF(OR(E9<>"",F9<>""),IF(B9="",NOW(),B9),"") -> 45722.401 | C9: Triwulan I | E9: Clinical indicators for predicting physical activity levels in long-term COVID-19: Insights from physical exertion and oxygen saturation | F9: Pemerintahan Digital (Digital Government) | G9: Rezzy Eko Caraka ,S.Si.,M.Sc(RES).,PhD. | Q9: Triana Karnadipa, Aditya Denny Pratama, Riza Pahlawi, Mita Noviana, Chye Wah Yu, Yi Wan | R9: Jurnal | S9: Published | T9: Journal of Bodywork and Movement Therapies | U9: Ya | V9: Q2 | W9: PI | X9: https://www.scopus.com/record/display.uri?eid=2-s2.0-85212560912&origin=resultslist | Y9: https://doi.org/10.1016/j.jbmt.2024.11.031 | AB9: Investigating Adolescent Vulnerability in Indonesia: A Socio-Remote Sensing Big Data Analytics Study Using Night Light Data | AC9: Published | AD9: https://doi.org/10.1109/ACCESS.2024.3355963
A10: 5 | B10: =IF(OR(E10<>"",F10<>""),IF(B10="",NOW(),B10),"") -> 45722.401 | C10: Triwulan I | E10: Improved LSTM hyperparameters alongside sentiment walk-forward validation for time series prediction | F10: Pemerintahan Digital (Digital Government) | G10: Rezzy Eko Caraka ,S.Si.,M.Sc(RES).,PhD. | Q10: Eko Putra Wahyuddin, Wahyuddin E.P., Robert Kurniawan, Wahyu Caesarendra, Caesarendra W., Prana Ugiana Gio, Bens Pardamean | R10: Jurnal | S10: Published | T10: Journal of Open Innovation: Technology, Market, and Complexity | U10: Ya | V10: Q1 | W10: PI | X10: https://www.scopus.com/record/display.uri?eid=2-s2.0-85212942087&origin=resultslist | Y10: https://doi.org/10.1016/j.joitmc.2024.100458 | AB10: Implementing night light data as auxiliary variable of small area estimation | AC10: Published | AD10: https://doi.org/10.1080/03610926.2022.2077963
A11: 6 | B11: =IF(OR(E11<>"",F11<>""),IF(B11="",NOW(),B11),"") -> 45722.401 | C11: Triwulan I | E11: Bibliometric analysis of model vehicle routing problem in logistics delivery | F11: Pemerintahan Digital (Digital Government) | G11: Rezzy Eko Caraka ,S.Si.,M.Sc(RES).,PhD. | Q11: Muhammad Khahfi Zuhanda, Hartono, Samsul Abdul Rahman Sidik Hasibuan, Dahlan Abdullah, Prana Ugiana Gio | R11: Jurnal | S11: Published | T11: Indonesian Journal of Electrical Engineering and Computer Science | U11: Ya | V11: Q3 | W11: PI | X11: https://www.scopus.com/record/display.uri?eid=2-s2.0-85208030650&origin=resultslist | Y11: https://doi.org/10.11591/ijeecs.v37.i1.pp530-539 | AB11: Emphasizing Data Quality for the Identification of Chili Varieties in the Context of Smart Agriculture | AC11: Published | AD11: https://doi.org/10.28945/5257
A12: 7 | B12: =IF(OR(E12<>"",F12<>""),IF(B12="",NOW(),B12),"") -> 45722.401 | C12: Triwulan I | E12: The development of a Web-based in-text citation analysis tool | F12: Interaksi Manusia-Komputer dan Visualisasi (Human Computer Interaction and Visualisation) | G12: Dr. Ambar Yoganingrum | H12: Hayuning Titi Karsanti S. Kom., M.Eng | I12: Yaniasih | Q12: Ira Maryati, Gita Citra Puspita, Ekawati Marlina | R12: Jurnal | S12: Published | T12: Emerald Publisher | U12: Ya | V12: Q1 | W12: PI | X12: https://www.emerald.com/insight/content/doi/10.1108/lhtn-12-2024-0208/full/html | Y12: https://doi.org/10.1108/LHTN-12-2024-0208 | AB12: Improving Research Support Services in Indonesian Academic Digital Libraries: A Recommendation for Business Process Reengineering Implementation Strategies | AC12: Published | AD12: https://doi.org/10.5860/llm.v37i3.7559
A13: 8 | B13: =IF(OR(E13<>"",F13<>""),IF(B13="",NOW(),B13),"") -> 45722.401 | C13: Triwulan I | E13: The Digital Twin City in Enhancing Flood Evacuation Systems: Future Opportunities and Challenges | F13: Interaksi Manusia-Komputer dan Visualisasi (Human Computer Interaction and Visualisation) | G13: Dr. Ambar Yoganingrum | H13: Abdurrakhman Prasetyadi, M.P | I13: Prof. Dr. Ana Hadiana, M.Eng.Sc. | Q13: Ary Setijadi Prihatmanto, Ridwan Sutriadi | R13: Jurnal | S13: Published | T13: IEEE Access | U13: Ya | V13: Q1 | W13: PI | X13: https://ieeexplore.ieee.org/document/10876129 | Y13: https://doi.org/10.1109/ACCESS.2025.3539346 | AB13: The Evaluation of Fundamental Safety Function and Defence in Depth of AP1000 Using Probabilistic Analysis | AC13: Published | AD13: https://doi.org/10.1063/5.0192928
A14: 9 | B14: =IF(OR(E14<>"",F14<>""),IF(B14="",NOW(),B14),"") -> 45722.401 | C14: Triwulan I | E14: Bibliometrics for analysing business opportunities and players in the pharmaceuticals fields | F14: Interaksi Manusia-Komputer dan Visualisasi (Human Computer Interaction and Visualisation) | G14: Dr. Ambar Yoganingrum | H14: Dr. Eng. Budi Nugroho | I14: Siti Kania Kushadiani, S.T., M.Kom. | Q14: Yaniasih, Koharudin | R14: Jurnal | S14: Published | T14: International Journal of Technological Learning, Innovation and Development (IJTLID) | U14: Ya | V14: Q3 | W14: PI | X14: https://www.inderscienceonline.com/doi/abs/10.1504/IJTLID.2025.144531 | Y14: https://doi.org/10.1504/IJTLID.2025.144531 | AB14: Thematic evolution of smart learning environments, insights and directions from a 20-year research milestones: A bibliometric analysis | AC14: Published | AD14: https://doi.org/10.1016/j.heliyon.2024.e26191
A15: 10 | B15: =IF(OR(E15<>"",F15<>""),IF(B15="",NOW(),B15),"") -> 45722.419 | D15: ☑️ | E15: The development of a Web-based in-text citation analysis tool | F15: Rekayasa Pengetahuan dan Data (Knowledge and Data Engineering) | G15: Hayuning Titi Karsanti S. Kom., M.Eng | Q15: Ira Maryati, Yaniasih Yaniasih, Gita Citra Puspita, Ekawati Marlina | R15: Jurnal | S15: Published | T15: Emerald Publisher | U15: Ya | V15: Q1 | W15: PI | X15: https://www.emerald.com/insight/content/doi/10.1108/lhtn-12-2024-0208/full/html | Y15: https://doi.org/10.1108/LHTN-12-2024-0208 | AB15: Fine-Tuning of Predictive Models CNN-LSTM and CONV-LSTM for Nowcasting PM2.5Level | AC15: Published | AD15: https://doi.org/10.1109/ACCESS.2024.3368034
A16: 11 | B16: =IF(OR(E16<>"",F16<>""),IF(B16="",NOW(),B16),"") -> 45722.421 | D16: ☑️ | E16: Bibliometrics for analysing business opportunities and players in the pharmaceuticals fields | F16: Pemerintahan Digital (Digital Government) | G16: Dr. Eng. Budi Nugroho | Q16: Yaniasih, Koharudin | R16: Jurnal | S16: Published | T16: International Journal of Technological Learning, Innovation and Development (IJTLID) | U16: Ya | V16: Q3 | W16: PI | X16: https://www.inderscienceonline.com/doi/abs/10.1504/IJTLID.2025.144531 | Y16: https://doi.org/10.1504/IJTLID.2025.144531 | AB16: Business Predictive Analytics of Smallholder Indonesian Maize using Vector Error Correction | AC16: Published
A17: 12 | B17: =IF(OR(E17<>"",F17<>""),IF(B17="",NOW(),B17),"") -> 45729.497 | C17: Triwulan I | E17: Hyperparameter Tuning on Machine Learning-Based Landslide Susceptibility Mapping (Case study: Palu City and Its Surrounding areas) | F17: Temu Kembali Informasi (Information Retrieval) | G17: Andri Fachrur Rozie, M. Eng. | Q17: Sukristiyanti, Pamela, Moch Hilmi Zaenal Putra, Yukni Arifianti, Hilda Lestiana, Tri Muji Susantoro, Sumaryono, Yohandi Kristiawan, Iqbal Eras Putra | R17: Jurnal | S17: Published | T17: Indonesian Journal on Geoscience | U17: Ya | V17: Q3 | W17: PI | X17: https://www.scopus.com/record/display.uri?eid=2-s2.0-85219687867&origin=recordpage | Y17: https://doi.org/10.17014/ijog.12.1.43-53 | AB17: Empowering deaf communication: a novel LSTM model for recognizing Indonesian sign language | AC17: Published | AD17: https://doi.org/10.1007/s10209-024-01095-1
A18: 13 | B18: =IF(OR(E18<>"",F18<>""),IF(B18="",NOW(),B18),"") -> 45735.484 | E18: Remote Sensing Applications in Biodiversity Assessment and Conservation of the Sundaland Biodiversity Hotspot | F18: Rekayasa Pengetahuan dan Data (Knowledge and Data Engineering) | G18: Wawan Hendriawan Nur, S.Si., M.T. | H18: Aang Gunawan S, S.Kom., M.T. | I18: Dr. Eng. Budi Nugroho | Q18: Yuliana Susilowati, Waluyo Eko Cahyono, Ayubella Anggraini Leksono, Dewi Puspitasari Leksono, Putri Larasati Leksono, Redempta Bungan Krisetiawan Putri, Yugo Kumoro, Ibnu Maryanto | R18: Bag Buku | S18: Accepted | T18: Apple Academic Press | U18: Ya | W18: PI | AB18: Determinants of knowledge sharing among civil servants and the moderating effects of leadership styles | AC18: Published | AD18: https://doi.org/10.1177/02663821231216687
A19: 14 | B19: =IF(OR(E19<>"",F19<>""),IF(B19="",NOW(),B19),"") -> 45736.242 | C19: Triwulan I | E19: The Examining of 360∘ Media That Support Learning in Field of Education | F19: Interaksi Manusia-Komputer dan Visualisasi (Human Computer Interaction and Visualisation) | G19: M. Yudhi Rezaldi, Ph.D | Q19: Gema Ari Prahara | R19: Prosiding | S19: Published | T19: KnE Social Sciences | U19: Ya | W19: PI | X19: https://kneopen.com/KnE-Social/article/view/17900/ | Y19: https://doi.org/10.18502/kss.v10i3.17900 | AB19: The development land utilization and cover of the Jambi district are examined and forecasted using Google Earth Engine and CNN1D | AC19: Published | AD19: https://doi.org/10.1016/j.rsase.2024.101175
A20: 15 | B20: =IF(OR(E20<>"",F20<>""),IF(B20="",NOW(),B20),"") -> 45736.242 | E20: How could Virtual Reality Inclusively Improve Disaster Awareness to Tsunami? | F20: Interaksi Manusia-Komputer dan Visualisasi (Human Computer Interaction and Visualisation) | G20: M. Yudhi Rezaldi, Ph.D | Q20: Gusti Ayu Ketut Surtiari, Syarifah Aini Dalimunthe, Abdul Fikri Angga Reksa, Taro Arikawa and Diah Lenggogeni | R20: Prosiding | S20: Accepted | T20: AIWEST 2024 | U20: Ya | W20: PI | X20: https://eprints.uad.ac.id/80093/1/BOOK%20OF%20ABSTRACT-AIWEST%20DR%202024.pdf | AB20: Exploring usage-based and usability metrics for user experience for sus- tainable e-learning systems | AC20: Published | AD20: https://doi.org/10.1051/e3sconf/202450102003
A21: 16 | B21: =IF(OR(E21<>"",F21<>""),IF(B21="",NOW(),B21),"") -> 45737.621 | C21: Triwulan I | E21: Design and Construction of an Automatic Dispenser for the Visually Impaired Using Microcontroller Technology | F21: Interaksi Manusia-Komputer dan Visualisasi (Human Computer Interaction and Visualisation) | G21: Arafat Febriandirza, Ph.D | Q21: Abdiel Alpriyan Gempa Alamsyah Sahurib | R21: Prosiding | S21: Published | T21: ICMAT 2024 | U21: Ya | W21: PI | X21: https://www.scopus.com/record/display.uri?eid=2-s2.0-85215504172&origin=recordpage | Y21: https://doi.org/10.3233/ATDE241220 | Z21: Konferensi ICMAT pada akhir tahun 2024 belum diklaim dan indeks scopus muncul di tahun 2025 | AA21: https://ebooks.iospress.nl/doi/10.3233/ATDE241220 | AB21: Plant-Disease Relation Model through BERT-BiLSTM-CRF Approach | AC21: Published | AD21: https://doi.org/10.52549/ijeei.v12i1.5154
A22: 17 | B22: =IF(OR(E22<>"",F22<>""),IF(B22="",NOW(),B22),"") -> 45737.634 | C22: Triwulan I | E22: Smart Home Innovation: IOT-Based Lighting Control System Design | F22: Interaksi Manusia-Komputer dan Visualisasi (Human Computer Interaction and Visualisation) | G22: Christine Cecylia Munthe, S.Kom. | H22: Arafat Febriandirza, Ph.D | R22: Prosiding | S22: Published | T22: ICMAT 2024 | U22: Ya | W22: PI | X22: https://www.scopus.com/record/display.uri?eid=2-s2.0-85215511644&origin=recordpage | Y22: https://doi.org/10.3233/ATDE241310 | Z22: Konferensi ICMAT pada akhir tahun 2024 belum diklaim dan indeks scopus muncul di tahun 2025 | AA22: https://ebooks.iospress.nl/doi/10.3233/ATDE241310 | AB22: Unveiling Sentiments: Social Media Analytics on Indonesian Startup and Fintech Discourse | AC22: Published | AD22: https://doi.org/10.1109/ICETSIS61505.2024.10459378
A23: 18 | B23: =IF(OR(E23<>"",F23<>""),IF(B23="",NOW(),B23),"") -> 45741.49 | C23: April | E23: Exploring Features and Products in E-Commerce on Consumers Behavior using Cognitive Affective | F23: Pemerintahan Digital (Digital Government) | G23: Rezzy Eko Caraka ,S.Si.,M.Sc(RES).,PhD. | Q23: PAHRUDIN PAHRUDIN, LI-WEI LIU1, PRANA UGIANA GIO, NUR ANITA YUNIKAWATI, BENS PARDAMEAN | R23: Prosiding | S23: Published | T23: IEEE Access | U23: Ya | W23: PI | X23: https://ieeexplore.ieee.org/document/10934986 | Y23: https://doi.org/10.1109/ACCESS.2025.3553192 | AB23: Developing a Seismic Land Capability Framework for Earthquake-resistant Housing Based on GIS Approach: A Case of Sukabumi District | AC23: Published | AD23: https://doi.org/10.21163/GT_2024.191.12
A24: 19 | B24: =IF(OR(E24<>"",F24<>""),IF(B24="",NOW(),B24),"") -> 45764.773 | C24: Triwulan IV | E24: Comparative Performance Analysis of CNN-Architectures on Coffee-bean Roast Classification | F24: Temu Kembali Informasi (Information Retrieval) | G24: Irfan Asfy Fakhry Anto S.Kom., M.T | Q24: Jony Winaryo Wibowo, Taufik Ibnu Salim, Aris Munandar | R24: Jurnal | S24: Published | T24: Telecommunication Computing Electronics and Control | U24: Ya | V24: Q3 | W24: PI | X24: https://drive.google.com/file/d/1yjgKM3kYTg0HSk339-r_Yg230KeUajb-/view?usp=drive_link | Y24: https://doi.org/10.12928/TELKOMNIKA.v23i6.27090 | AB24: BERTopic Analysis of Indonesian Biodiversity Policy on Social Media | AC24: Published | AD24: https://doi.org/10.37936/ecti-cit.2024173.255058
A25: 20 | B25: =IF(OR(E25<>"",F25<>""),IF(B25="",NOW(),B25),"") -> 45768.35 | C25: April | E25: Leveraging YOLOv8 for Real-Time Parking Space Detection | F25: Interaksi Manusia-Komputer dan Visualisasi (Human Computer Interaction and Visualisation) | G25: Dr. Esa Prakasa, MT | H25: Dr. Eng. Ir Yuyun, S.Kom., M.T | Q25: Mahabintang Pallawabonang, Muh. Adnan, Sitti Zuhriyah, Amirul Mukmin | R25: Prosiding | S25: Published | T25: 2024 Beyond Technology Summit on Informatics International Conference (BTS-I2C) | U25: Ya | W25: PI | X25: https://ieeexplore.ieee.org/abstract/document/10942123 | Y25: https://doi.org/10.1109/BTS-I2C63534.2024.10942123 | AB25: A Systematic Literature Review on University Collaboration in Open Innovation: Trends, Technologies, and Frameworks | AC25: Published | AD25: https://doi.org/10.34190/ejkm.22.1.3407
A26: 21 | B26: =IF(OR(E26<>"",F26<>""),IF(B26="",NOW(),B26),"") -> 45768.35 | C26: April | E26: Leveraging the Pre-Trained Whisper Model and Levenshtein Distance for Audio Buginesse Transcription | F26: Pengolahan Bahasa Alami (Natural Language Processing) | G26: Dr. Eng. Ir Yuyun, S.Kom., M.T | H26: Dr. Esa Prakasa, MT | Q26: Amirul Mukmin, Muh. Adnan,Abdul Jalil, Mahabintang Pallawabonang | R26: Prosiding | S26: Published | T26: 2024 Beyond Technology Summit on Informatics International Conference (BTS-I2C) | U26: Ya | W26: PI | X26: https://ieeexplore.ieee.org/abstract/document/10942151 | Y26: https://doi.org/10.1109/BTS-I2C63534.2024.10942151 | AB26: Unraveling Knowledge-based Chatbot Adoption Intention in Enhancing Species Literacy | AC26: Published | AD26: https://doi.org/10.28945/5280
A27: 22 | B27: =IF(OR(E27<>"",F27<>""),IF(B27="",NOW(),B27),"") -> 45768.35 | C27: April | E27: Grammar Error Correction in Indonesian Sports News: Comparing the Performance of Pre-Trained T5 and BART Models | F27: Pengolahan Bahasa Alami (Natural Language Processing) | G27: Dr. Eng. Ir Yuyun, S.Kom., M.T | H27: Dr. Esa Prakasa, MT | Q27: Muh. Adnan, Najirah Umar, Nasrullah, Adi Sadli, A. Edeth Fuari Anatasya, Hazriani, Mashur Razak | R27: Prosiding | S27: Published | T27: 2024 Beyond Technology Summit on Informatics International Conference (BTS-I2C) | U27: Ya | W27: PI | X27: https://ieeexplore.ieee.org/abstract/document/10941994 | Y27: https://doi.org/10.1109/BTS-I2C63534.2024.10941994 | AB27: Transactional Business Process Redesign of Procurement Planning System using Heuristic Method | AC27: Published | AD27: https://doi.org/10.1109/ICoSEIT60086.2024.10497473
A28: 23 | B28: =IF(OR(E28<>"",F28<>""),IF(B28="",NOW(),B28),"") -> 45768.361 | D28: ☑️ | E28: Leveraging YOLOv8 for Real-Time Parking Space Detection | F28: Pengolahan Bahasa Alami (Natural Language Processing) | G28: Dr. Eng. Ir Yuyun, S.Kom., M.T | Q28: Mahabintang Pallawabonang, Muh. Adnan, Sitti Zuhriyah, Amirul Mukmin | R28: Prosiding | S28: Published | T28: 2024 Beyond Technology Summit on Informatics International Conference (BTS-I2C) | U28: Ya | W28: PI | X28: https://ieeexplore.ieee.org/abstract/document/10942123 | Y28: https://doi.org/10.1109/BTS-I2C63534.2024.10942123 | AB28: Supply chain pattern of blue swimming crabs in the north coast of Java, Indonesia | AC28: Published | AD28: https://doi.org/10.5267/j.uscm.2024.5.007
A29: 24 | B29: =IF(OR(E29<>"",F29<>""),IF(B29="",NOW(),B29),"") -> 45768.366 | D29: ☑️ | E29: Leveraging the Pre-Trained Whisper Model and Levenshtein Distance for Audio Buginesse Transcription | F29: Interaksi Manusia-Komputer dan Visualisasi (Human Computer Interaction and Visualisation) | G29: Dr. Esa Prakasa, MT | Q29: Amirul Mukmin, Muh. Adnan,Abdul Jalil, Mahabintang Pallawabonang | R29: Prosiding | S29: Published | T29: 2024 Beyond Technology Summit on Informatics International Conference (BTS-I2C) | U29: Ya | W29: PI | X29: https://ieeexplore.ieee.org/abstract/document/10942151 | Y29: https://doi.org/10.1109/BTS-I2C63534.2024.10942151 | AB29: Technology readiness level assessment of system information zoonosis and emerging infectious disease | AC29: Published | AD29: https://doi.org/10.1063/5.0208106
A30: 25 | B30: =IF(OR(E30<>"",F30<>""),IF(B30="",NOW(),B30),"") -> 45768.368 | D30: ☑️ | E30: Grammar Error Correction in Indonesian Sports News: Comparing the Performance of Pre-Trained T5 and BART Models | F30: Interaksi Manusia-Komputer dan Visualisasi (Human Computer Interaction and Visualisation) | G30: Dr. Esa Prakasa, MT | Q30: Muh. Adnan, Najirah Umar, Nasrullah, Adi Sadli, A. Edeth Fuari Anatasya, Hazriani, Mashur Razak | R30: Prosiding | S30: Published | T30: 2024 Beyond Technology Summit on Informatics International Conference (BTS-I2C) | U30: Ya | W30: PI | X30: https://ieeexplore.ieee.org/abstract/document/10941994 | Y30: https://doi.org/10.1109/BTS-I2C63534.2024.10941994 | AB30: Measurement of Si Pixel Sensor Alignment for the ALICE ITS Detector | AC30: Published | AD30: https://doi.org/10.1088/1361-6501/ad4fae
A31: 26 | B31: =IF(OR(E31<>"",F31<>""),IF(B31="",NOW(),B31),"") -> 45770.547 | C31: April | E31: Internet Service Assessment in Lombok Barat Regency | F31: Pemerintahan Digital (Digital Government) | G31: Dr. Eng. Budi Nugroho | H31: Dra. Andrari Grahitandaru, M.Sc. | Q31: Sumirah | R31: Prosiding | S31: Published | T31: INTERNATIONAL CONFERENCE ON INFORMATION TECHNOLOGY SYSTEMS AND INNOVATION (ICITSI 2024) | U31: Ya | W31: PI | X31: https://ieeexplore.ieee.org/abstract/document/10929191 | Y31: https://doi.org/10.1109/ICITSI65188.2024.10929191 | Z31: ICITSI 2024 dilaksanakan pada bulan Desember 2024, dan baru terbit di IEEE Xplore pada bulan Maret 2025. Paper belum kami klaim sebagai capaian di tahun 2024. | AB31: An Analysis of the Open Government Data Ecosystem in Tangerang Regency to Promote Data Sharing Initiatives | AC31: Published | AD31: https://doi.org/10.1109/IC3INA64086.2024.10732524
A32: 27 | B32: =IF(OR(E32<>"",F32<>""),IF(B32="",NOW(),B32),"") -> 45770.55 | C32: April | E32: On the Use of Remote Sensing Data for Monitoring NDVI Anomalies and Correlations with Rainfall Anomalies in West Java Province, Indonesia: Addressing Sustainable Development Goal 2 | F32: Pemerintahan Digital (Digital Government) | G32: Hengki Muradi, M.Si. | Q32: Orbita Roswintiarti, Novie Indriasari, Fadilah Halim Rasyidi, Inggit Lolita Sari, Kustiyo, Babag Purbantoro, Ansy Indrajad, Akhmad Ubehi | R32: Jurnal | S32: Published | T32: Remote Sensing in Earth Systems Sciences | U32: Ya | V32: Q2 | W32: PI | X32: https://link.springer.com/content/pdf/10.1007/s41976-025-00222-7.pdf | Y32: https://doi.org/10.1007/s41976-025-00222-7 | AB32: A qualitative exploration of challenges and factors in research data management across Indonesian research institutes | AC32: Published | AD32: https://doi.org/10.1177/09610006241252662
A33: 28 | B33: =IF(OR(E33<>"",F33<>""),IF(B33="",NOW(),B33),"") -> 45775.63 | C33: April | E33: Community preparedness for earthquake disasters: A preliminary assessment of awareness and disaster infrastructure response in Cianjur, West Java-Indonesia | F33: Pengolahan Bahasa Alami (Natural Language Processing) | G33: Prabu Kresna Putra, S.T., M.T.I. | Q33: Dewayany Sutrisno, Yatin Suwarno, Ati Rahadiati, Muhammad Iqbal Habibie, Hari Prayogi, Amien Widodo, Fathia Zulfati Sabrina, Ahmad Kosasih | R33: Jurnal | S33: Published | T33: F1000Research | U33: Ya | V33: Q2 | W33: PI | X33: https://www.scopus.com/record/display.uri?eid=2-s2.0-86000769038&origin=recordpage | Y33: https://doi.org/10.12688/f1000research.143577.3 | AB33: Air Quality Monitoring in Indonesia | AC33: Published | AD33: https://doi.org/10.1109/AGERS61027.2023.10490762
A34: 29 | B34: =IF(OR(E34<>"",F34<>""),IF(B34="",NOW(),B34),"") -> 45775.78 | C34: April | E34: The recognition and protection of customary law communities in maintaining culture as a tourist attraction in Sembalun village East Lombok | F34: Pemerintahan Digital (Digital Government) | G34: Rezzy Eko Caraka ,S.Si.,M.Sc(RES).,PhD. | Q34: Komang Mahawira, Ali Muhtasom, Amirosa Ria Satiadji, Achlan Fahlevi Royanow | R34: Jurnal | S34: Published | T34: International Journal of Innovative Research and Scientific Studies | U34: Ya | V34: Q2 | W34: PI | X34: https://www.scopus.com/record/display.uri?eid=2-s2.0-105000200852&origin=recordpage | Y34: https://doi.org/10.53894/ijirss.v8i2.5289 | AB34: Exploring Regional Dynamics Through Social Media Conversations and Socio-Economic Surveys: Uncovering Perspectives on the Cianjur Earthquake | AC34: Published | AD34: https://doi.org/10.1109/AGERS61027.2023.10490691
A35: 30 | B35: =IF(OR(E35<>"",F35<>""),IF(B35="",NOW(),B35),"") -> 45780.486 | C35: Mei | E35: Strategies to encourage data owners to self-archive data sets | F35: Interaksi Manusia-Komputer dan Visualisasi (Human Computer Interaction and Visualisation) | G35: Dr. Ambar Yoganingrum | Q35: Danarsiwi Tri Lastiwi, Ekawati Marlina, Seno Yudhanto, Dhian Kusumawardhani | R35: Jurnal | S35: Published | T35: Library Hi Tech News (LHTN) | U35: Ya | V35: Q1 | W35: PI | X35: https://www.emerald.com/insight/content/doi/10.1108/lhtn-03-2025-0044/full/html?skipTracking=true | Y35: https://doi.org/10.1108/LHTN-03-2025-0044 | AB35: The Role of Data Governance in a High-Level Approach of Data Migration to Open Data | AC35: Published | AD35: https://doi.org/10.1177/02663821241264702
A36: 31 | B36: =IF(OR(E36<>"",F36<>""),IF(B36="",NOW(),B36),"") -> 45780.487 | C36: Mei | E36: Chili leaf segmentation using meta-learning for improved model accuracy | F36: Temu Kembali Informasi (Information Retrieval) | G36: Dr. Wiwin Suwarningsih, M.T. | H36: Dr. Purnomo Husnul Khotimah, M.T | I36: Ir. Dianadewi Riswantini, M. Sc., M.B.A. | J36: Andri Fachrur Rozie, M. Eng. | K36: Ekasari Nugraheni, M.T. | L36: Andria Arisal, M. Eng. | M36: Devi Munandar, S.Kom., M.Mat. | Q36: Rinda Kirana, Noor Roufiq Ahmadi | R36: Jurnal | S36: Published | T36: Bulletin of Electrical Engineering and Informatics (BEEI) | U36: Ya | V36: Q3 | W36: PI | X36: https://beei.org/index.php/EEI/article/view/7929/4237 | Y36: https://doi.org/10.11591/eei.v14i3.7929 | AB36: A Grouper Fish Mortality Prediction Model Using Transfer Learning Approach | AC36: Published | AD36: https://doi.org/10.1109/AIMS61812.2024.10513177
A37: 32 | B37: =IF(OR(E37<>"",F37<>""),IF(B37="",NOW(),B37),"") -> 45832.683 | C37: Triwulan II | E37: Virtual reality as a pandemic solution: adapting education, working, tourism, and industrial in COVID-19 situation | F37: Interaksi Manusia-Komputer dan Visualisasi (Human Computer Interaction and Visualisation) | G37: M. Yudhi Rezaldi, Ph.D | H37: Dr. Ambar Yoganingrum | I37: Dr. Esa Prakasa, MT | J37: Arafat Febriandirza, Ph.D | K37: Rio Nurtantyana, S.Pd., M.Pd., M.Sc., Ph.D. | L37: Abdurrakhman Prasetyadi, M.P | M37: Aria Bisri, S.Kom. M.T. | N37: Ridwan Suhud, S.Kom., M.T. | O37: Christine Cecylia Munthe, S.Kom. | P37: Rumadi, S.T., M.T. | Q37: Nazlena Mohamad Ali, Cahyo Trianggoro | R37: Bag Buku | S37: Published | T37: The Prediction of Future Pandemic (Elsevier) | U37: Ya | W37: PI | X37: https://www.sciencedirect.com/science/article/abs/pii/B9780443338717000179 | Y37: https://doi.org/10.1016/B978-0-443-33871-7.00017-9 | AB37: Requirements Engineering of Knowledge Management System for Smallholder Dairy Farmers | AC37: Published | AD37: https://doi.org/10.28991/HEF-2024-05-02-02
A38: 33 | B38: =IF(OR(E38<>"",F38<>""),IF(B38="",NOW(),B38),"") -> 45800.193 | C38: Mei | E38: Automated Detection of Helmet Wearing with YOLOv8 and Real-Time Monitoring for Factory Safety | F38: Temu Kembali Informasi (Information Retrieval) | G38: Dr. Wiwin Suwarningsih, M.T. | Q38: Ratna Santi, Ashwin Sasongko Sastrosubroto | R38: Jurnal | S38: Published | T38: Interdisciplinary Journal of Information, Knowledge, and Management | U38: Ya | V38: Q3 | W38: PI | X38: https://www.informingscience.org/Publications/5499 | Y38: https://doi.org/10.28945/5499 | AB38: Bibliometrics for Analysing Business Opportunities and Players in the Pharmaceuticals Fields | AC38: Accepted | AD38: https://doi.org/10.1504/IJTLID.2025.10065144
A39: 34 | B39: =IF(OR(E39<>"",F39<>""),IF(B39="",NOW(),B39),"") -> 45803.311 | C39: Mei | E39: Analysis of Factors Influencing Digital Transformation of Tourism Villages: Evidence from Bogor, Indonesia | F39: Rekayasa Pengetahuan dan Data (Knowledge and Data Engineering) | G39: Dr. Foni Agus Setiawan, M.Kom. | Q39: Isbandriyati Muthmainnah, Iis Anisa Yulia, Aditya Sugih Setiawan, Immas Nurhayati, Bambang Hengky Rainanto, Sri Harini, Endri | R39: Jurnal | S39: Published | T39: Tourism and Hospitality (MDPI) | U39: Ya | V39: Q1 | W39: PI | X39: https://www.mdpi.com/2673-5768/6/2/57 | Y39: https://doi.org/10.3390/tourhosp6020057 | AB39: A Lexical and Post-lexical Prosodic Documentation of Embaloh Language | AC39: Published | AD39: https://doi.org/10.33736/ils.6025.2024
A40: 35 | B40: =IF(OR(E40<>"",F40<>""),IF(B40="",NOW(),B40),"") -> 45803.609 | C40: Triwulan II | E40: Analyzing Halal Concerns on Korean Food Using Text-Mining: Perspectives from Indonesian Social Media Users | F40: Temu Kembali Informasi (Information Retrieval) | G40: Ekasari Nugraheni, M.T. | H40: Andria Arisal, M. Eng. | I40: Andri Fachrur Rozie, M. Eng. | J40: Ir. Dianadewi Riswantini, M. Sc., M.B.A. | K40: Dr. Purnomo Husnul Khotimah, M.T | L40: Dr. Wiwin Suwarningsih, M.T. | R40: Jurnal | S40: Published | T40: International Journal on Food System Dynamics | U40: Ya | V40: Q2 | W40: PI | X40: https://brill.com/view/journals/fsd/aop/article-10.1163-18696945-bja00006/article-10.1163-18696945-bja00006.xml | Y40: https://doi.org/10.1163/18696945-bja00006 | AB40: Feature Selection and Performance Evaluation of Buzzer Classification Model | AC40: Published | AD40: https://doi.org/10.25077/josi.v23.n1.p1-14.2024
A41: 36 | B41: =IF(OR(E41<>"",F41<>""),IF(B41="",NOW(),B41),"") -> 45804.841 | C41: Triwulan II | E41: The Development of A Digital Transformation Model for Higher Education Using the Object-Process Methodology | F41: Interaksi Manusia-Komputer dan Visualisasi (Human Computer Interaction and Visualisation) | G41: Rio Nurtantyana, S.Pd., M.Pd., M.Sc., Ph.D. | H41: Aria Bisri, S.Kom. M.T. | I41: Abdurrakhman Prasetyadi, M.P | Q41: Atina Putri, Allya Paramita Koesoema, Yusep Rosmansyah | R41: Prosiding | S41: Published | T41: International Conference on Computer, Control, Informatics and its Applications, IC3INA | U41: Ya | W41: PI | X41: https://www.scopus.com/record/display.uri?eid=2-s2.0-85211933869&origin=recordpage | Y41: https://doi.org/10.1109/IC3INA64086.2024.10732551 | Z41: IC3INA tahun 2024 akhir, belum diklaim | AB41: Rice Phenology Classification Model Based on Sentinel-1 Using Machine 2 Learning Method on Google Earth Engine | AC41: Published | AD41: https://doi.org/10.1080/07038992.2024.2368036
A42: 37 | B42: =IF(OR(E42<>"",F42<>""),IF(B42="",NOW(),B42),"") -> 45804.857 | C42: Mei | E42: Ihoya: knowledge management system based on community using User-Centered Design (UCD) method | F42: Rekayasa Pengetahuan dan Data (Knowledge and Data Engineering) | G42: Siti Kania Kushadiani, S.T., M.Kom. | Q42: Muhammad Rafi, Sulistyo Puspitodjati, Niken Fitria Apriani, Shidiq Al Hakim, Al Hafiz Akbar Maulana Siagian, Slamet Riyanto, Rodiah | R42: Jurnal | S42: Published | T42: International Journal of Information Technology (Singapore) | U42: Ya | V42: Q2 | W42: PI | X42: https://www.scopus.com/record/display.uri?eid=2-s2.0-85211901572&origin=recordpage | Y42: https://doi.org/10.1007/s41870-024-02344-5 | AB42: Performance of Weather Research Forecasting Model for Seasonal Prediction of Precipitation over Indonesian Maritime Continent | AC42: Published | AD42: https://doi.org/10.1016/j.kjs.2024.100293
A43: 38 | B43: =IF(OR(E43<>"",F43<>""),IF(B43="",NOW(),B43),"") -> 45805.37 | E43: Development of an AI-Driven System for Scientific Article Context Extraction and Knowledge Graph Visualization | F43: Interaksi Manusia-Komputer dan Visualisasi (Human Computer Interaction and Visualisation) | G43: Rio Nurtantyana, S.Pd., M.Pd., M.Sc., Ph.D. | Q43: Abdul Rasyid Himawan, Uun Hariyanti, Tri Afirianto | R43: Bag Buku | S43: Accepted | T43: Lecture Notes in Educational Technology | U43: Ya | W43: PI | X43: https://drive.google.com/file/d/1Mg0DMI-eF61PyJguKFwRR2XhvxztsEGY/view?usp=drive_link | Z43: Accepted, belum published; Output untuk PKS dengan UB tahun 2025 | AB43: Skin Microbial Composition and Genetic Mutation Analysis in Precision Medicine for Epidermolysis Bullosa | AC43: Published | AD43: https://doi.org/10.2174/0113894501290512240327091531
A44: 39 | B44: =IF(OR(E44<>"",F44<>""),IF(B44="",NOW(),B44),"") -> 45805.378 | C44: Oktober | E44: The development of Contextual Chat Interactions with Retrieval-Augmented Generation (RAG) System for Facilitating Learning Hadith | F44: Interaksi Manusia-Komputer dan Visualisasi (Human Computer Interaction and Visualisation) | G44: Rio Nurtantyana, S.Pd., M.Pd., M.Sc., Ph.D. | Q44: Yudi Priyadi, Eko Darwiyanto | R44: Jurnal | S44: Published | T44: Indonesian Journal of Electrical Engineering and Computer Science | U44: Ya | V44: Q4 | W44: PI | X44: https://ijeecs.iaescore.com/index.php/IJEECS/article/view/42679 | Y44: http://doi.org/10.11591/ijeecs.v39.i2.pp987-995 | AB44: Motivations and Potential Solutions in Developing a Knowledge Management System for Organization at Higher Education: A Systematic Literature Review | AC44: Published | AD44: https://doi.org/10.20473/jisebi.10.2.270-289
A45: 40 | B45: =IF(OR(E45<>"",F45<>""),IF(B45="",NOW(),B45),"") -> 45805.429 | C45: Triwulan III | E45: Rural transformation research: Current state, dynamics, and future directions | F45: Interaksi Manusia-Komputer dan Visualisasi (Human Computer Interaction and Visualisation) | G45: Abdurrakhman Prasetyadi, M.P | Q45: Galuh Syahbana Indraprahasta (BRIN); Arief Rahman, Andi Y. Saputra, Vely Brian (IPB) | R45: Jurnal | S45: Published | T45: AREA (UK) | U45: Ya | V45: Q1 | W45: PI | X45: https://rgs-ibg.onlinelibrary.wiley.com/doi/10.1111/area.70049 | Y45: https://doi.org/10.1111/area.70049 | AB45: RECOMMENDATION SYSTEM FOR AN ONLINE SHOPPING PAY-LATER SYSTEM USING A MULTISTAGE APPROACH: A CASE STUDY FROM INDONESIA | AC45: Published | AD45: https://doi.org/10.28945/5366
A46: 41 | B46: =IF(OR(E46<>"",F46<>""),IF(B46="",NOW(),B46),"") -> 45805.433 | E46: Speech-Driven Facial Animation Using Transformer Models: A Foundational Layer for Smart System 4-Layer Architectures | F46: Interaksi Manusia-Komputer dan Visualisasi (Human Computer Interaction and Visualisation) | G46: Abdurrakhman Prasetyadi, M.P | Q46: Ary Setijadi Prihatmanto, Agus Sukoco, Dewi Trisnawati (ITB) | R46: Jurnal | S46: Under Review | T46: IEEE ACCESS | U46: Ya | V46: Q1 | W46: PI | AB46: Effectiveness of Landslide Susceptibility Mapping Using the Maximum Entropy Model and Weights of Evidence Modelling in the Kuningan Regency, West Java, Indonesia | AC46: Published | AD46: https://doi.org/10.17794/rgn.2024.3.3
A47: 42 | B47: =IF(OR(E47<>"",F47<>""),IF(B47="",NOW(),B47),"") -> 45805.582 | C47: Mei | E47: A WebGL Serious Game for Practicing English Conversations in Public Places Using Speech Recognition | F47: Interaksi Manusia-Komputer dan Visualisasi (Human Computer Interaction and Visualisation) | G47: M. Yudhi Rezaldi, Ph.D | H47: Dr. Esa Prakasa, MT | Q47: Rickman Roedavan, Iis Kunia Nurhayati, Kemas Muslim Lhaksmana, and Sritenaya Geovani Putri | R47: Jurnal | S47: Published | T47: International Journal of Serious Games | U47: Ya | V47: Q2 | W47: PI | X47: https://journal.seriousgamessociety.org/index.php/IJSG/article/view/890 | Y47: https://doi.org/10.17083/ijsg.v12i2.890 | AB47: Latest Research in Data Augmentation for Low Resource Language Text Translation: A Review | AC47: Published | AD47: https://doi.org/10.1109/IC3INA64086.2024.10732042.
A48: 43 | B48: =IF(OR(E48<>"",F48<>""),IF(B48="",NOW(),B48),"") -> 45805.678 | E48: Revolutionizing Language Learning and Proficiency with Adaptive Assessments and AI Driven System | F48: Pengolahan Bahasa Alami (Natural Language Processing) | G48: Elvira Nurfadhilah, S.Komp., M. Kom | H48: Dian Isnaeni Nurul Afra, S.Kom., M.T.I. | I48: Prabu Kresna Putra, S.T., M.T.I. | J48: Nimas Ayu Untariyati, S.Kom, M.T.I | K48: Radhiyatul Fajri, S.Kom, M.Pd.T, M.Kom. | L48: Siska Pebiana S.Kom., M.Kom. | Q48: Dr. Ir. Hammam Riza, M.Sc. | R48: Bag Buku | S48: Accepted | T48: IGI Global | W48: PI | AB48: Enhancing Bugis Language POS Tagging Using Recurrent Neural Networks and Semi-Supervised Self-Training | AC48: Published | AD48: https://doi.org/10.1109/IC3INA64086.2024.10732738
A49: 44 | B49: =IF(OR(E49<>"",F49<>""),IF(B49="",NOW(),B49),"") -> 45810.45 | C49: Triwulan II | E49: Functional and Non-Functional Requirement (FR and NFR) Formation Based on Requirement Elicitation Using Text Semantics in IdVar4CL Artifact | F49: Interaksi Manusia-Komputer dan Visualisasi (Human Computer Interaction and Visualisation) | G49: Rio Nurtantyana, S.Pd., M.Pd., M.Sc., Ph.D. | Q49: Nayla Fatimatuzzahra; Yudi Priyadi | R49: Prosiding | S49: Published | T49: 2025 10th International Conference on Signal Processing and Communication (ICSC) | U49: Ya | W49: PI | X49: https://ieeexplore.ieee.org/document/10968323 | Y49: https://doi.org/10.1109/ICSC64553.2025.10968323 | AB49: Unlocking insights from Ministry of Marine Affairs and Fisheries annual reports using LDA: a deep dive into SDG 14 | AC49: Published | AD49: https://doi.org/10.12928/TELKOMNIKA.v22i4.26063
A50: 45 | B50: =IF(OR(E50<>"",F50<>""),IF(B50="",NOW(),B50),"") -> 45819.426 | C50: Triwulan II | E50: Modeling sentiment analysis of Indonesian biodiversity policy Tweets using IndoBERTweet | F50: Pengolahan Bahasa Alami (Natural Language Processing) | G50: Dr. Dipl.(FH) Ing Asril, M.Sc | H50: M. Teduh Uliniansyah, B.Eng., M.Sc., Ph.D. | I50: Agung Santosa, BSEE, M.Kom | J50: Ir. Gunarso | R50: Jurnal | S50: Published | T50: IAES International Journal of Artificial Intelligence (IJ-AI) | U50: Ya | V50: Q2 | W50: PI | X50: https://ijai.iaescore.com/index.php/IJAI/article/view/26816 | Y50: http://doi.org/10.11591/ijai.v14.i3.pp2389-2401 | AB50: Flank wear detection with signal variational mode decomposition and support vector machine algorithm | AC50: Published | AD50: https://doi.org/10.1063/5.0205683
A51: 46 | B51: =IF(OR(E51<>"",F51<>""),IF(B51="",NOW(),B51),"") -> 45819.546 | C51: Triwulan II | E51: Assessing the Economic Impact of Peat Fires on Industrial Plantation Forests in Mesuji Subdistrict, South Sumatra, Indonesia | F51: Pengolahan Bahasa Alami (Natural Language Processing) | G51: Prabu Kresna Putra, S.T., M.T.I. | Q51: Tiara Grace FL, Azalea Eugenie, Doni Fernando, Evie Avianti, Rizki Amaliyah, Hari Priyadi, Ilvi Fauziyah Cahyaningtiyas, Muhammad Iqbal Habibie | R51: Prosiding | S51: Published | T51: IEEE Asia-Pacific Conference on Geoscience, Electronics and Remote Sensing Technology (AGERS) | U51: Ya | W51: PI | X51: https://ieeexplore.ieee.org/abstract/document/10932935/ | Y51: https://doi.org/10.1109/AGERS65212.2024.10932935 | Z51: Seminar pada akhir tahun. Published di Tanggal 26 March 2025 | AB51: Enhanced you only look once approach for automatic phytoplankton identification | AC51: Published | AD51: https://doi.org/10.11591/ijai.v13.i3.pp3426-3436
A52: 47 | B52: =IF(OR(E52<>"",F52<>""),IF(B52="",NOW(),B52),"") -> 45820.619 | C52: Triwulan II | E52: Ensuring unbiasedness: foundational insights into integrating GSTARIMA and DNN models for rainfall prediction | F52: Temu Kembali Informasi (Information Retrieval) | G52: Devi Munandar, S.Kom., M.Mat. | Q52: Budi Nurani Ruchjana,Atje Setiawan Abdullah &Hilman Ferdinandus Pardede | R52: Jurnal | S52: Published | T52: Connection Science | U52: Ya | V52: Q1 | W52: PI | X52: https://www.tandfonline.com/doi/full/10.1080/09540091.2025.2507179 | Y52: https://doi.org/10.1080/09540091.2025.2507179 | AB52: Implementation of Motion Estimation Algorithms in Multi-scalability to Provide High-efficiency Video Coding | AC52: Published | AD52: https://doi.org/10.22266/IJIES2024.0831.76
A53: 48 | B53: =IF(OR(E53<>"",F53<>""),IF(B53="",NOW(),B53),"") -> 45832.841 | C53: Triwulan II | E53: Effect of heat treatment on the microstructure and corrosion properties of electroless Ni-P coating on AISI 1010 steel in a simulated seawater | F53: Rekayasa Pengetahuan dan Data (Knowledge and Data Engineering) | G53: Dr. Arya Adhyaksa Waskita, M.Si | Q53: Rahayu Kusumastuti, Arya Fahriansyah, Siti Musabikha, Siska Prifiharni, Arini Nikitasari, Yulinda Lestari, Sriyono, Ari Yustisia Akbar, Yudi Nugraha Thaha, Sigit Dwi Yudanto, Gadang Priyotomo | R53: Jurnal | S53: Published | T53: Physica Scripta | U53: Ya | V53: Q3 | W53: Pl | X53: https://www.scopus.com/record/display.uri?eid=2-s2.0-105007755356&origin=recordpage | Y53: https://doi.org/10.1088/1402-4896/add966 | AB53: Islam in business ethics research: a bibliometric analysis and future research agenda | AC53: Published | AD53: https://doi.org/10.1108/IJOES-02-2024-0058
A54: 49 | B54: =IF(OR(E54<>"",F54<>""),IF(B54="",NOW(),B54),"") -> 45832.859 | C54: Triwulan II | E54: Customer Satisfaction Evaluation in Online Food Delivery Services: A Systematic Literature Review | F54: Pengolahan Bahasa Alami (Natural Language Processing) | G54: Prabu Kresna Putra, S.T., M.T.I. | Q54: Adimas Fiqri Ramdhansya, Shella Maria Vernanda, Indra Budi, Aris Budi Santoso | R54: Jurnal | S54: Published | T54: Jurnal RESTI | U54: Ya | V54: Q3 | W54: PI | X54: https://www.scopus.com/record/display.uri?eid=2-s2.0-105005968093&origin=recordpage | Y54: https://doi.org/10.29207/resti.v9i2.6205 | AB54: Understanding Pediatric Health Trends in Papua: Insights from SUSENAS, RISKESDAS, Remote Sensing, and Its Relevance to Prabowo and Gibran's Free Lunch and Milk Program | AC54: Published | AD54: https://doi.org/10.1109/ACCESS.2024.3380018
A55: 50 | B55: =IF(OR(E55<>"",F55<>""),IF(B55="",NOW(),B55),"") -> 45838.354 | C55: Oktober | E55: Maintaining Academic Integrity in the Era of Large Language Models: A Guideline for Responsible Prompt Engineering | F55: Pengolahan Bahasa Alami (Natural Language Processing) | G55: Nuraisa Novia Hidayati, S.Kom., M.Kom. | H55: Agung Santosa, BSEE, M.Kom | I55: Elvira Nurfadhilah, S.Komp., M. Kom | J55: Ir. Andi Djalal Latief, M.S. | K55: Dr. Kokoy Siti Komariah S.Kom., M.T., M.Eng. | L55: Dr. Dipl.(FH) Ing Asril, M.Sc | M55: Siska Pebiana S.Kom., M.Kom. | N55: Dr. Eng. Ir Yuyun, S.Kom., M.T | O55: Radhiyatul Fajri, S.Kom, M.Pd.T, M.Kom. | P55: Ir. Tri Sampurno, M.Sc | R55: Bag Buku | S55: Published | T55: IGI Global | U55: Ya | W55: PI | X55: https://www.igi-global.com/book/advanced-prompt-engineering-techniques-resources/359191 | Y55: https://doi.org/10.4018/979-8-3373-0250-8.ch005 | AB55: Using LLM to Convert Bahasa Indonesia Commands into JSON Structures for GIS System API | AC55: Published | AD55: https://doi.org/10.1109/IC3INA64086.2024.10732440.
A56: 51 | B56: =IF(OR(E56<>"",F56<>""),IF(B56="",NOW(),B56),"") -> 45845.661 | C56: Juli | E56: Weighting in-text citation location and context meanings for proposing citation quality score metric | F56: Pengolahan Bahasa Alami (Natural Language Processing) | G56: Yaniasih | Q56: Indra Budi | R56: Jurnal | S56: Published | T56: Performance Measurement and Metrics | U56: Ya | V56: Q1 | W56: PI | X56: https://www.emerald.com/insight/content/doi/10.1108/pmm-04-2024-0025/full/html | Y56: https://doi.org/10.1108/PMM-04-2024-0025 | AB56: ALICE upgrades during the LHC Long Shutdown 2 | AC56: Published | AD56: https://doi.org/10.1088/1748-0221/19/05/P05062
A57: 52 | B57: =IF(OR(E57<>"",F57<>""),IF(B57="",NOW(),B57),"") -> 45846.882 | C57: Juli | E57: Integrated seismo-geodetic observatory network for monitoring the Lembang Fault, West Java, Indonesia | F57: Interaksi Manusia-Komputer dan Visualisasi (Human Computer Interaction and Visualisation) | G57: Aang Gunawan S, S.Kom., M.T. | H57: Ridwan Suhud, S.Kom., M.T. | Q57: Nuraini Rahma Hanifa, Endra Gunawan, Dini Nurfiani, Achmad Fakhrus Shomim, Faiz Muttaqy, Lina Handayani, Deasy Arisa, Rian Amukti, Muhammad Hanif, Yayat Sudrajat, Dannie Hidayat, Iwan Hermawan, Agus Men Riyanto, Eko Yulianto, Adrin Tohari, Qori'atu Zahro, Atin Nur Aulia, Juniator Tulius, Sri Widiyantoro, Rachmah Ida, Cecep Pratama, Putri Natari Ratna, and Titi Anggono | R57: Jurnal | S57: Published | T57: Earth and Planetary Physics | U57: Ya | V57: Q2 | X57: https://www.eppcgs.org/en/article/doi/10.26464/epp2025076 | Y57: http://dx.doi.org/10.26464/epp2025076 | AB57: The preliminary test of the ide-Cabe application on chili seed production | AC57: Published | AD57: https://doi.org/10.1088/1755-1315/1377/1/012102
A58: 53 | B58: =IF(OR(E58<>"",F58<>""),IF(B58="",NOW(),B58),"") -> 45854.559 | E58: Cancel Culture: Perspective of Social Media Team | F58: Temu Kembali Informasi (Information Retrieval) | G58: Dr. DIPL. ING (FH) Anne Parlina, M.P. | Q58: Riri Kusumarani | R58: Bag Buku | S58: Accepted | T58: Alfred Deakin Institute for Citizenship and Globalisation (ADI) | W58: PI | AB58: Assessing Regional Precipitation Patterns Using Multiple Global Satellite-Based Datasets in the Upper Citarum Watershed, Indonesia | AC58: Published | AD58: https://doi.org/10.1007/s12524-024-01952-9
A59: 54 | B59: =IF(OR(E59<>"",F59<>""),IF(B59="",NOW(),B59),"") -> 45854.566 | E59: Digital Consumption Patterns: A Case Study of the Dirty Vote Movie | F59: Temu Kembali Informasi (Information Retrieval) | G59: Dr. DIPL. ING (FH) Anne Parlina, M.P. | Q59: Riri Kusumarani | R59: Bag Buku | S59: Accepted | T59: Alfred Deakin Institute for Citizenship and Globalisation (ADI) | W59: PI | AB59: Identifying Language Anxiety Among Foreign Language Learners Using GRU | AC59: Published | AD59: https://doi.org/10.1109/ICoABCD63526.2024.10704343
A60: 55 | B60: =IF(OR(E60<>"",F60<>""),IF(B60="",NOW(),B60),"") -> 45856.668 | C60: Juli | E60: Multiscale Geographically and Temporally Weighted Regression with LASSO and Adaptive LASSO for Tuberculosis Incidence Mapping in West Java | F60: Temu Kembali Informasi (Information Retrieval) | G60: Dr. Purnomo Husnul Khotimah, M.T | H60: Ir. Dianadewi Riswantini, M. Sc., M.B.A. | I60: Devi Munandar, S.Kom., M.Mat. | Q60: Muhammad Yusuf Al Habsy, Ro'fah Nur Rachmawati, Rifani Bhakti Natari, Muh. Hafizh Izzaturrahim | R60: Jurnal | S60: Published | T60: Communication in Biomathematical Sciences | U60: Ya | V60: Q2 | W60: PI | X60: https://journals.itb.ac.id/index.php/cbms/article/view/23943 | Y60: https://doi.org/10.5614/cbms.2025.8.1.6 | AB60: Citrus Leaf Variety Identification Based on RGB and HSV Color Features | AC60: Published | AD60: https://doi.org/10.1109/IC3INA64086.2024.10732212
A61: 56 | B61: =IF(OR(E61<>"",F61<>""),IF(B61="",NOW(),B61),"") -> 45857.539 | C61: Juli | E61: Target Strength of Eels from Echosounder and Calibrated Fish Finder Using Acoustic Measurement and Numerical Model | F61: Rekayasa Pengetahuan dan Data (Knowledge and Data Engineering) | G61: Dr. Foni Agus Setiawan, M.Kom. | Q61: Angga Dwinovantyo, Triyanto, Endra Triwisesa, Octavianto Samir, Gadis Sri Haryani, Hendro Wibowo, Hidayat, Fachmijany Sulawesty, Eva Nafisyah, Lukman, Fauzan Ali | R61: Jurnal | S61: Published | T61: International Journal of Technology | U61: Ya | V61: Q1 | W61: PI | X61: https://ijtech.eng.ui.ac.id/article/view/6525 | Y61: https://doi.org/10.14716/ijtech.v16i4.6525 | AB61: Developing a Visual Dashboard to Improve Research Activity Assessment | AC61: Published | AD61: https://doi.org/10.1109/IC3INA64086.2024.10732819
A62: 57 | B62: =IF(OR(E62<>"",F62<>""),IF(B62="",NOW(),B62),"") -> 45861.388 | E62: From Regulation to Response: Structuring Trust in Government Question Answering through Layout-Aware Retrieval | F62: Pemerintahan Digital (Digital Government) | G62: Nimas Ayu Untariyati, S.Kom, M.T.I | H62: M. Teduh Uliniansyah, B.Eng., M.Sc., Ph.D. | Q62: Achmad Zaki Rahman, Aris Puji Widodo, Kusworo Adi | R62: Jurnal | S62: Under Review | T62: Neural Computing and Applications | U62: Ya | V62: Q1 | W62: PI | AB62: Estimating Software Vulnerabilities from Git Project Open Source: A Machine Learning Approach | AC62: Published | AD62: 10.1109/ICITRI62858.2024.10699087
A63: 58 | B63: =IF(OR(E63<>"",F63<>""),IF(B63="",NOW(),B63),"") -> 45862.653 | C63: Juli | E63: Wood Species Classification Based on Wood Porosity Distribution of Macroscopic Image | F63: Interaksi Manusia-Komputer dan Visualisasi (Human Computer Interaction and Visualisation) | G63: Dr. Esa Prakasa, MT | Q63: Bambang Sugiarto; Norhaida Mohd Suaib; Mohd Shafry Mohd Rahim; Nor Anita Fairos Ismail; Ikmal Faiq Albakri Mustafa Albakri | R63: Prosiding | S63: Published | T63: 2024 IEEE International Symposium on Consumer Technology (ISCT) | U63: Ya | W63: PI | X63: https://www.scopus.com/record/display.uri?eid=2-s2.0-85215306307&origin=recordpage | Y63: http://doi.org/10.1109/ISCT62336.2024.10791236 | Z63: Kegiatan di akhir tahun 2024 | AB63: Segmentation of Libraries, CMS, and PHP Frameworks Based on Code Characteristics: Implementation of Clustering Using K-Means | AC63: Published | AD63: 10.1109/ICITRI62858.2024.10699032
A64: 59 | B64: =IF(OR(E64<>"",F64<>""),IF(B64="",NOW(),B64),"") -> 45864.391 | C64: Juli | E64: Dictionary-based extraction of hyperbole and swear words for sarcasm detection in Indonesian Tweets | F64: Rekayasa Pengetahuan dan Data (Knowledge and Data Engineering) | G64: Siti Kania Kushadiani, S.T., M.Kom. | Q64: Novitasari Arlim, Al Hafiz Akbar Maulana Siagian, Slamet Riyanto, Rodiah, Shidiq Al Hakim, Retno Asihanti Setiorini, Niken Fitria Apriani, Rini Arianty, Diana Tri Susetianingtias | R64: Jurnal | S64: Published | T64: International Journal of Information Technology (Singapore) | U64: Ya | V64: Q1 | W64: PI | X64: https://www.scopus.com/pages/publications/85212466361 | Y64: http://doi.org/10.1007/s41870-024-02361-4 | AB64: Development of Non-Immersive Virtual Reality for Rock Outcrops Learning | AC64: Published | AD64: https://doi.org/10.1109/IC3INA64086.2024.10732232
A65: 60 | B65: =IF(OR(E65<>"",F65<>""),IF(B65="",NOW(),B65),"") -> 45866.423 | C65: Agustus | E65: Performance of CNN and LSTM Model on COVID-19 News Headline Data Classification | F65: Temu Kembali Informasi (Information Retrieval) | G65: Dr. Purnomo Husnul Khotimah, M.T | Q65: Dian Kurniasari, Luthfia Nur Azizah, Warsono | R65: Jurnal | S65: Published | T65: Baghdad Science Journal | U65: Ya | V65: Q2 | W65: PI | X65: https://bsj.uobaghdad.edu.iq/home/vol22/iss7/29/ | Y65: https://doi.org/10.21123/2411-7986.5009 | AB65: Enhancing Waste Management Decisions: A Group DSS Approach Using SSM and AHP in Indonesia | AC65: Published | AD65: https://doi.org/10.28945/5373
A66: 61 | B66: =IF(OR(E66<>"",F66<>""),IF(B66="",NOW(),B66),"") -> 45875.477 | C66: Agustus | E66: Integrating Sentinel-2 and ESA World Cover for Effective Land Use and Land Cover Assessment Using Machine Learning | F66: Pengolahan Bahasa Alami (Natural Language Processing) | G66: Prabu Kresna Putra, S.T., M.T.I. | Q66: Muhammad Iqbal Habibie, Nety Nurda, Doni Fernando, Robby Arifandri, Hari Prayogi, Dionysius Bryan Sencaki | R66: Jurnal | S66: Published | T66: Advances in Space Research | U66: Ya | V66: Q1 | W66: PI | X66: https://www.sciencedirect.com/science/article/pii/S0273117725008385 | Y66: https://doi.org/10.1016/j.asr.2025.07.083 | AB66: Animation tsunami modelling in 3D to determine shelter and evacuation routes | AC66: Published | AD66: https://doi.org/10.1080/17477891.2024.2400140
A67: 62 | B67: =IF(OR(E67<>"",F67<>""),IF(B67="",NOW(),B67),"") -> 45875.477 | C67: Agustus | E67: A simple Contrastive Embedding Framework for Low-resource Fake News Detection | F67: Pengolahan Bahasa Alami (Natural Language Processing) | G67: Iftitahu Ni'mah, S.Kom., M.I.T. | H67: Dr. Rini Wijayanti, S.Kom., M.Kom. | I67: Agung Santosa, BSEE, M.Kom | J67: Dr. Dipl.(FH) Ing Asril, M.Sc | K67: Ir. Tri Sampurno, M.Sc | L67: M. Teduh Uliniansyah, B.Eng., M.Sc., Ph.D. | Q67: Meng Fang, Vlado Menkovski, Mykola Pechenizkiy | R67: Jurnal | S67: Published | T67: Neural Computing and Applications | U67: Ya | V67: Q1 | W67: PI | X67: https://drive.google.com/file/d/14XXmL7aNGpebuUsbPAc-xInEh448J6vf/view?usp=drive_link | Y67: https://doi.org/10.1007/s00521-025-11467-0 | AB67: Improving Software Defect Prediction Performance through Effective Forward Selection Method with Linear Regression for Handling Class Imbalance | AC67: Published | AD67: https://doi.org/10.1109/ICITRI62858.2024.10699214
A68: 63 | B68: =IF(OR(E68<>"",F68<>""),IF(B68="",NOW(),B68),"") -> 45875.617 | C68: Agustus | E68: Big Data Analytics for Uncovering Voxel Connectivity Patterns in Attention Deficit Hyperactivity Disorder | F68: Pemerintahan Digital (Digital Government) | G68: Rezzy Eko Caraka ,S.Si.,M.Sc(RES).,PhD. | Q68: Supardi K, Gio PU, Isnaniawardhani V, Chen RC, Djatmiko B, Pardamean B | R68: Jurnal | S68: Published | T68: Dovepress, Taylor & Francis Group | U68: Ya | W68: PI | X68: https://www.dovepress.com/big-data-analytics-for-uncovering-voxel-connectivity-patterns-in-atten-peer-reviewed-fulltext-article-JMDH | Y68: https://doi.org/10.2147/JMDH.S523137 | AB68: Teleworking and Psychological Well-being: Insights and Applications for TVET Institutions | AC68: Published | AD68: https://doi.org/10.30880/JTET.2024.16.02.002
A69: 64 | B69: =IF(OR(E69<>"",F69<>""),IF(B69="",NOW(),B69),"") -> 45878.505 | C69: Agustus | E69: Strategies for Addressing the Limited Labeled Datasets in Fake News Detection: A Systematic Review | F69: Pengolahan Bahasa Alami (Natural Language Processing) | G69: Yaniasih | H69: Dr. Dipl.(FH) Ing Asril, M.Sc | I69: Ir. Andi Djalal Latief, M.S. | J69: Dian Isnaeni Nurul Afra, S.Kom., M.T.I. | K69: Elvira Nurfadhilah, S.Komp., M. Kom | L69: Nuraisa Novia Hidayati, S.Kom., M.Kom. | M69: Radhiyatul Fajri, S.Kom, M.Pd.T, M.Kom. | N69: Siska Pebiana S.Kom., M.Kom. | O69: Hayuning Titi Karsanti S. Kom., M.Eng | Q69: Siti Saleha | R69: Jurnal | S69: Published | T69: SN Computer Science | U69: Ya | V69: Q2 | W69: PI | X69: https://link.springer.com/article/10.1007/s42979-025-04238-0 | Y69: https://doi.org/10.1007/s42979-025-04238-0 | AB69: Strategic insights for MSMEs: navigating the new normal with big data and business analytics | AC69: Published | AD69: https://doi.org/10.1108/JABS-10-2022-0354
A70: 65 | B70: =IF(OR(E70<>"",F70<>""),IF(B70="",NOW(),B70),"") -> 45881.357 | D70: ☑️ | E70: Strategies for Addressing the Limited Labeled Datasets in Fake News Detection: A Systematic Review | F70: Rekayasa Pengetahuan dan Data (Knowledge and Data Engineering) | G70: Hayuning Titi Karsanti S. Kom., M.Eng | Q70: Gita Citra Puspita, Siti Saleha | R70: Jurnal | S70: Published | T70: SN Computer Science | U70: Ya | V70: Q2 | W70: PI | X70: https://link.springer.com/article/10.1007/s42979-025-04238-0 | Y70: https://doi.org/10.1007/s42979-025-04238-0 | AB70: Geospatial intelligence framework for BTS infrastructure planning toward universal internet access target in Indonesia | AC70: Published | AD70: https://doi.org/10.1016/j.jag.2024.104274
A71: 66 | B71: =IF(OR(E71<>"",F71<>""),IF(B71="",NOW(),B71),"") -> 45894.38 | C71: Agustus | E71: Machine Learning with Self-Assessment Manikin Valence Scale for Fine-Grained Sentiment Analysis | F71: Rekayasa Pengetahuan dan Data (Knowledge and Data Engineering) | G71: Lindung Parningotan Manik, PDEng. | Q71: Harry Susianto, Arawinda Dinakaramani, R. Niken Pramanik, Totok Suhardijanto | R71: Jurnal | S71: Published | T71: Information (Switzerland) | U71: Ya | V71: Q2 | W71: PI | X71: https://www.scopus.com/pages/publications/105011607308 | Y71: https://doi.org/10.3390/info16070562 | AB71: Geographically weighted regression analysis of electricity consumption in Indonesian households: aligning with SDG 7 | AC71: Published | AD71: https://doi.org/10.12928/TELKOMNIKA.v22i6.26051
A72: 67 | B72: =IF(OR(E72<>"",F72<>""),IF(B72="",NOW(),B72),"") -> 45903.445 | C72: Triwulan III | E72: Development of Fish Metabolome Database: Expanding Access and Advancing Management of Metabolite Data Resources | F72: Temu Kembali Informasi (Information Retrieval) | G72: Andre Sihombing, S.Kom., M.Sc. | H72: Dr. DIPL. ING (FH) Anne Parlina, M.P. | Q72: Ira Maryati, Giri Rohmad Brokah, Lia Sadita, Harry B. Santoso | R72: Jurnal | S72: Published | T72: urkish Journal of FISHERIES and AQUATIC SCIENCES | U72: Ya | V72: Q3 | W72: PI | X72: https://www.trjfas.org/abstract.php?lang=en&id=15146 | Y72: https://doi.org/10.4194/TRJFAS26139 | AB72: Challenges and Technology Trends in Implementing a Human Resource Management System: A Systematic Literature Review | AC72: Published | AD72: https://doi.org/10.20473/jisebi.10.3.355-367
A73: 68 | B73: =IF(OR(E73<>"",F73<>""),IF(B73="",NOW(),B73),"") -> 45911.358 | C73: Triwulan III | E73: Lithium-ion battery life prediction using gated convolutional neural network with convolutional block attention module | F73: Temu Kembali Informasi (Information Retrieval) | G73: Andri Fachrur Rozie, M. Eng. | Q73: Ade Ramdan Vicky Zilvan, Asri Rizki Yuliani, Hilman F. Pardede, Endang Suryawati, Candra Nur Ihsan, Sandra Yuwana R. Bambang Sugiarto, | R73: Jurnal | S73: Published | T73: Journal of King Saud University - Engineering Sciences | U73: Ya | V73: Q1 | W73: PI | X73: https://www.scopus.com/pages/publications/105015439698?origin=resultslist | Y73: https://doi.org/10.1007/s44444-025-00035-5 | AB73: XoT (Xducation of Things): Harnessing AI and edge computing to educate all things | AC73: Published | AD73: https://doi.org/10.1109/ACCESS.2024.3474015
A74: 69 | B74: =IF(OR(E74<>"",F74<>""),IF(B74="",NOW(),B74),"") -> 45916.447 | E74: Maize Breeding for Drought Tolerance: A Bibliometric Analysis of 54 Years of Research | F74: Interaksi Manusia-Komputer dan Visualisasi (Human Computer Interaction and Visualisation) | G74: Abdurrakhman Prasetyadi, M.P | Q74: Sutrisno | R74: Jurnal | S74: Submit | T74: Discover Applied Science: Springer Nature | U74: Ya | V74: Q1 | W74: PI | AB74: Indonesian Sign Language (BISINDO) Alphabet Detection Using the You Only Look Once (YOLO) Algorithm Version 8 | AC74: Published | AD74: https://doi.org/10.1109/IC3INA64086.2024.10732209
A75: 70 | B75: =IF(OR(E75<>"",F75<>""),IF(B75="",NOW(),B75),"") -> 45922.447 | D75: ☑️ | E75: Lithium-ion battery life prediction using gated convolutional neural network with convolutional block attention module | F75: Interaksi Manusia-Komputer dan Visualisasi (Human Computer Interaction and Visualisation) | G75: Prof. Dr. Ana Hadiana, M.Eng.Sc. | Q75: Ade Ramdan Vicky Zilvan, Asri Rizki Yuliani, Hilman F. Pardede, Endang Suryawati, Candra Nur Ihsan, Sandra Yuwana R. Bambang Sugiarto, | R75: Jurnal | S75: Published | T75: Journal of King Saud University - Engineering Sciences | U75: Ya | V75: Q1 | W75: PI | X75: https://www.scopus.com/pages/publications/105015439698?origin=resultslist | Y75: https://doi.org/10.1007/s44444-025-00035-5 | AB75: Comparative Performance of Water Index for Water Segmentation Model Using U-Net Architecture | AC75: Published | AD75: https://doi.org/10.1109/IC3INA64086.2024.10732848
A76: 71 | B76: =IF(OR(E76<>"",F76<>""),IF(B76="",NOW(),B76),"") -> 45922.852 | C76: Triwulan III | E76: Malaria risk assessment in Indonesia: a machine and deep learning framework | F76: Pemerintahan Digital (Digital Government) | G76: Rezzy Eko Caraka ,S.Si.,M.Sc(RES).,PhD. | Q76: Anjar Dimara Sakti, Jasmine Nur Mahdani, Hubbi Nashrullah Muhammad, Elstri Sihotang, Cokro Santoso, Khairunnisah Afina Nur Fauziyyah Fedri Ruluwedrata Rinawan, Khairunnisa Supardi | R76: Jurnal | S76: Published | T76: International Journal of Applied Earth Observation and Geoinformation | U76: Ya | V76: Q1 | W76: PI | X76: https://www.scopus.com/pages/publications/105014811615?origin=resultslist | Y76: https://doi.org/10.1016/j.jag.2025.104793 | AB76: Ensuring Trustworthiness in Qualitative Research: The Role of Triangulation Techniques | AC76: Published | AD76: https://doi.org/10.4018/979-8-3693-3069-2.ch012
A77: 72 | B77: =IF(OR(E77<>"",F77<>""),IF(B77="",NOW(),B77),"") -> 45925.331 | E77: A Domain-Specific Retrieval-Augmented Generation Chatbot for Medical Queries on Adenomyosis and Endometriosis | F77: Pengolahan Bahasa Alami (Natural Language Processing) | G77: Nuraisa Novia Hidayati, S.Kom., M.Kom. | Q77: Luthfi Atikah | R77: Prosiding | S77: Accepted | T77: International Conference on Computer, Control, Informatics and its Applications, IC3INA 2025 | W77: PI | AB77: Multi-Temporal Cloud Removal of Satellite Image for Surface Water Segmentation | AC77: Published | AD77: https://doi.org/10.1109/IC3INA64086.2024.10732147
A78: 73 | B78: =IF(OR(E78<>"",F78<>""),IF(B78="",NOW(),B78),"") -> 45925.345 | E78: Spatio-Temporal Analysis of Environmental Influence Toward ARI Cases Spread in West Java Using INLA | F78: Temu Kembali Informasi (Information Retrieval) | G78: Irfan Asfy Fakhry Anto S.Kom., M.T | H78: Dr. Purnomo Husnul Khotimah, M.T | I78: Ir. Dianadewi Riswantini, M. Sc., M.B.A. | Q78: Melati Janet Livia Simanjuntat,Muhamad Syazali, Rifani Bhakti Natari, Noersomadi | R78: Prosiding | S78: Accepted | T78: International Conference on Computer, Control, Informatics and its Applications, IC3INA 2025 | W78: PI | X78: https://drive.google.com/file/d/1onfgUfcNhFiPmGmol8YhY4Y5QJDi2e5y/view?usp=drive_link | AB78: Exploring the evolution of data management in E-government: bibliometric analysis | AC78: Published | AD78: https://doi.org/10.1109/IC3INA64086.2024.10732787
A79: 74 | B79: =IF(OR(E79<>"",F79<>""),IF(B79="",NOW(),B79),"") -> 45943.767 | E79: Retrieval-Augmented Large Language Models for a Chronic Kidney Disease Patient Education Chatbot | F79: Pengolahan Bahasa Alami (Natural Language Processing) | G79: Elvira Nurfadhilah, S.Komp., M. Kom | H79: Agung Santosa, BSEE, M.Kom | I79: Prabu Kresna Putra, S.T., M.T.I. | R79: Prosiding | S79: Accepted | T79: International Conference on Computer, Control, Informatics and its Applications, IC3INA 2025 | W79: PI | AB79: Assessment of Hyperparameter Optimization Techniques for Cross-Stitched Multi-Task Learning | AC79: Published | AD79: https://doi.org/10.1109/IC3INA64086.2024.10732471
A80: 75 | B80: =IF(OR(E80<>"",F80<>""),IF(B80="",NOW(),B80),"") -> 45943.769 | E80: Towards a Safe and Trustworthy LLM-RAG Chatbot for Hemodialysis Patient Education: Design, Implementation, and Preliminary Evaluation | F80: Pengolahan Bahasa Alami (Natural Language Processing) | G80: Prabu Kresna Putra, S.T., M.T.I. | H80: Elvira Nurfadhilah, S.Komp., M. Kom | I80: Siska Pebiana S.Kom., M.Kom. | R80: Prosiding | S80: Accepted | T80: International Conference on Computer, Control, Informatics and its Applications, IC3INA 2025 | W80: PI | AB80: Enhancing OCR Accuracy for Bugis Language to Bahasa Indonesia Dictionary Conversion Through Image Pre-Processing and Scaling Techniques | AC80: Published | AD80: https://doi.org/10.1109/IC3INA64086.2024.10732090
A81: 76 | B81: =IF(OR(E81<>"",F81<>""),IF(B81="",NOW(),B81),"") -> 45943.769 | D81: ☑️ | E81: Towards a Safe and Trustworthy LLM-RAG Chatbot for Hemodialysis Patient Education: Design, Implementation, and Preliminary Evaluation | F81: Interaksi Manusia-Komputer dan Visualisasi (Human Computer Interaction and Visualisation) | G81: Dr. Esa Prakasa, MT | R81: Prosiding | S81: Accepted | T81: International Conference on Computer, Control, Informatics and its Applications, IC3INA 2025 | W81: PI | AB81: Artificial Intelligence Technologies in Mental Health: Transforming Depression Care through Innovation | AC81: Published | AD81: https://doi.org/10.4018/979-8-3693-7011-7
A82: 77 | B82: =IF(OR(E82<>"",F82<>""),IF(B82="",NOW(),B82),"") -> 45953.266 | E82: Support Vector Machine Performance: Simulation and Rice Phenology Application | F82: Pemerintahan Digital (Digital Government) | G82: Hengki Muradi, M.Si. | Q82: Asep Saefuddin, I Made Sumertajaya, Agus Mohamad Soleh, Dede Dirgahayu Domiri | R82: Jurnal | S82: Accepted | T82: Jurnal IAES International Journal of Artificial Intelegence | U82: Ya | V82: Q2 | W82: PI | AB82: Evaluation of the Quality of ChatGPT in Translating Texts on Indonesian War of Independence From Dutch to Indonesian | AC82: Published | AD82: https://doi.org/10.1109/IC3INA64086.2024.10732746
A83: 78 | B83: =IF(OR(E83<>"",F83<>""),IF(B83="",NOW(),B83),"") -> 45953.321 | E83: SKV-Cache: A Topology-Aware Cache Framework for Efficient Question Answering over Governmental Archival KGs | F83: Pemerintahan Digital (Digital Government) | G83: Nimas Ayu Untariyati, S.Kom, M.T.I | H83: M. Teduh Uliniansyah, B.Eng., M.Sc., Ph.D. | Q83: Prof. Dr. Kusworo Adi, S.Si., M.T., Dr. Aris Puji Widodo, S.Si., M.T. | R83: Prosiding | S83: Accepted | T83: International Conference on Computer, Control, Informatics and its Applications, IC3INA 2025 | U83: Ya | W83: PI | AB83: The Development of the Mobile Interactive Virtual Nuclear Educator With AR and RAG for Learning Nuclear Energy in Indonesia | AC83: Published | AD83: https://doi.org/10.1109/IC3INA64086.2024.10732800
A84: 79 | B84: =IF(OR(E84<>"",F84<>""),IF(B84="",NOW(),B84),"") -> 45953.408 | E84: Bridging Information Science and Data Science: The Strategic Role of Informetrics in the Era of Big Data and Open Science | F84: Pemerintahan Digital (Digital Government) | G84: Dr. Eng. Budi Nugroho | H84: Dr. Ambar Yoganingrum | I84: Yaniasih | J84: Dr. Ekawati Marlina, S.T., M.T. | K84: Ira Maryati | L84: Abdurrakhman Prasetyadi, M.P | M84: Rumadi, S.T., M.T. | N84: Aria Bisri, S.Kom. M.T. | R84: Prosiding | S84: Accepted | T84: International Conference on Computer, Control, Informatics and its Applications, IC3INA 2025 | W84: PI | AB84: Development of a Mental Health Chatbot Using Large Language Models for Indonesian Undergraduates | AC84: Published | AD84: https://doi.org/10.1109/IC3INA64086.2024.10732708
A85: 80 | B85: =IF(OR(E85<>"",F85<>""),IF(B85="",NOW(),B85),"") -> 45953.408 | E85: Integration of Big Data, Dynamic Systems, and Artificial Intelligence in Local Government Decision Making: A Systematic Literature Review | F85: Pemerintahan Digital (Digital Government) | G85: Dr. Eng. Budi Nugroho | Q85: Sumirah, Adi Wibowo | R85: Prosiding | S85: Accepted | T85: International Conference on Computer, Control, Informatics and its Applications, IC3INA 2025 | U85: Ya | W85: PI | AB85: Enhanced U-Net models with encoder and augmentation for phytoplankton segmentation | AC85: Published | AD85: https://doi.org/10.11591/ijaas.v13.i4.pp1009-1018
A86: 81 | B86: =IF(OR(E86<>"",F86<>""),IF(B86="",NOW(),B86),"") -> 45953.408 | E86: Village Website Content Analysis as an Indicator of Government Digital Readiness: An Informetric Study in West Lombok Regency | F86: Pemerintahan Digital (Digital Government) | G86: Dr. Eng. Budi Nugroho | H86: Dra. Andrari Grahitandaru, M.Sc. | Q86: Sumirah, Adi Wibowo | R86: Prosiding | S86: Accepted | T86: International Conference on Smart-Green Technology in Electrical and Information Systems | U86: Ya | W86: PI | AB86: Spatial Analysis of Drought Vulnerability Related to Climate Change and Under Five Children’s Nutritional Status | AC86: Published | AD86: https://doi.org/10.1051/bioconf/202413300019
A87: 82 | B87: =IF(OR(E87<>"",F87<>""),IF(B87="",NOW(),B87),"") -> 45953.408 | E87: A Review of Technology Evolution and Risk of Autonomous Vehicles | F87: Pemerintahan Digital (Digital Government) | G87: Dr. Eng. Budi Nugroho | H87: Abdurrakhman Prasetyadi, M.P | I87: M. Yudhi Rezaldi, Ph.D | Q87: Cahyo Trianggoro, Rabiah Abdul Kadir | R87: Jurnal | S87: Accepted | T87: Indonesian Journal of Electrical Engineering and Computer Science | U87: Ya | W87: PI | AB87: Climate Change and Rural Development: A Bibliometric Review | AC87: Published | AD87: https://doi/org/10.1051/bioconf/202413402006
A88: 83 | B88: =IF(OR(E88<>"",F88<>""),IF(B88="",NOW(),B88),"") -> 45953.429 | E88: Artificial Intelligence Technology Approach in Nudging Strategies: A Bibliometric Analysis | F88: Pemerintahan Digital (Digital Government) | G88: Dr. Ekawati Marlina, S.T., M.T. | H88: Ira Maryati | Q88: Winda Anestya Ayunda, Shidiq Al Hakim, Al Hafiz Akbar Maulana Siagian, Mirna Rahmadina Gumati, Marudur Pandapotan Damanik, Danarsiwi Tri Lastiwi | R88: Prosiding | S88: Accepted | T88: International Conference on Computer, Control, Informatics and its Applications, IC3INA 2025 | U88: Ya | W88: PI | AB88: Exploiting the leading potential of Indonesia through strategic alliances with the G20 and SDG-aligned policy making | AC88: Published | AD88: https://doi.org/10.15196/RS140502
A89: 84 | B89: =IF(OR(E89<>"",F89<>""),IF(B89="",NOW(),B89),"") -> 45953.482 | E89: Non-Invasive Asthma Detection with FMCW Radar: An Imbalanced Learning Approach | F89: Pengolahan Bahasa Alami (Natural Language Processing) | G89: Dr. Kokoy Siti Komariah S.Kom., M.T., M.Eng. | Q89: Ariana Tulus Purnomo, Ding-Bing Lin, Dian Nurdiana, Bong-Kee Sin | R89: Prosiding | S89: Accepted | T89: International Conference on Computer, Control, Informatics and its Applications, IC3INA 2025 | U89: Ya | W89: PI | AB89: User Emotion in Website Design: A Kansei Analysis Approach | AC89: Published | AD89: https://doi.org/10.1109/ICISS62896.2024.10751252
A90: 85 | B90: =IF(OR(E90<>"",F90<>""),IF(B90="",NOW(),B90),"") -> 45953.526 | E90: Evaluating Generative Fusion Decoding for Indonesian Automatic Speech Recognition | F90: Pengolahan Bahasa Alami (Natural Language Processing) | G90: Dr. Dipl.(FH) Ing Asril, M.Sc | H90: Agung Santosa, BSEE, M.Kom | R90: Prosiding | S90: Accepted | T90: International Conference on Computer, Control, Informatics and its Applications, IC3INA 2025 | U90: Ya | W90: PI | AB90: Optical properties of Eu3+/Dy3+ ion co-doped TeO2 - B2O3 - CaO - Al2O3 glass and its potential for solar energy harvesting | AC90: Published | AD90: http://doi.org/10.1016/j.optmat.2024.115070 | AE90: PRE
A91: 86 | B91: =IF(OR(E91<>"",F91<>""),IF(B91="",NOW(),B91),"") -> 45953.535 | E91: Design and Implementation of GeoMIMO: A Geoinformatic Data Platform for Multi Inputs and Multi Outputs | F91: Temu Kembali Informasi (Information Retrieval) | G91: Andria Arisal, M. Eng. | H91: Andri Fachrur Rozie, M. Eng. | I91: Andre Sihombing, S.Kom., M.Sc. | J91: Dr. Esa Prakasa, MT | Q91: Ahmad Sutanto, Andy Indradjad, Dede D. Domiri, Emiyati, Hastuadi Harsa, M. Rokhis Khomarudi, Muh. Hafizh Izzaturrahim, Muhammad Hanif Muslim , Nurmajid Setyasaputra, Rifki Sadikin, Rubini Jusuf, Silvan A. B. S. Permana, Sjaeful Afandi, Zaenal Akbar | R91: Prosiding | S91: Accepted | T91: International Conference on Computer, Control, Informatics and its Applications, IC3INA 2025 | U91: Ya | W91: PI | AB91: A comprehensive study on transparent conducting oxides in compact microbial fuel cells: Integrated spectroscopic and electrochemical analyses for monitoring biofilm growth | AC91: Published | AD91: https://doi.org/10.1016/j.bios.2024.116067
A92: 87 | B92: =IF(OR(E92<>"",F92<>""),IF(B92="",NOW(),B92),"") -> 45953.539 | E92: Design and Evaluation of an ELK Stack-Based Monitoring Framework for Resource Optimization in National HPC Infrastructure | F92: Temu Kembali Informasi (Information Retrieval) | G92: Andria Arisal, M. Eng. | Q92: Fatima Khairunnisa, Yan Mareden, Suharyo Sumowidagdo | R92: Prosiding | S92: Accepted | T92: International Conference on Computer, Control, Informatics and its Applications, IC3INA 2025 | U92: Ya | W92: PI | AB92: Electrical impedance spectroscopy for skin layer assessment: A scoping review of electrode design, measurement methods, and post-processing techniques | AC92: Published | AD92: https://doi.org/10.1016/j.measurement.2023.114111
A93: 88 | B93: =IF(OR(E93<>"",F93<>""),IF(B93="",NOW(),B93),"") -> 45953.854 | E93: Modelling Process Mining Benefits: A context of Indonesia and Australia | F93: Temu Kembali Informasi (Information Retrieval) | G93: Nungki Dian Sulistyo Darmayanti | Q93: Abel Armas Cervantes, Sherah Kurnia, Arti Dian Nastiti, Ainun Herlambang | R93: Prosiding | S93: Accepted | T93: International Conference on Computer, Control, Informatics and its Applications, IC3INA 2025 | U93: Ya | W93: PI | AB93: Challenges of using natural extracts as green reducing agents in the synthesis of rGO: A brief review | AC93: Published | AD93: http://doi.org/10.1016/j.rechem.2023.101270
A94: 89 | B94: =IF(OR(E94<>"",F94<>""),IF(B94="",NOW(),B94),"") -> 45953.864 | E94: Transformer Based Hybridization Text Classifiers In Online Gambling Spam Identification Case Study | F94: Temu Kembali Informasi (Information Retrieval) | H94: Dr. Purnomo Husnul Khotimah, M.T | I94: Nungki Dian Sulistyo Darmayanti | Q94: Muh. Hafizh Izzaturrahim | R94: Prosiding | S94: Accepted | T94: International Conference on Computer, Control, Informatics and its Applications, IC3INA 2025 | U94: Ya | W94: PI | AB94: Improved efficiency and stability of dye-sensitized solar cells by using iodide-based electrolyte with high viscosity solvent | AC94: Published | AD94: https://doi.org/10.1016/j.matlet.2023.135847
A95: 90 | B95: =IF(OR(E95<>"",F95<>""),IF(B95="",NOW(),B95),"") -> 45953.865 | E95: Who is My Audience? Discovering Student Personas from LMS Data | F95: Temu Kembali Informasi (Information Retrieval) | G95: Nungki Dian Sulistyo Darmayanti | Q95: Ainun Herlambang, Abel Armas Cervantez, Antonette Mendoza | R95: Prosiding | S95: Accepted | T95: 36th Australasian Association for Engineering Education Annual Conference , Brisbane, 7 – 10 December 2025. | U95: Ya | W95: PI | AB95: Improved performance of protected CuO photocathodes evaluated by photoelectrochemical characterizations using hydrogen peroxide | AC95: Published | AD95: http://doi.org/10.1016/j.matlet.2023.135735
A96: 91 | B96: =IF(OR(E96<>"",F96<>""),IF(B96="",NOW(),B96),"") -> 45954.454 | E96: Gamification System for Enhancing Personal Mobility Vehicle Driving Test Through Virtual Reality | F96: Interaksi Manusia-Komputer dan Visualisasi (Human Computer Interaction and Visualisation) | G96: Abdurrakhman Prasetyadi, M.P | H96: Aria Bisri, S.Kom. M.T. | Q96: Roni Permana Saputra | R96: Prosiding | S96: Accepted | T96: International Conference on Computer, Control, Informatics and its Applications, IC3INA 2025 | U96: Ya | W96: PI | AB96: One-Dimensional HKUST-1-Decorated Glassy Carbon Electrode for the Sensitive Electrochemical Immunosensor of NS1 Dengue Virus Serotype‑3 | AC96: Published | AD96: https://doi.org/10.1021/acsomega.3c07856
A97: 92 | B97: =IF(OR(E97<>"",F97<>""),IF(B97="",NOW(),B97),"") -> 45955.864 | C97: Oktober | E97: Expertise Retrieval Using Adjusted TF-IDF and Keyword Mapping to ACM Classification Terms | F97: Pengolahan Bahasa Alami (Natural Language Processing) | G97: Lyla Ruslana Aini | Q97: Evi Yulianti | R97: Jurnal | S97: Published | T97: Jurnal RESTI | U97: Ya | V97: Q3 | W97: PI | X97: https://www.scopus.com/pages/publications/105010384373?origin=resultslist | Y97: https://doi.org/10.29207/resti.v9i3.6397 | AB97: Enhancing urine glucose sensing performance through the introduction of two dimensional-transition metal dichalcogenides and gold nanoparticles into silver/UiO-66 chip of surface plasmon resonance | AC97: Published | AD97: http://doi.org/10.1088/1361-6528/ad12ed
A98: 93 | B98: =IF(OR(E98<>"",F98<>""),IF(B98="",NOW(),B98),"") -> 45961.748 | C98: November | E98: Rapid determination of daily ionospheric F-layer critical frequency value using a quick-scale method based on Frequency-Time-Intensity plots | F98: Rekayasa Pengetahuan dan Data (Knowledge and Data Engineering) | G98: Satrio Adi Priyambada, S.Kom., M.Kom., Ph.D. | Q98: Varuliantor Dear, Jiyo Harjosuwito, Annis Siradj Mardiani, Adi Purwono, Afrizal Bahar, Indah Susanti, Rezy Pradipta | R98: Jurnal | S98: Published | T98: Journal of Atmospheric and Solar-Terrestrial Physics | U98: Ya | V98: Q2 | W98: PI | X98: https://www.sciencedirect.com/science/article/pii/S136468262500255X | Y98: https://doi.org/10.1016/j.jastp.2025.106671 | AB98: Label-free and early detection of HER2 breast cancer biomaker based on UiO-66-NH2 modified gold chip (Au/UiO-66-NH2) using surface plasmon resonance technique | AC98: Published | AD98: https://doi.org/10.1016/j.microc.2024.109963
A99: 94 | B99: =IF(OR(E99<>"",F99<>""),IF(B99="",NOW(),B99),"") -> 45965.414 | E99: Explaining Mental Disorder Classification in Dialogues: Turn-Level Analysis and Label Dynamics | F99: Pengolahan Bahasa Alami (Natural Language Processing) | G99: Dr. Rini Wijayanti, S.Kom., M.Kom. | H99: Iftitahu Ni'mah, S.Kom., M.I.T. | I99: Ekasari Nugraheni, M.T. | Q99: Ana Heryana | R99: Prosiding | S99: Accepted | T99: International Conference on Computer, Control, Informatics and its Applications, IC3INA 2025 | U99: Ya | W99: PI | AB99: Synthesis and Characterization of ZIF 67 Manganese Bimetal for Electrochemical Sensor Application | AC99: Published | AD99: http://doi.org/10.1088/1742-6596/2705/1/012007
A100: 95 | B100: =IF(OR(E100<>"",F100<>""),IF(B100="",NOW(),B100),"") -> 45967.507 | D100: ☑️ | E100: Exploring the influence of soft information from economic news on exchange rate and gold price movements | F100: Rekayasa Pengetahuan dan Data (Knowledge and Data Engineering) | G100: Rahardito Dio Prastowo, S.T. | H100: Prabu Kresna Putra, S.T., M.T.I. | Q100: Indra Budi, Amanah Ramadiah, Aris Budi Santoso | R100: Jurnal | S100: Accepted | T100: IAES International Journal of Artificial Intelligence (IJ-AI) | U100: Ya | V100: Q2 | W100: PI | X100: https://drive.google.com/file/d/1-hImjNbN26mOa7qGhYYOfR-FaMijCTvX/view?usp=sharing | Y100: http://doi.org/10.11591/ijai.v14.i6.pp5231-5239 | AB100: The Impact of Export on the Development of Green Industries for Sustainability in DI Yogyakarta Region, Indonesia: an Extended Input-Output Analysis | AC100: Published | AD100: http://doi.org/10.15244/pjoes/174400
A101: 96 | B101: =IF(OR(E101<>"",F101<>""),IF(B101="",NOW(),B101),"") -> 45967.507 | D101: ☑️ | E101: Participatory Human-AI Mechanisms for Multi-Taxon Citizen Science Biodiversity Platforms: Architectural Design and Data Quality Management | F101: Rekayasa Pengetahuan dan Data (Knowledge and Data Engineering) | G101: Rahardito Dio Prastowo, S.T. | H101: Lindung Parningotan Manik, PDEng. | I101: Siti Kania Kushadiani, S.T., M.Kom. | J101: Satrio Adi Priyambada, S.Kom., M.Kom., Ph.D. | K101: Muhamad Jafar Elly | L101: Ariani Indrawati, M.TI | R101: Prosiding | S101: Accepted | T101: International Conference on Emerging Trends in Information Systems and Informatics (ICETISI 2025) | U101: Ya | W101: PI | X101: https://drive.google.com/file/d/1DPe5Il-ryR7TGw8TWDvgs_4QiECrsXDZ/view?usp=sharing | AB101: Pyrolysis process control: temperature control design and application for optimum process operation | AC101: Published | AD101: https://ijece.iaescore.com/index.php/IJECE/article/view/34009/17222
A102: 97 | B102: =IF(OR(E102<>"",F102<>""),IF(B102="",NOW(),B102),"") -> 45973.497 | E102: Evaluating Retrieval Augmented Generation (RAG) Chunking Strategy for Question Answering in Indonesian Law of The Sea | F102: Pengolahan Bahasa Alami (Natural Language Processing) | G102: Iftitahu Ni'mah, S.Kom., M.I.T. | H102: Lyla Ruslana Aini | I102: Radhiyatul Fajri, S.Kom, M.Pd.T, M.Kom. | J102: Siska Pebiana S.Kom., M.Kom. | K102: Nuraisa Novia Hidayati, S.Kom., M.Kom. | L102: Dr. Rini Wijayanti, S.Kom., M.Kom. | R102: Prosiding | S102: Accepted | T102: International Conference on Computer, Control, Informatics and its Applications, IC3INA 2025 | U102: Ya | W102: PI | AB102: Machine Learning Model and Molecular Docking for Screening Medicinal Plants as HIV-1 Reverse Transcriptase Inhibitors | AC102: Published | AD102: http://doi.org/10.33640/2405-609X.3341
...

Sheet PWRP
A1: PURWARUPA
A4: DIISI OLEH PJ MONEV | E4: PUSAT RISET SAINS DATA DAN INFORMASI | G4: SIVITAS PRSDI
A5: NO | B5: Periode Input | C5: Periode Stamp | E5: JUDUL | F5: KELOMPOK RISET | G5: 1 | H5: 2 | I5: 3 | J5: 4 | K5: 5 | L5: 6 | M5: 7 | N5: 8 | O5: 9 | P5: 10 | Q5: NON SIVITAS PRSDI | R5: JENIS | S5: STATUS | T5: MEMILIKI MITRA ? | U5: NAMA MITRA | V5: No KI yang termanfaatkan dalam Lisensi | W5: UPLOAD GDRIVE | X5: CATATAN | Y5: Evidence bisa dalam bentuk Dokumentasi, perjanjian lisensi, dokumen sertifikan/terdaftar di DJKI
A6: 1 | B6: =IF(OR(E6<>"",F6<>""),IF(B6="",NOW(),B6),"") -> 45735.472 | E6: Digital Twin untuk Analisis Risiko Banjir Kota Bandung | F6: Interaksi Manusia-Komputer dan Visualisasi (Human Computer Interaction and Visualisation) | G6: Abdurrakhman Prasetyadi, M.P | H6: Prof. Dr. Ana Hadiana, M.Eng.Sc. | I6: Dr. Esa Prakasa, MT | J6: M. Yudhi Rezaldi, Ph.D | K6: Dr. Ambar Yoganingrum | L6: Arafat Febriandirza, Ph.D | M6: Aria Bisri, S.Kom. M.T. | N6: Rio Nurtantyana, S.Pd., M.Pd., M.Sc., Ph.D. | O6: Rumadi, S.T., M.T. | P6: Christine Cecylia Munthe, S.Kom. | Q6: Dr. Ary Setijadi Prihatmanto, Prof. Ridwan Sutriadi (ITB), Ai Sulastri (UPI) | R6: Software Prototype | S6: Skala Uji Lab | T6: Belum | W6: PWRP
A7: 2 | B7: =IF(OR(E7<>"",F7<>""),IF(B7="",NOW(),B7),"") -> 45874.616 | E7: Hak Cipta Program Komputer : Aplikasi Pemilu Elektronik (e-Voting) (000535510) | F7: Pemerintahan Digital (Digital Government) | G7: Dra. Andrari Grahitandaru, M.Sc. | H7: Drs. Zain Saifullah, M.Sc. | I7: Ir. Gunarso | S7: Lisensi | T7: Sudah | U7: PT. Inti Konten Indonesia (INTENS) | W7: PWRP
A8: 3 | B8: =IF(OR(E8<>"",F8<>""),IF(B8="",NOW(),B8),"") -> 45998.454 | C8: Triwulan IV | E8: Sistem Big Data Bahasa dan Sastra Lisan Perbatasan (BAHASAN) | F8: Rekayasa Pengetahuan dan Data (Knowledge and Data Engineering) | G8: Dr. Foni Agus Setiawan, M.Kom. | R8: Software Prototype | S8: Lisensi | T8: Sudah | U8: STKIP Persada Khatulistiwa, Sintang | V8: EC002025055955 | W8: PWRP
A9: 4 | B9: =IF(OR(E9<>"",F9<>""),IF(B9="",NOW(),B9),"") -> 45999.676 | E9: BugisLingua - Sistem Terjemahan Bahasa Bugis | F9: Pengolahan Bahasa Alami (Natural Language Processing) | G9: Dr. Eng. Ir Yuyun, S.Kom., M.T | H9: Agung Santosa, BSEE, M.Kom | I9: Lyla Ruslana Aini | J9: Ir. Andi Djalal Latief, M.S. | K9: Ir. Gunarso | L9: Siska Pebiana S.Kom., M.Kom. | M9: Radhiyatul Fajri, S.Kom, M.Pd.T, M.Kom. | N9: Nuryani | O9: Elvira Nurfadhilah, S.Komp., M. Kom | P9: M. Teduh Uliniansyah, B.Eng., M.Sc., Ph.D. | Q9: Gusnawaty, Hazriani, Pammuda | R9: Software Prototype | S9: Skala Uji Lab | T9: Sudah | U9: Fakultas Ilmu Budaya Univ. Hasanuddin | W9: PWRP | X9: Mohon evidence nomor HKI
A10: 5 | B10: =IF(OR(E10<>"",F10<>""),IF(B10="",NOW(),B10),"") -> 45999.682 | E10: Alat bantu pemeriksaan hasil rekam ujaran Bahasa Bugis | F10: Pengolahan Bahasa Alami (Natural Language Processing) | G10: Agung Santosa, BSEE, M.Kom | H10: Dr. Eng. Ir Yuyun, S.Kom., M.T | I10: Lyla Ruslana Aini | J10: Ir. Andi Djalal Latief, M.S. | K10: Ir. Gunarso | L10: Siska Pebiana S.Kom., M.Kom. | M10: Radhiyatul Fajri, S.Kom, M.Pd.T, M.Kom. | N10: Nuryani | O10: Elvira Nurfadhilah, S.Komp., M. Kom | P10: M. Teduh Uliniansyah, B.Eng., M.Sc., Ph.D. | Q10: Gusnawaty, Hazriani, Pammuda | S10: Skala Uji Lab | T10: Sudah | U10: Fakultas Ilmu Budaya Univ. Hasanuddin | W10: PWRP | X10: Mohon evidence nomor HKI
A11: 6 | B11: =IF(OR(E11<>"",F11<>""),IF(B11="",NOW(),B11),"") -> 46001.642 | C11: Triwulan IV | E11: Hak Cipta INACOVED (Dataset) | F11: Temu Kembali Informasi (Information Retrieval) | G11: Dr. Purnomo Husnul Khotimah, M.T | H11: Andri Fachrur Rozie, M. Eng. | I11: Andria Arisal, M. Eng. | J11: Ekasari Nugraheni, M.T. | K11: Ir. Dianadewi Riswantini, M. Sc., M.B.A. | L11: Dr. Wiwin Suwarningsih, M.T. | S11: Lisensi | T11: Sudah | U11: FMIPA Universitas Lampung | V11: EC002023112261 | W11: PWRP
A12: 7 | B12: =IF(OR(E12<>"",F12<>""),IF(B12="",NOW(),B12),"") -> 46001.642 | C12: Triwulan IV | E12: Hak Cipta Bangkit-TS (Program Komputer) | F12: Temu Kembali Informasi (Information Retrieval) | G12: Dr. Purnomo Husnul Khotimah, M.T | H12: Andri Fachrur Rozie, M. Eng. | I12: Andria Arisal, M. Eng. | Q12: Febi Siti Sutria Ningsih, Dian Kurniasari, Warsono | R12: Software Prototype | S12: Lisensi | T12: Sudah | U12: FMIPA Universitas Lampung | V12: EC002022107186 | W12: PWRP
A13: 8 | B13: =IF(OR(E13<>"",F13<>""),IF(B13="",NOW(),B13),"") | W13: PWRP
A14: 9 | B14: =IF(OR(E14<>"",F14<>""),IF(B14="",NOW(),B14),"") | W14: PWRP
A15: 10 | B15: =IF(OR(E15<>"",F15<>""),IF(B15="",NOW(),B15),"") | W15: PWRP
A16: 11 | B16: =IF(OR(E16<>"",F16<>""),IF(B16="",NOW(),B16),"") | W16: PWRP
A17: 12 | B17: =IF(OR(E17<>"",F17<>""),IF(B17="",NOW(),B17),"") | W17: PWRP
A18: 13 | B18: =IF(OR(E18<>"",F18<>""),IF(B18="",NOW(),B18),"") | W18: PWRP
A19: 14 | B19: =IF(OR(E19<>"",F19<>""),IF(B19="",NOW(),B19),"") | W19: PWRP
A20: 15 | B20: =IF(OR(E20<>"",F20<>""),IF(B20="",NOW(),B20),"") | W20: PWRP
A21: 16 | B21: =IF(OR(E21<>"",F21<>""),IF(B21="",NOW(),B21),"") | W21: PWRP
A22: 17 | B22: =IF(OR(E22<>"",F22<>""),IF(B22="",NOW(),B22),"") | W22: PWRP
A23: 18 | B23: =IF(OR(E23<>"",F23<>""),IF(B23="",NOW(),B23),"") | W23: PWRP
A24: 19 | B24: =IF(OR(E24<>"",F24<>""),IF(B24="",NOW(),B24),"") | W24: PWRP
... A53: 48 | B53: =IF(OR(E53<>"",F53<>""),IF(B53="",NOW(),B53),"") | W53: PWRP

Sheet Dana Eks + PKS
A3: DIISI OLEH PJ MONEV | E3: PUSAT RISET SAINS DATA DAN INFORMASI | G3: PIC/KORD KEGIATAN (SIVITAS PRSDI) | Y3: KERJA SAMA | AA3: PERJANJIAN | AC3: EVIDEN/DAKUNG
A4: NO | B4: Periode Input | C4: Periode Stamp | E4: JUDUL | F4: KELOMPOK RISET | G4: 1 | H4: 2 | I4: 3 | J4: 4 | K4: 5 | L4: 6 | M4: 7 | N4: 8 | O4: 9 | P4: 10 | Q4: NON SIVITAS PRSDI | R4: TIPE | S4: JENIS | T4: SUMBER | U4: OUTPUT | V4: PIHAK K3 | W4: NILAI | X4: KETERANGAN | Y4: NO KERJASAMA | Z4: TANGGAL KERJASAMA | AA4: NO PERJANJIAN | AB4: TANGGAL PERJANJIAN | AC4: LINK UPLOAD | AD4: STATUS UPLOAD | AE4: TAHUN PKS | AF4: NO KI YANG TERMANFAATKAN | AG4: LINK BUKTI DUKUNG | AH4: CATATAN
A5: 1 | B5: =IF(OR(E5<>"",F5<>""),IF(B5="",NOW(),B5),"") -> 45722.426 | C5: Triwulan I | E5: Pengembangan Aplikasi Model Pembelajaran Al-Qur'an Metode Yusro | F5: Interaksi Manusia-Komputer dan Visualisasi (Human Computer Interaction and Visualisation) | G5: Ridwan Suhud, S.Kom., M.T. | H5: Dr. Esa Prakasa, MT | I5: Prof. Dr. Ana Hadiana, M.Eng.Sc. | J5: Abdurrakhman Prasetyadi, M.P | K5: M. Yudhi Rezaldi, Ph.D | L5: Aria Bisri, S.Kom. M.T. | M5: Andria Arisal, M. Eng. | N5: Andri Fachrur Rozie, M. Eng. | Q5: Dr. Bambang Setiadi | R5: Kerjasama | S5: Dalam Negeri | V5: Universitas Swadaya Gunung Jati | Y5: No. 002/V/KS/01/2025 dan 01/Lemlit-UGJ/I/2025 | Z5: 45667 | AC5: Dana Eksternal & Kerjasama | AD5: Sudah | AE5: 2022 addendum 2024 | AH5: mahasiswa PKL 6 orang dan MBKM 6 orang
A6: 2 | B6: =IF(OR(E6<>"",F6<>""),IF(B6="",NOW(),B6),"") -> 45722.426 | C6: Triwulan II | E6: Pengembangan Platform Digital Smart Research Environment (SRE) yang bertumpu pada Konektivitas Kecerdasan Buatan dan Kolaborasi Pakar untuk Mendukung Perkembangan Riset dan Inovasi di Indonesia | F6: Interaksi Manusia-Komputer dan Visualisasi (Human Computer Interaction and Visualisation) | G6: Rio Nurtantyana | H6: Dr. Ambar Yoganingrum | I6: Arafat Febriandirza, Ph.D | J6: M. Yudhi Rezaldi, Ph.D | K6: Abdurrakhman Prasetyadi, M.P | L6: Aria Bisri, S.Kom. M.T. | M6: Rumadi, S.T., M.T. | R6: Dana Eksternal | S6: Dalam Negeri | T6: RIIM | U6: In Cash | W6: 164200000 | X6: RIIM Kompetitif Gel. 7 | Y6: NOMOR 61/II.7/HK/2024 | Z6: 45650 | AC6: Dana Eksternal & Kerjasama | AD6: Sudah | AE6: 2025
A7: 3 | B7: =IF(OR(E7<>"",F7<>""),IF(B7="",NOW(),B7),"") -> 45733.363 | C7: Mei | E7: Metaspeak: Platform Pembelajaran Multi-Bahasa Mandiri Berbasis Metaverse Untuk Mengatasi Kecemasan Berbahasa | F7: Interaksi Manusia-Komputer dan Visualisasi (Human Computer Interaction and Visualisation) | G7: M. Yudhi Rezaldi, Ph.D | H7: Dr. Esa Prakasa, MT | I7: Dr. Purnomo Husnul Khotimah, M.T | R7: Kerjasama | S7: Dalam Negeri | V7: LPPM Tel U | X7: PKS tahun 2024, Jangka waktu 3 tahun | Y7: 160/V/KS/06/2024 | Z7: 45470 | AC7: Dana Eksternal & Kerjasama | AD7: Sudah | AE7: 2024 | AH7: - Paper published di Q2 Scopus - Perlu konfirmasi apa dpt dana external di tahun 2025
A8: 4 | B8: =IF(OR(E8<>"",F8<>""),IF(B8="",NOW(),B8),"") -> 45736.463 | C8: Triwulan I | E8: Pengembangan Sistem Identifikasi Fitoplankton Perairan Indonesia Dengan Menggunakan Computer Vision | F8: Interaksi Manusia-Komputer dan Visualisasi (Human Computer Interaction and Visualisation) | G8: Dr. Esa Prakasa, MT | H8: Aria Bisri, S.Kom. M.T. | Q8: Riyo Wardoyo (PRKAKS), Arief Rachman (ORKM), Diah Radini Noerjito (ORHL), Ovide DWA (UNS), Tri Retnaningsih (UNDIP), Kusworo (UNDIP) | R8: Dana Eksternal | S8: Dalam Negeri | T8: RIIM | U8: In Cash | W8: 90000000 | X8: RIIM Gel. 3, Tahun ke-2 | AA8: B-838/II.7.5/FR.06/5/2023 | AB8: 8 Mei 2023 | AC8: Dana Eksternal & Kerjasama | AD8: Sudah | AE8: 2024 | AH8: Menunggu Pencairan Dana
A9: 5 | B9: 45761 | C9: April | E9: Pengembangan Sistem Kustomisasi Model Bahasa untuk Meningkatkan Akurasi Whisper dalam Pengenalan Ucapan Otomatis Ujung-ke-Ujung | F9: Pengolahan Bahasa Alami (Natural Language Processing) | G9: Dr. Dipl.(FH) Ing Asril, M.Sc | H9: Agung Santosa, BSEE, M.Kom | I9: Lyla Ruslana Aini | J9: Ir. Gunarso | K9: M. Teduh Uliniansyah, B.Eng., M.Sc., Ph.D. | L9: Elvira Nurfadhilah, S.Komp., M. Kom | M9: Siska Pebiana S.Kom., M.Kom. | Q9: Tim PT Bahasa Kita: Oskar Riandi; Izzul Haq Al Hakam;Achmad Satria Putera | R9: Dana Eksternal | S9: Dalam Negeri | T9: RIIM | U9: In Cash | W9: 165600000 | X9: RIIM Kompetitif Gel. 7 | AA9: B-5647/II.7.5/RT.01.01/4/2025 B-6888/III.6/TK.01.03/4/2025 | AB9: 45761 | AC9: Dana Eksternal & Kerjasama | AD9: Sudah | AE9: 2025 | AH9: SK DEPUTI BIDANG FASILITASI RISET DAN INOVASI, BADAN RISET DAN INOVASI NASIONAL, NOMOR 61/II.7/HK/2024 TENTANG PENERIMA PROGRAM RISET DAN INOVASI UNTUK INDONESIA MAJU KOMPETISI GELOMBANG 7
A10: 6 | B10: =IF(OR(E10<>"",F10<>""),IF(B10="",NOW(),B10),"") -> 45805.383 | E10: Pengembangan Platform Digital Smart Research Environment (SRE) yang bertumpu pada Konektivitas Kecerdasan Buatan dan Kolaborasi Pakar untuk Mendukung Perkembangan Riset dan Inovasi di Indonesia | F10: Interaksi Manusia-Komputer dan Visualisasi (Human Computer Interaction and Visualisation) | G10: Rio Nurtantyana | H10: Dr. Ambar Yoganingrum | I10: Arafat Febriandirza, Ph.D | J10: M. Yudhi Rezaldi, Ph.D | K10: Abdurrakhman Prasetyadi, M.P | L10: Aria Bisri, S.Kom. M.T. | M10: Rumadi, S.T., M.T. | R10: Dana Eksternal | S10: Dalam Negeri | T10: RIIM | U10: In Kind | AA10: 384/V/KS/10/2024 | AB10: 45567 | AC10: Dana Eksternal & Kerjasama | AD10: Sudah | AE10: 2024
A11: 7 | B11: =IF(OR(E11<>"",F11<>""),IF(B11="",NOW(),B11),"") -> 45805.402 | C11: Mei | E11: Pengembangan Teknologi Imersif dan Penyediaan Asset Aplikasi 3D | F11: Interaksi Manusia-Komputer dan Visualisasi (Human Computer Interaction and Visualisation) | G11: Abdurrakhman Prasetyadi, M.P | H11: Dr. Esa Prakasa, MT | I11: M. Yudhi Rezaldi, Ph.D | J11: Dr. Ambar Yoganingrum | K11: Arafat Febriandirza, Ph.D | L11: Rio Nurtantyana, S.Pd., M.Pd., M.Sc., Ph.D. | M11: Ridwan Suhud, S.Kom., M.T. | N11: Aria Bisri, S.Kom. M.T. | Q11: Cahyo Trianggoro | R11: Kerjasama | S11: Dalam Negeri | U11: In Kind | V11: UPI Cibiru Bandung | Y11: 177/V/KS/06/2024 | Z11: 45456 | AC11: Dana Eksternal & Kerjasama | AD11: Sudah | AE11: 2024 | AH11: Kerjasama masih berlangsung, untuk Dana Eksternal (Rp. 36.900.000) sudah dikalim 2024
A12: 8 | B12: 45805 | C12: Triwulan IV | E12: PERANCANGAN ASSET VISUAL GAME (2D/3D) UNTUK MEMPERKENALKAN KEBUDAYAAN DAERAH YANG ADA DI SULAWESI DAN KEPULAUAN NUSA TENGGARA | F12: Interaksi Manusia-Komputer dan Visualisasi (Human Computer Interaction and Visualisation) | G12: M. Yudhi Rezaldi, Ph.D | H12: Ridwan Suhud, S.Kom., M.T. | I12: Abdurrakhman Prasetyadi, M.P | J12: Aang Gunawan S, S.Kom., M.T. | K12: Rio Nurtantyana, S.Pd., M.Pd., M.Sc., Ph.D. | L12: Dr. Ambar Yoganingrum | M12: Aria Bisri, S.Kom. M.T. | N12: Arafat Febriandirza, Ph.D | O12: Dr. Esa Prakasa, MT | P12: Prof. Dr. Ana Hadiana, M.Eng.Sc. | Q12: Cahyo Trianggoro, Niken Fitria Apriani, Dian Andriana | R12: Kerjasama | S12: Dalam Negeri | U12: In Kind | V12: Universitas Telkom | Y12: 232/V/KS/07/2024 | Z12: 45490 | AC12: Dana Eksternal & Kerjasama | AE12: 2024 | AH12: Jangka waktu 2 tahun menghasilkan HKI : EC002025132928, 16 September 2025
A13: 9 | B13: 45805 | C13: Triwulan IV | E13: PERANCANGAN ASSET VISUAL GAME (2D/3D) UNTUK MEMPERKENALKAN KEBUDAYAAN DAERAH MALUKU DAN PAPUA | F13: Interaksi Manusia-Komputer dan Visualisasi (Human Computer Interaction and Visualisation) | G13: M. Yudhi Rezaldi, Ph.D | H13: Ridwan Suhud, S.Kom., M.T. | I13: Abdurrakhman Prasetyadi, M.P | J13: Aang Gunawan S, S.Kom., M.T. | K13: Rio Nurtantyana, S.Pd., M.Pd., M.Sc., Ph.D. | L13: Dr. Ambar Yoganingrum | M13: Aria Bisri, S.Kom. M.T. | N13: Arafat Febriandirza, Ph.D | O13: Dr. Esa Prakasa, MT | P13: Prof. Dr. Ana Hadiana, M.Eng.Sc. | Q13: Cahyo Trianggoro, Niken Fitria Apriani | R13: Kerjasama | S13: Dalam Negeri | U13: In Kind | V13: Universitas Pasundan | Y13: 176/V/KS/06/2024 | Z13: 45462 | AC13: Dana Eksternal & Kerjasama | AE13: 2024 | AH13: Jangka waktu 2 tahun
A14: 10 | B14: =IF(OR(E14<>"",F14<>""),IF(B14="",NOW(),B14),"") -> 45825.595 | E14: Penerapan Algoritma Komodo Mlipir dalam Menyelesaikan Vehicle Routing Problem untuk Rute Wisata Multi-Hari di Yogyakarta | F14: Interaksi Manusia-Komputer dan Visualisasi (Human Computer Interaction and Visualisation) | G14: Rio Nurtantyana, S.Pd., M.Pd., M.Sc., Ph.D. | Q14: Abdurahman Baizal | R14: Dana Eksternal | S14: Dalam Negeri | T14: RIIM | U14: In Kind | V14: Telkom University | W14: 104000000 | X14: RIIM Gel 7, Tahun ke-1 | AC14: Dana Eksternal & Kerjasama | AE14: 2024 | AH14: Jangka Waktu 3 tahun Dana external sudah d klaim 2024
A15: 11 | B15: =IF(OR(E15<>"",F15<>""),IF(B15="",NOW(),B15),"") -> 45862.832 | C15: Juli | E15: Kolaborasi Riset Di Bidang Kesehatan Jantung | F15: Interaksi Manusia-Komputer dan Visualisasi (Human Computer Interaction and Visualisation) | G15: Dr. Esa Prakasa, MT | H15: Dr. Purnomo Husnul Khotimah, M.T | R15: Kerjasama | S15: Dalam Negeri | T15: Mitra/Universitas | V15: Telkom University | Y15: 18/V/KS/04/2022 dan 090/SAM4/RC-HUMIC/2022 | Z15: 21 April 2022 | AC15: Dana Eksternal & Kerjasama | AD15: Sudah
A16: 12 | B16: =IF(OR(E16<>"",F16<>""),IF(B16="",NOW(),B16),"") -> 45862.842 | C16: Juli | E16: Kolaborasi Riset Pengembangan Sistem Penerjemah Bahasa Isyarat BISINDO Menggunakan Analisis Video | F16: Interaksi Manusia-Komputer dan Visualisasi (Human Computer Interaction and Visualisation) | G16: Dr. Esa Prakasa, MT | R16: Kerjasama | S16: Dalam Negeri | T16: Mitra/Universitas | V16: PT. Inovasi Disabilitas Indonesia | Y16: 54/V/KS/07/2022 dan 20.04/Hear Me-PKS/VII/2022 | Z16: 14 Juli 2022 | AC16: Dana Eksternal & Kerjasama | AD16: Sudah | AE16: 2021 | AH16: paper accepted 1 jurnal int.
A17: 13 | B17: =IF(OR(E17<>"",F17<>""),IF(B17="",NOW(),B17),"") -> 45862.855 | C17: Juli | E17: Penelitian dan Pengembangan Human-Centered Computing Untuk Digital Library dan Distance Learning | F17: Interaksi Manusia-Komputer dan Visualisasi (Human Computer Interaction and Visualisation) | G17: Dr. Esa Prakasa, MT | H17: Andre Sihombing, S.Kom., M.Sc. | R17: Kerjasama | S17: Dalam Negeri | T17: Mitra/Universitas | V17: UI | Y17: 531/V/KS/11/2023 dan PKS-99/UN2.F11.D/HKP.05.01/2023 | Z17: 3 November 2023 | AC17: Dana Eksternal & Kerjasama | AD17: Sudah | AE17: 2024 | AH17: mahasiswa MBKM 1
A18: 14 | B18: =IF(OR(E18<>"",F18<>""),IF(B18="",NOW(),B18),"") -> 45880.358 | C18: Agustus | E18: Collaboration and Co-Development of Human-Computer Interaction and Visualization Through Smart Robotics and Mobile Applications for Authentic Contextual Exploration | F18: Interaksi Manusia-Komputer dan Visualisasi (Human Computer Interaction and Visualisation) | G18: Arafat Febriandirza, Ph.D | R18: Kerjasama | S18: Luar Negeri | T18: Mitra/Universitas | V18: Taiwan Vest Information INC | X18: Taiwan | Y18: Perjanjian Kerjasama | Z18: 8 Agustus 2025 | AC18: Dana Eksternal & Kerjasama | AD18: Sudah | AG18: https://drive.google.com/drive/folders/1pfWg0y9PDMakt1iYy0pe81S0Me33MgWo?usp=drive_link | AH18: SURAT TUGAS NOMOR B-303/III.6.3/RT.07.00/1/2025, Tgl. 7 Januari 2025
A19: 15 | B19: =IF(OR(E19<>"",F19<>""),IF(B19="",NOW(),B19),"") -> 45880.366 | E19: Kerjasama Internasional, Ttd LoI PRSDI dengan UKM Malaysia, KelRis HCIV | F19: Interaksi Manusia-Komputer dan Visualisasi (Human Computer Interaction and Visualisation) | G19: Arafat Febriandirza, Ph.D | R19: Kerjasama | S19: Luar Negeri | T19: Mitra/Universitas | V19: UKM Malaysia | AC19: Dana Eksternal & Kerjasama | AH19: Tahun ke-2, Masih Dalam Proses Monitoring dan Evaluasi
A20: 16 | B20: =IF(OR(E20<>"",F20<>""),IF(B20="",NOW(),B20),"") -> 45881.341 | E20: PRSDI - ITENAS | F20: Interaksi Manusia-Komputer dan Visualisasi (Human Computer Interaction and Visualisation) | G20: Arafat Febriandirza, Ph.D | R20: Kerjasama | S20: Dalam Negeri | T20: Mitra/Universitas | V20: ITENAS | AC20: Dana Eksternal & Kerjasama
A21: 17 | B21: =IF(OR(E21<>"",F21<>""),IF(B21="",NOW(),B21),"") -> 45893.781 | C21: Agustus | E21: Kegiatan Penelitian dan Pengembangan Platform Kolaborasi Digital Dengan Teknologi Visualisasi Berbasis Knowledge Graph | F21: Interaksi Manusia-Komputer dan Visualisasi (Human Computer Interaction and Visualisation) | G21: Rio Nurtantyana, S.Pd., M.Pd., M.Sc., Ph.D. | R21: Kerjasama | S21: Dalam Negeri | T21: Mitra/Universitas | V21: Unversitas Brawijaya | Y21: 384/V/KS/10/2024 dan 03404/UN10.F1501/B/KS/2024 | Z21: 02/10/2024 | AC21: Dana Eksternal & Kerjasama | AD21: Sudah
A22: 18 | B22: =IF(OR(E22<>"",F22<>""),IF(B22="",NOW(),B22),"") -> 45894.437 | C22: Agustus | E22: Kolaborasi Dalam Riset dan Inovasi Dalam Arah Strategis Dan Tematik, Serta Mekanisme Dalam Metaverse, Realitas Virtual, Realitas Tertambah, Hologram, Realitas Terpanjang, Realitas Campuran, Dan Bidang-Bidang Terkait | F22: Interaksi Manusia-Komputer dan Visualisasi (Human Computer Interaction and Visualisation) | G22: M. Yudhi Rezaldi, Ph.D | R22: Kerjasama | S22: Luar Negeri | T22: Mitra/Universitas | V22: IVI - Universiti Kebangsaan Malaysia (UKM) | X22: UKM Malaysia | Y22: Surat Pernyataan Kehendak (SPK) | Z22: 7 Agustus 2025 | AC22: Dana Eksternal & Kerjasama | AD22: Sudah
A23: 19 | B23: =IF(OR(E23<>"",F23<>""),IF(B23="",NOW(),B23),"") -> 45924.823 | C23: Triwulan III | E23: Riset Dibidang Teknologi Data-Driven Analytic Untuk Mendukung Pencapaian Sustainable Development Goals | F23: Interaksi Manusia-Komputer dan Visualisasi (Human Computer Interaction and Visualisation) | G23: Aria Bisri, S.Kom. M.T. | R23: Kerjasama | S23: Dalam Negeri | T23: Mitra/Universitas | U23: In Kind | V23: Institut Teknologi Sumatera | Y23: 344/V/KS/09/2025 dan 249/IT9.3.1/HK.08.00/2025 | Z23: 15/09/2025 | AC23: Dana Eksternal & Kerjasama | AD23: Sudah
A24: 20 | B24: =IF(OR(E24<>"",F24<>""),IF(B24="",NOW(),B24),"") -> 45938.434 | C24: Oktober | E24: BRICS New Industry “Golden Egret” Excellence Scholarship 2025 BPIC Training Program on Industrial Green Development and Digitalization | F24: Interaksi Manusia-Komputer dan Visualisasi (Human Computer Interaction and Visualisation) | G24: Arafat Febriandirza, Ph.D | R24: Dana Eksternal | S24: Luar Negeri | T24: Mitra/Universitas | U24: In Kind | W24: 70806550 | AC24: Dana Eksternal & Kerjasama | AD24: Sudah
A25: 21 | B25: =IF(OR(E25<>"",F25<>""),IF(B25="",NOW(),B25),"") -> 45722.426 | C25: Triwulan I | E25: Penerapan Big Data Cognitive Analytics Terhadap Pariwisata dan Ekonomi Kreatif | F25: Pemerintahan Digital (Digital Government) | G25: Rezzy Eko Caraka ,S.Si.,M.Sc(RES).,PhD. | H25: Dra. Andrari Grahitandaru, M.Sc. | I25: Drs. Zain Saifullah, M.Sc. | J25: Nimas Ayu Untariyati, S.Kom, M.T.I | K25: Dr. Eng. Budi Nugroho | R25: Kerjasama | S25: Dalam Negeri | V25: Sekolah Tinggi Ilmu Ekonomi Sabang (STIES) Banda Aceh | W25: 187240000 | X25: PKS TAHUN 2024, Jangka waktu 3 tahun | Y25: No. 524/V/KS/12/2024 dan 102/MoU/STIES/VII/2024 | Z25: 45649 | AC25: Dana Eksternal & Kerjasama | AD25: Sudah | AH25: Klaim untuk tahun 2025. Terdapat output KTI. Publikasi di Prosiding / International Conference (Sheet PI No 38) = Sudah di input (no.5), dan sudah di klaim
A26: 22 | B26: =IF(OR(E26<>"",F26<>""),IF(B26="",NOW(),B26),"") -> 45861.352 | C26: Juli | E26: Sinergi Dibidang Penelitian, Pengembangan, Pengkajian, Penerapan Ilmu Pengetahuan dan Teknologi Serta Investasi dan Inovasi Untuk Mendukung Pembangunan di Kabupaten Muara Enim | F26: Pemerintahan Digital (Digital Government) | G26: Dra. Andrari Grahitandaru, M.Sc. | R26: Kerjasama | S26: Dalam Negeri | V26: Pemkab Muara Enim | Y26: 119/21/IV/2025 dan `51/I/KS/07/2025 | Z26: 17 Juli 2025 | AC26: Dana Eksternal & Kerjasama | AD26: Sudah | AE26: 2024 | AH26: PKS tahun 2024 Jangka waktu 3 Tahun
A27: 23 | B27: =IF(OR(E27<>"",F27<>""),IF(B27="",NOW(),B27),"") -> 45862.884 | C27: Triwulan IV | E27: Hak Cipta Program Komputer : Aplikasi Pemilu Elektronik (e-Voting) (000535510) | F27: Pemerintahan Digital (Digital Government) | G27: Dra. Andrari Grahitandaru, M.Sc. | H27: Drs. Zain Saifullah, M.Sc. | I27: Ir. Gunarso | R27: Kerjasama | S27: Dalam Negeri | T27: Mitra/Universitas | V27: PT. Inti Konten Indonesia (INTENS) | X27: Perjanjian Lisensi | AA27: B-972/II.8/MR.01.01/3/2024 dan 007/PKS/INTENS/III/2024 | AB27: 45370 | AC27: Dana Eksternal & Kerjasama | AD27: Sudah | AE27: 2024 | AG27: https://drive.google.com/drive/u/1/search?q=PKS | AH27: Jangka Waktu 5 tahun Tahun 2025 PT Intens ( Perjanjian Lisensi) untuk penerapan eVoting di Kab Indramayu, Kab Krawang dan Kab Gresik. Apakah menghasilkan lisensi di tahun 2025 ?
A28: 24 | B28: =IF(OR(E28<>"",F28<>""),IF(B28="",NOW(),B28),"") -> 45862.898 | C28: Juli | E28: Penelitian, Pengembangan, Pengkajian, dan Penerapan, Serta Invensi dan Inovasi di Kabupaten Belitung | F28: Pemerintahan Digital (Digital Government) | G28: Dra. Andrari Grahitandaru, M.Sc. | H28: Dr. Esa Prakasa, MT | R28: Kerjasama | S28: Dalam Negeri | T28: Mitra/Universitas | V28: Kab. Belitung | Y28: 87/I/KS/10/2024 dan 181/06/NK/I/2024 | Z28: 01-10-2024 | AC28: Dana Eksternal & Kerjasama | AD28: Sudah | AE28: 2024 | AG28: https://drive.google.com/drive/u/1/search?q=pks
A29: 25 | B29: =IF(OR(E29<>"",F29<>""),IF(B29="",NOW(),B29),"") -> 45733.363 | C29: Mei | E29: Riset dan Pengembangan Mesin Penerjemah Bahasa Makassar dan Bahasa Cia-cia ke Bahasa Indonesia | F29: Pengolahan Bahasa Alami (Natural Language Processing) | G29: M. Teduh Uliniansyah, B.Eng., M.Sc., Ph.D. | R29: Kerjasama | S29: Dalam Negeri | V29: Universitas Handayani Makassar | X29: PKS tahun 2024, Jangka waktu 3 tahun | AA29: 444/V/KS/10/2024 | AB29: 04/11/2024 | AC29: Dana Eksternal & Kerjasama | AD29: Sudah
A30: 26 | B30: =IF(OR(E30<>"",F30<>""),IF(B30="",NOW(),B30),"") -> 45733.363 | E30: Chatbot Lisa | F30: Pengolahan Bahasa Alami (Natural Language Processing) | G30: Elvira Nurfadhilah, S.Komp., M. Kom | R30: Kerjasama | S30: Dalam Negeri | V30: Unit Hemodialisis RSUD Cimacan Cianjur | AA30: 335/V/KS/09/2024 | AB30: 01/10/2024 | AC30: Dana Eksternal & Kerjasama | AH30: Mohon PKS di Upload atau mohon buat surat keterangan pemanfaatan pada tahun 2025 dari RSUD | AI30: Rencana KI Termanfaatkan
A31: 27 | B31: =IF(OR(E31<>"",F31<>""),IF(B31="",NOW(),B31),"") -> 45735.47 | C31: Juli | E31: Riset dan Pengembangan Part of Speech (POS) Tag dan Mesin Penerjemah Bahasa Bugis ke Bahasa Indonesia | F31: Pengolahan Bahasa Alami (Natural Language Processing) | G31: Dr. Eng. Ir Yuyun, S.Kom., M.T | R31: Kerjasama | S31: Dalam Negeri | T31: Mitra/Universitas | V31: Univ. Hasanuddin | W31: 512160000 | Y31: 335/V/KS/09/2024 dan 3782/UN4.9.7/HK.07.00/2024 | Z31: 02-09-2024 | AC31: Dana Eksternal & Kerjasama | AD31: Sudah | AE31: 2023, Amandemen 2025 berakhir 2030
A32: 28 | B32: =IF(OR(E32<>"",F32<>""),IF(B32="",NOW(),B32),"") -> 45736.487 | C32: Triwulan I | E32: ASEAN-Korea Cooperation Fund (AKCF) - Korea Institute of Science and Technology Information (KISTI) | F32: Pengolahan Bahasa Alami (Natural Language Processing) | G32: Iftitahu Ni'mah, S.Kom., M.I.T. | Q32: Dr. Rifki Sadikin (PR Komputasi) | R32: Dana Eksternal | S32: Luar Negeri | T32: Mitra/Universitas | U32: In Kind | V32: Korea Institute of Science and Technology Information (KISTI) | W32: 26169600 | AC32: Dana Eksternal & Kerjasama | AD32: Sudah | AE32: 2022 | AH32: Jangka Waktu 5 tahun
A33: 29 | B33: =IF(OR(E33<>"",F33<>""),IF(B33="",NOW(),B33),"") -> 45787.816 | C33: Juli | E33: Course on Digital Governance, Cybersecurity and A.I. Adoption for Public Service. | F33: Pengolahan Bahasa Alami (Natural Language Processing) | G33: Siska Pebiana S.Kom., M.Kom. | R33: Dana Eksternal | S33: Luar Negeri | T33: Mitra/Universitas | U33: In Kind | V33: Technical Cooperation Directorate Ministry of Foreign Affairs, Singapore Cooperation Programme | W33: 57757712 | X33: SURAT TUGAS NOMOR B-9626/III.6/TK.02.01/5/2025 | AC33: Dana Eksternal & Kerjasama | AD33: Sudah
A34: 30 | B34: =IF(OR(E34<>"",F34<>""),IF(B34="",NOW(),B34),"") -> 0 | C34: Juli | E34: Visiting Researcher ke Pukyong National University dengan tema "Exploring Food Computing" | F34: Pengolahan Bahasa Alami (Natural Language Processing) | G34: Dr. Kokoy Siti Komariah S.Kom., M.T., M.Eng. | R34: Dana Eksternal | S34: Luar Negeri | T34: Visiting Research | U34: In Kind | V34: Pukyong National University | W34: 40000000 | X34: SURAT TUGAS NOMOR B-4143/III.6/TK.02.01/2/2025 | AC34: Dana Eksternal & Kerjasama | AD34: Sudah | AE34: 2023 | AH34: Jangka Waktu 3 tahun
A35: 31 | B35: =IF(OR(E35<>"",F35<>""),IF(B35="",NOW(),B35),"") -> 45862.904 | C35: Juli | E35: Pendekatan Inovatif Data Analitik Guna Meningkatkan Kualitas Pendidikan dan Pengalaman Belajar Peserta Didik Pada Platform Pembelajaran Daring | F35: Pengolahan Bahasa Alami (Natural Language Processing) | G35: Dr. Kokoy Siti Komariah S.Kom., M.T., M.Eng. | H35: Dr. Esa Prakasa, MT | I35: Rio Nurtantyana, S.Pd., M.Pd., M.Sc., Ph.D. | J35: Satrio Adi Priyambada, S.Kom., M.Kom., Ph.D. | R35: Kerjasama | S35: Dalam Negeri | T35: Mitra/Universitas | V35: Universitas Terbuka | Y35: 258/V/KS/07/2024 dan B/2675/UN31.FST/HK.08.00/2024 | Z35: 01-08-2024 | AC35: Dana Eksternal & Kerjasama | AD35: Sudah | AE35: 2024
A36: 32 | B36: =IF(OR(E36<>"",F36<>""),IF(B36="",NOW(),B36),"") -> 45924.816 | C36: Triwulan III | E36: Development of Smart Grid Ontology for Interoperability and Knowledge Sharing | F36: Pengolahan Bahasa Alami (Natural Language Processing) | G36: M. Teduh Uliniansyah, B.Eng., M.Sc., Ph.D. | R36: Kerjasama | S36: Luar Negeri | T36: Mitra/Universitas | U36: In Kind | V36: California polytechnic state University (Calpoly) USA | Z36: 2025 | AC36: Dana Eksternal & Kerjasama | AD36: Sudah | AE36: 2025 | AH36: Jangka Waktu 1 tahun
A37: 33 | B37: =IF(OR(E37<>"",F37<>""),IF(B37="",NOW(),B37),"") -> 45937.348 | E37: Screening Tool Untuk Pengenalan Hidrokarbon Dan Non-Hidrokarbon Menggunakan Data Seismik | F37: Pengolahan Bahasa Alami (Natural Language Processing) | G37: M. Teduh Uliniansyah, B.Eng., M.Sc., Ph.D. | R37: Dana Eksternal | S37: Dalam Negeri | T37: RIIM | U37: In Cash | W37: 101000000 | X37: RIIM gel 9 | AC37: Dana Eksternal & Kerjasama | AE37: 2024 | AH37: Jangka Waktu 3 tahun
A38: 34 | B38: =IF(OR(E38<>"",F38<>""),IF(B38="",NOW(),B38),"") -> 45736.452 | C38: November | E38: Pengembangan Metode End-ToEnd Provenance Artefak Riset Karakterisasi Kacang Tunggak (Vigna unguiculata L.Walp) dalam Mengungkap Sumber Daya Genetiknya | F38: Rekayasa Pengetahuan dan Data (Knowledge and Data Engineering) | G38: Dr. Arya Adhyaksa Waskita, M.Si | R38: Dana Eksternal | S38: Dalam Negeri | T38: RIIM | U38: In Cash | W38: 197000000 | X38: RIIM Gel. 4, Tahun ke-2 | AA38: B-3836/II.7.5/FR.06.00/11/2023 | AB38: 27 November 2023 | AC38: Dana Eksternal & Kerjasama | AD38: Sudah | AE38: 2024 | AH38: Jangka Waktu 3 tahun
A39: 35 | B39: =IF(OR(E39<>"",F39<>""),IF(B39="",NOW(),B39),"") -> 45737.353 | C39: Triwulan I | E39: Pembangunan Sistem Big Data Bahasa dan Folklor Lisan Perbatasan Kalimantan Barat, Indonesia - Sarawak, Malaysia dalam Kerangka Pelestarian Budaya Indonesia | F39: Rekayasa Pengetahuan dan Data (Knowledge and Data Engineering) | G39: Dr. Foni Agus Setiawan, M.Kom. | R39: Dana Eksternal | S39: Dalam Negeri | T39: RIIM | U39: In Cash | W39: 91000000 | X39: RIIM Gel. 4, Tahun ke-2 | Y39: 293/V/KS/08/2025 | Z39: 45894 | AA39: B-3836/II.7.5/FR.06.00/11/2023 | AB39: 27 November 2023 | AC39: Dana Eksternal & Kerjasama | AD39: Sudah
A40: 36 | B40: =IF(OR(E40<>"",F40<>""),IF(B40="",NOW(),B40),"") -> 45787.797 | C40: Triwulan III | E40: International Conference on “Science and Technolocy Information Management System: Practices and Experiences” | F40: Rekayasa Pengetahuan dan Data (Knowledge and Data Engineering) | G40: Lindung Parningotan Manik, PDEng. | R40: Dana Eksternal | S40: Luar Negeri | T40: Mitra/Universitas | U40: In Kind | V40: Nepal Academy of Science & Technology | W40: 20100000 | X40: SURAT TUGAS NOMOR B-9792/III.6/TK.08.00/5/2025 | AC40: Dana Eksternal & Kerjasama | AD40: Sudah | AE40: 2025
A41: 37 | B41: =IF(OR(E41<>"",F41<>""),IF(B41="",NOW(),B41),"") -> 45866.614 | C41: Juli | E41: Riset Pengembangan Platform Smart Tourism Pada Destinasi Pariwisata Super Prioritas Berbasis Data Science | F41: Rekayasa Pengetahuan dan Data (Knowledge and Data Engineering) | G41: Dr. Foni Agus Setiawan, M.Kom. | H41: Hayuning Titi Karsanti S. Kom., M.Eng | I41: Dr. Eng. Ir Yuyun, S.Kom., M.T | Q41: Ery Setiyawan Jullev Atmadji, Kristopher | R41: Kerjasama | S41: Dalam Negeri | T41: Mitra/Universitas | U41: In Kind | V41: Puliteknik Jember | Y41: 352/V/KS/09/2024 dan 10496/PL17/KS/2024 | Z41: 03-10-2024 | AC41: Dana Eksternal & Kerjasama | AD41: Sudah | AE41: 2025
A42: 38 | B42: =IF(OR(E42<>"",F42<>""),IF(B42="",NOW(),B42),"") -> 45875.612 | C42: Agustus | E42: KOLABORASI PENELITIAN DAN INOVASI PADA KNOWLEDGE GRAPH UNTUK PENGEMBANGAN AI | F42: Rekayasa Pengetahuan dan Data (Knowledge and Data Engineering) | G42: Dr. Foni Agus Setiawan, M.Kom. | R42: Kerjasama | S42: Luar Negeri | T42: Mitra/Universitas | V42: SEKOLAH KOMPUTASI DAN KOMPUTASI INOVATIF, UNIVERSITAS BRITANIA RAYA VIETNAM | X42: Vietnam | AC42: Dana Eksternal & Kerjasama | AD42: Sudah | AH42: Sudah Di Klaim Nomor 41
A43: 39 | B43: =IF(OR(E43<>"",F43<>""),IF(B43="",NOW(),B43),"") -> 45901.538 | E43: International Conference on “Science and Technolocy Information Management System: Practices and Experiences” | F43: Rekayasa Pengetahuan dan Data (Knowledge and Data Engineering) | G43: Lindung Parningotan Manik, PDEng. | R43: Dana Eksternal | S43: Luar Negeri | T43: Mitra/Universitas | U43: In Kind | V43: NAM S&T Centre and NAST | W43: 20100000 | AC43: Dana Eksternal & Kerjasama | AD43: Sudah | AH43: Menunggu berkas PKS
A44: 40 | B44: =IF(OR(E44<>"",F44<>""),IF(B44="",NOW(),B44),"") -> 45930.343 | C44: Oktober | E44: RISET DAN INOVASI PENGEMBANGAN SISTEM BIG DATA BAHASA DAN SASTRA LISAN PERBATASAN KALIMANTAN BARAT, INDONESIA - SARAWAK, MALAYSIA | F44: Rekayasa Pengetahuan dan Data (Knowledge and Data Engineering) | G44: Dr. Foni Agus Setiawan, M.Kom. | R44: Kerjasama | S44: Dalam Negeri | T44: Mitra/Universitas | U44: In Kind | V44: SEKOLAH TINGGI KEGURUAN DAN ILMU PENDIDIKAN PERSADA KHATULISTIWA SINTANG | Y44: Nomor : 293A//KS 10812025 dan 146 lltlU lD5/H3ru1/2A25 | Z44: 25-08-2025 | AC44: Dana Eksternal & Kerjasama | AE44: 2024 | AH44: Jangka waktu Kerjasama 3 tahun
A45: 41 | B45: =IF(OR(E45<>"",F45<>""),IF(B45="",NOW(),B45),"") -> 45722.426 | C45: Triwulan I | E45: Penelitian dan Pengembangan Pemodelan Information Retrieval | F45: Temu Kembali Informasi (Information Retrieval) | G45: Dr. Purnomo Husnul Khotimah, M.T. | R45: Kerjasama | S45: Dalam Negeri | V45: FMIPA - Universitas Lampung | Y45: No. 299/V/KS/12/2022 dan 7449/UN26.17/KS.00.00/2022 | Z45: 9 Desember 2024, Addendum ke-1 | AC45: Dana Eksternal & Kerjasama | AD45: Sudah | AE45: 2025
A46: 42 | B46: =IF(OR(E46<>"",F46<>""),IF(B46="",NOW(),B46),"") -> 45735.525 | C46: Mei | E46: Pemantauan Kejadian Penyakit Menular Menggunakan Metode Digital Epidemiology untuk Mendukung Program One Health | F46: Temu Kembali Informasi (Information Retrieval) | G46: Dr. Purnomo Husnul Khotimah, M.T | R46: Dana Eksternal | S46: Dalam Negeri | T46: RIIM | U46: In Cash | W46: 76000000 | X46: RIIM Gel. 4, Tahun ke-2 | AA46: B-3836/II.7.5/FR.06.00/11/2023 | AB46: 27 November 2023 | AC46: Dana Eksternal & Kerjasama | AD46: Sudah | AE46: 2025 | AH46: Sudah diklaim nomor 18
A47: 43 | B47: 45735.525 | C47: Triwulan I | E47: PENELITIAN DAN PENGEMBANGAN TEKNOLOGI IDENTIFIKASI VARIETAS CABAI MENGGUNAKAN DEEP LEARNING UNTUK MEMPERTAHAKAN KEMURNIAN BENIH | F47: Temu Kembali Informasi (Information Retrieval) | G47: Dr. Wiwin Suwarningsih, M.T. | R47: Kerjasama | S47: Dalam Negeri | T47: Mitra/Universitas | V47: BALAI PENELITIAN TANAMAN SAYURAN (BALITSA) Lembang | X47: PKS tahun 2021, Jangka waktu 5 tahun | AA47: NOMOR: B-7459/III/KS.01.01/8/2021 NOMOR: B-1115.1/1-1K.220/H.3.1/08/2021, Tgl. 23 Agustus 2021 | AB47: 44431 | AC47: Dana Eksternal & Kerjasama | AD47: Sudah | AH47: RIIM Gelombang 9
A48: 44 | B48: =IF(OR(E47<>"",F48<>""),IF(B48="",NOW(),B48),"") -> 45735.526 | C48: Triwulan I | E48: Penelitian dan Pengembangan Water Bodies Segmentation and Spatiotemporal Analysis of Surface Water Using Data Analytics | F48: Temu Kembali Informasi (Information Retrieval) | G48: Devi Munandar, S.Kom., M.Mat. | H48: Andre Sihombing, S.Kom., M.Sc. | R48: Kerjasama | S48: Dalam Negeri | T48: Mitra/Universitas | V48: Universitas Riau | X48: PKS 2024, Jangka waktu 3 Tahun | AA48: PKS No 283/V/KS/08/2024 dan 2576/UN19.5.1.1.3/KS.00.00/2024 | AB48: 20 Agustus 2024 | AC48: Dana Eksternal & Kerjasama | AD48: Sudah | AE48: 2025
A49: 45 | B49: =IF(OR(E49<>"",F49<>""),IF(B49="",NOW(),B49),"") -> 45735.958 | C49: Triwulan I | E49: ACM ASEAN School on HPC and AI | F49: Temu Kembali Informasi (Information Retrieval) | G49: Andria Arisal, M. Eng. | R49: Dana Eksternal | S49: Luar Negeri | T49: Mitra/Universitas | U49: In Kind | V49: National Super Computing Center, Singapore dan Association Computing Machinery | W49: 61075000 | X49: National Super Computing Center, Singapore dan Association Computing Machinery | AC49: Dana Eksternal & Kerjasama | AD49: Sudah | AE49: 2025
A50: 46 | B50: =IF(OR(E50<>"",F50<>""),IF(B50="",NOW(),B50),"") -> 45869.5 | C50: Agustus | E50: ACM Europe Summer School on HPC Computer Architectures for AI and Dedicated Applications | F50: Temu Kembali Informasi (Information Retrieval) | G50: Andria Arisal, M. Eng. | R50: Dana Eksternal | S50: Luar Negeri | T50: Mitra/Universitas | U50: In Kind | V50: Barcelona Supercomputing Center + Association Computing Machinery (SIG HPC) | W50: 52528400 | X50: Barcelona Supercomputing Center + Association Computing Machinery (SIG HPC) | AC50: Dana Eksternal & Kerjasama | AD50: Sudah | AE50: 2025
A51: 47 | B51: =IF(OR(E51<>"",F51<>""),IF(B51="",NOW(),B51),"") -> 45910.431 | E51: Identifikasi Keragaman Fenotip Varietas Cabai Berbasis Kecerdasan Artificial | F51: Temu Kembali Informasi (Information Retrieval) | G51: Dr. Wiwin Suwarningsih, M.T. | H51: Dr. Purnomo Husnul Khotimah, M.T | I51: Andri Fachrur Rozie, M. Eng. | J51: Andria Arisal, M. Eng. | K51: Ekasari Nugraheni, M.T. | L51: Ir. Dianadewi Riswantini, M. Sc., M.B.A. | M51: Devi Munandar, S.Kom., M.Mat. | N51: Irfan Asfy Fakhry Anto S.Kom., M.T | Q51: Irya Wisnubhadra, S.T, M.T, Ph.D, IPM (Universitas Atma Jaya Yogyakarta) Dr. Christina Juliane (STMIK LIKMI Bandung) Rakhmayudi, M.Kom (Universitas Subang) Dr. Rinda Kirana (PRHB-BRIN) Gede Deny Kharisman PT Bukitmas Agritech Int.) Noor Roufiq Ahmadi (BPSI Sayuran-Kementan) Pepen Ependi (BPSI Sayuran-Kementan) | R51: Dana Eksternal | S51: Dalam Negeri | T51: RIIM | U51: In Cash | W51: 92000000 | X51: RIIM gel 9 | AC51: Dana Eksternal & Kerjasama | AE51: 2025 | AH51: RIIM Gelombang 9
A52: 48 | B52: =IF(OR(E52<>"",F52<>""),IF(B52="",NOW(),B52),"") -> 45933.348 | C52: Oktober | E52: PENGEMBANGAN TEKNOLOGI WERENG BATANG COKLAT BERBASIS IDENTIFIKASI DAN PREDIKSI YANG PRESISI UNTUK KETAHANAN PANGAN D.I. YOGYAKARTA | F52: Temu Kembali Informasi (Information Retrieval) | G52: Dr. Wiwin Suwarningsih, M.T. | Q52: Dr. Arlyna Budi Pustika, S.P., M.P; Sutomo, S.Hut., M.Sc., Ph.D.; Prof. Dr. Drs. Sudarmaji, MP. | R52: Dana Eksternal&Kerjasama | S52: Dalam Negeri | T52: Mitra/Universitas | U52: In Kind | V52: Dinas Pertanian dan Ketahanan Pangan Daerah Istimewa Yogyakarta | W52: 54500000 | X52: Nota Kesepakatan BRIN & Pemerintah DIY nomor 21/I/KS/02/2024 & No. 100.3.7.1/1473 | Y52: 5/III.11.3/HK/2025 | AC52: Dana Eksternal & Kerjasama | AD52: Sudah | AE52: 2025
A53: 49 | B53: =IF(OR(E53<>"",F53<>""),IF(B53="",NOW(),B53),"") -> 45854.581 | E53: Pengukuran Kualitas Air (pH dan TDS) Berbasiskan Internet of Thing | F53: Temu Kembali Informasi (Information Retrieval) | G53: Dr. DIPL. ING (FH) Anne Parlina, M.P. | Q53: Misbahul Fajri | R53: Dana Eksternal&Kerjasama | S53: Dalam Negeri | T53: Mitra/Universitas | U53: In Kind | X53: PKS tahun 2024 3 tahun | AC53: Dana Eksternal & Kerjasama
A54: 50 | B54: =IF(OR(E54<>"",F54<>""),IF(B54="",NOW(),B54),"") -> 45981.678 | C54: November | E54: Deepfake Detection for Personalised Learning | F54: Pengolahan Bahasa Alami (Natural Language Processing) | G54: Dr. Rini Wijayanti, S.Kom., M.Kom. | R54: Kerjasama | S54: Luar Negeri | T54: Mitra/Universitas | U54: In Kind | V54: DEPARTMENT OF COMPUTER ENGINEERING, FACULTY OF ENGINEERING, CHULALONGKORN UNIVERSITY, THAILAND | X54: Letter of Intent 1 tahun | Z54: 13 Oktober 2025 | AC54: Dana Eksternal & Kerjasama | AD54: Sudah | AE54: 2025
A55: 51 | B55: =IF(OR(E55<>"",F55<>""),IF(B55="",NOW(),B55),"") -> 45981.689 | C55: November | E55: Screening Tool Untuk Pengenalan Hidrokarbon Dan Non-Hidrokarbon Menggunakan Data Seismik | F55: Temu Kembali Informasi (Information Retrieval) | G55: Dr. Wiwin Suwarningsih, M.T. | H55: Devi Munandar, S.Kom., M.Mat. | I55: Irfan Asfy Fakhry Anto S.Kom., M.T | J55: M. Teduh Uliniansyah, B.Eng., M.Sc., Ph.D. | K55: Dr. Esa Prakasa, MT | L55: Rumadi, S.T., M.T. | M55: Christine Cecylia Munthe, S.Kom. | N55: Hengki Muradi, M.Si. | Q55: Dr. Ir. Nia Kurnia Praja M.T. Maman Hermana, Phd | R55: Kerjasama | S55: Luar Negeri | T55: RIIM | U55: In Kind | V55: Intitute Technology Petronas Malaysia | X55: Letter of Intent 1 tahun | Z55: 20 November 2025 | AC55: Dana Eksternal & Kerjasama | AD55: Sudah | AE55: 2025 | AH55: Kegiatan RIIM Gel 9 (Pak Teduh), didalam kegiatan tersebut ada kerjasama riset dengan pihak luar negeri (Malaysia).
A56: 52 | B56: =IF(OR(E56<>"",F56<>""),IF(B56="",NOW(),B56),"") -> 45981.861 | C56: November | E56: Penelitian, Pengembangan, Pengkajian, dan Penerapan, Serta Invensi dan Inovasi Dalam Rangka Pembangunan Daerah di Kabupaten Lombok Barat | F56: Pemerintahan Digital (Digital Government) | G56: Dr. Eng. Budi Nugroho | H56: Dr. Esa Prakasa, MT | I56: Dr. Purnomo Husnul Khotimah, M.T | Q56: Pemkab Lombok Barat | R56: Kerjasama | S56: Dalam Negeri | T56: Mitra/Universitas | U56: In Kind | V56: Pemkab. Lombok Barat | Y56: 85/I/KS/10/2025 dan 100.3.7.1/27/NK/2025 | Z56: 27 Oktober 2025 | AC56: Dana Eksternal & Kerjasama | AD56: Sudah | AE56: 2025
A57: 53 | B57: 45989 | C57: November | E57: Collaboration on research and innovation on metaverse, virtual reality, augmented reality, hologram, extended reality, and mix reality | F57: Interaksi Manusia-Komputer dan Visualisasi (Human Computer Interaction and Visualisation) | G57: M. Yudhi Rezaldi, Ph.D | H57: Dr. Esa Prakasa, MT | I57: Dr. Ambar Yoganingrum | J57: Prof. Dr. Ana Hadiana, M.Eng.Sc. | K57: Arafat Febriandirza, Ph.D | L57: Rio Nurtantyana, S.Pd., M.Pd., M.Sc., Ph.D. | M57: Ridwan Suhud, S.Kom., M.T. | N57: Abdurrakhman Prasetyadi, M.P | O57: Aria Bisri, S.Kom. M.T. | P57: Rumadi, S.T., M.T. | Q57: Assoc. Prof. Dr. Rabiah Abdul Qadir, Assoc. Prof. Dr. Nazlena Mohamad Ali | R57: Kerjasama | S57: Luar Negeri | T57: Mitra/Universitas | V57: Institut Visual Informasi -Universitas Kebangsaan Malaysia | X57: Letter of Intent 1 tahun | Z57: 45876 | AC57: Dana Eksternal & Kerjasama | AD57: Sudah | AH57: Christine Cecylia Munthe, S.Kom., Halim Hamadi (Kedua nama tersebut belum termasuk dalam kolom civitas PRSDI, karena kolom civitas hanya untuk 10 nama
A58: 54 | B58: 45989 | C58: November | E58: A Systematic Review of Virtual Reality Exergames for Older Adults: Enhancing Physical, Cognitive, and Social Health | F58: Interaksi Manusia-Komputer dan Visualisasi (Human Computer Interaction and Visualisation) | G58: M. Yudhi Rezaldi, Ph.D | Q58: Xiacheng Song, Nazlena Mohamad Ali, Mohamad Hidir Mhd Salim | R58: Dana Eksternal | S58: Luar Negeri | T58: Mitra/Universitas | U58: In Kind | V58: Institut Visual Informasi -Universitas Kebangsaan Malaysia | W58: Rp. 49.500.000 | AC58: Dana Eksternal & Kerjasama | AG58: https://drive.google.com/file/d/1N7DXD5GgE-BJdQILEc9AG3gMjq8sALNQ/view?usp=drive_link | AH58: APC (biaya publikasi jurnal)
A59: 55 | B59: 45989 | C59: November | E59: Riset dan pengembangan Large Language Model (LLM) Multimodal untuk sistem Triase semi Otomatis di Rumah Sakit Indonesia | F59: Pengolahan Bahasa Alami (Natural Language Processing) | G59: Yaniasih | H59: Nuraisa Novia Hidayati, S.Kom., M.Kom. | I59: M. Teduh Uliniansyah, B.Eng., M.Sc., Ph.D. | J59: Agung Santosa, BSEE, M.Kom | K59: Dr. Dipl.(FH) Ing Asril, M.Sc | L59: Ir. Gunarso | M59: Dr. DIPL. ING (FH) Anne Parlina, M.P. | N59: Dr. Rini Wijayanti, S.Kom., M.Kom. | O59: Dr. Kokoy Siti Komariah S.Kom., M.T., M.Eng. | P59: Ir. Andi Djalal Latief, M.S. | Q59: Arief Sartono, Ahmad Ridwan Fauzi, Lalan Jaelani | R59: Kerjasama | S59: Dalam Negeri | T59: Mitra/Universitas | U59: In Kind | V59: PT Envision Lab Studio - LPPM Universitas Suryakancana | W59: 35000000 | Y59: 386/V/KS/09/2025 | Z59: 45874 | AC59: Dana Eksternal & Kerjasama | AD59: Sudah
A60: 56 | B60: =IF(OR(E60<>"",F60<>""),IF(B60="",NOW(),B60),"") -> 45994.454 | E60: Advancing SDG 11 Through Capacity Building and Science-Based Urban Spatial Planning (SciBUSP) in Southeast Asia: Big Earth Data Solutions for Sustainable Urban Planning | F60: Pengolahan Bahasa Alami (Natural Language Processing) | G60: Prabu Kresna Putra, S.T., M.T.I. | Q60: Prof. Dewayany (F), Bowei Chen (M), Ngoc Thang Nguyen (M), Suzanna Noor Azmi (F), Robby Arifandri (M), Aninda Wisaksanti Rudiastuti (F), Boby Bagja Pratama (M), Ayub Sugara (M) | R60: Dana Eksternal | S60: Luar Negeri | T60: Hibah | U60: In Kind | V60: 1. The International Research Center of Big Data for Sustainable Development Goals (CBAS), Chinese Academy of Sciences 2. Institute of Geography, Vietnam Academy of Science and Technology 3. Universiti Teknologi Malaysia 4. National Research and Innovation Agency (BRIN) 5. Faculty of Agriculture, Bengkulu University | W60: 500850000 | X60: https://doi.org/10.30852/p.33903 | AB60: The official term of the Contract is from 1 October 2025 to 30 September 2026. | AC60: Dana Eksternal & Kerjasama | AG60: https://www.apn-gcr.org/project/advancing-sdg-11-through-capacity-building-and-science-based-urban-spatial-planning-scibusp-in-southeast-asia-big-earth-data-solutions-for-sustainable-urban-planning/ | AH60: Mohon evidence di upload / surat keperangan valuasi
A61: 57 | B61: =IF(OR(E61<>"",F61<>""),IF(B61="",NOW(),B61),"") -> 45994.548 | C61: Triwulan IV | E61: Â 2025 Alumni Workshop on Local Actions for Disaster Risk Reduction and Climate Change Adaptation | F61: Pemerintahan Digital (Digital Government) | G61: Rezzy Eko Caraka ,S.Si.,M.Sc(RES).,PhD. | R61: Dana Eksternal | S61: Luar Negeri | T61: Mitra/Universitas | U61: In Kind | V61: UNITAR CIFAL Jeju/JITC (Thailand) | W61: 46288995 | AC61: Dana Eksternal & Kerjasama | AD61: Sudah
A62: 58 | B62: =IF(OR(E62<>"",F62<>""),IF(B62="",NOW(),B62),"") -> 45999.605 | E62: The first workshop on Asian Multi-Cultural LLM by National Institute of Information and Communications Technology (NICT) | F62: Pengolahan Bahasa Alami (Natural Language Processing) | G62: Dr. Eng. Ir Yuyun, S.Kom., M.T | R62: Dana Eksternal | S62: Luar Negeri | T62: Mitra/Universitas | U62: In Kind | V62: National Institute of Information and Communications Technology (NICT) Jepang | AC62: Dana Eksternal & Kerjasama
A63: 59 | B63: =IF(OR(E63<>"",F63<>""),IF(B63="",NOW(),B63),"") -> 46001.77 | C63: Triwulan IV | E63: MOST-111-2221 E-006-010-MY3 – Integrating Remote Sensing and Statistical Models for Climate and Carbon Studies (2025–2027) | F63: Pemerintahan Digital (Digital Government) | G63: Rezzy Eko Caraka ,S.Si.,M.Sc(RES).,PhD. | R63: Dana Eksternal | S63: Luar Negeri | T63: Mitra/Universitas | U63: In Kind | V63: Chaoyang University of Technology - China | W63: 1502059500 | AC63: Dana Eksternal & Kerjasama | AD63: Sudah
A64: 60 | B64: =IF(OR(E64<>"",F64<>""),IF(B64="",NOW(),B64),"") | AC64: Dana Eksternal & Kerjasama
A65: 61 | B65: =IF(OR(E65<>"",F65<>""),IF(B65="",NOW(),B65),"") | AC65: Dana Eksternal & Kerjasama
A66: 62 | B66: =IF(OR(E66<>"",F66<>""),IF(B66="",NOW(),B66),"") | AC66: Dana Eksternal & Kerjasama
A67: 63 | B67: =IF(OR(E67<>"",F67<>""),IF(B67="",NOW(),B67),"") | AC67: Dana Eksternal & Kerjasama
A68: 64 | B68: =IF(OR(E68<>"",F68<>""),IF(B68="",NOW(),B68),"") | AC68: Dana Eksternal & Kerjasama
A69: 65 | B69: =IF(OR(E69<>"",F69<>""),IF(B69="",NOW(),B69),"") | AC69: Dana Eksternal & Kerjasama
A70: 66 | B70: =IF(OR(E70<>"",F70<>""),IF(B70="",NOW(),B70),"") | AC70: Dana Eksternal & Kerjasama
A71: 67 | B71: =IF(OR(E71<>"",F71<>""),IF(B71="",NOW(),B71),"") | AC71: Dana Eksternal & Kerjasama
B76: =IF(OR(E76<>"",F76<>""),IF(B76="",NOW(),B76),"") | AC76: Dana Eksternal & Kerjasama
B77: =IF(OR(E77<>"",F77<>""),IF(B77="",NOW(),B77),"") | AC77: Dana Eksternal & Kerjasama
B78: =IF(OR(E78<>"",F78<>""),IF(B78="",NOW(),B78),"") | AC78: Dana Eksternal & Kerjasama
B79: =IF(OR(E79<>"",F79<>""),IF(B79="",NOW(),B79),"") | AC79: Dana Eksternal & Kerjasama
B80: =IF(OR(E80<>"",F80<>""),IF(B80="",NOW(),B80),"") | AC80: Dana Eksternal & Kerjasama
B81: =IF(OR(E81<>"",F81<>""),IF(B81="",NOW(),B81),"") | AC81: Dana Eksternal & Kerjasama
B82: =IF(OR(E82<>"",F82<>""),IF(B82="",NOW(),B82),"") | AC82: Dana Eksternal & Kerjasama
B83: =IF(OR(E83<>"",F83<>""),IF(B83="",NOW(),B83),"") | AC83: Dana Eksternal & Kerjasama
B84: =IF(OR(E84<>"",F84<>""),IF(B84="",NOW(),B84),"") | AC84: Dana Eksternal & Kerjasama

Sheet SDM IPTEK
A1: SDM IPTEK MELANJUTKAN SEKOLAH
A4: DIISI OLEH PJ MONEV | E4: PUSAT RISET SAINS DATA DAN INFORMASI
A5: NO | B5: Periode Input | C5: Periode Stamp | E5: NAMA SDM IPTEK | F5: KELOMPOK RISET | G5: JENJANG PENDIDIKAN DITEMPUH | H5: NAMA UNIVERSITAS | I5: STATUS | J5: KETERANGAN | K5: UPLOAD DAKUNG | L5: LINK DOKUMEN PENDUKUNG | M5: STATUS UPLOAD | N5: CATATAN
A6: 1 | B6: =IF(OR(E6<>"",F6<>""),IF(B6="",NOW(),B6),"") -> 45728.55 | C6: Triwulan I | E6: Andre Sihombing, S.Kom., M.Sc. | F6: Temu Kembali Informasi (Information Retrieval) | G6: S3 | H6: Pennsylvania State University | I6: Tugas Belajar LN | J6: Sudah menerima Offer letter dari Universitas, saat ini akan proses pengajuan perpindahan kampus ke LPDP | K6: SDM Iptek | L6: https://drive.google.com/drive/folders/1saqMiUVsZgR1VyCEvn4MASkLksLD2T6J | M6: Sudah | N6: Sudah menerima Offer letter dari Universitas, saat ini akan proses pengajuan perpindahan kampus ke LPDP | O6: Terbit LOA sebagai evidence Biaya: Beasiswa (evidence lainnya) dan Mandiri (ada evidence langsung Klaim)
A7: 2 | B7: =IF(OR(E7<>"",F7<>""),IF(B7="",NOW(),B7),"") -> 45736.243 | E7: Andria Arisal, M. Eng. | F7: Temu Kembali Informasi (Information Retrieval) | G7: S3 | H7: Universitas Indonesia | I7: Tugas Belajar DBR | J7: DBR Sedang semester 2 | K7: SDM Iptek | L7: https://drive.google.com/file/d/1NDR4G2ztYUm9YEl0iAsPKdc9YmL7fN-p/view?usp=sharing | M7: Sudah | N7: Sudah di klaim 2024 (Tw4)
A8: 3 | B8: =IF(OR(E8<>"",F8<>""),IF(B8="",NOW(),B8),"") -> 45736.243 | C8: Triwulan I | E8: Hayuning Titi Karsanti S. Kom., M.Eng | F8: Rekayasa Pengetahuan dan Data (Knowledge and Data Engineering) | G8: S3 | H8: Universitas Gadjah Mada | I8: Tugas Belajar Dalam Negeri non DBR | J8: SK Tugas Belajar per 1 Maret 2025 | K8: SDM Iptek | L8: https://drive.google.com/drive/folders/1BCWpu0GAYOZmKfXCjvC_raBXz06KeIc8?usp=sharing | M8: Sudah | N8: Sudah aktif perkuliahan per 10 Februari 2025, menggunakan pendanaan dari LPDP
A11: 6 | B11: =IF(OR(E11<>"",F11<>""),IF(B11="",NOW(),B11),"") -> 45805.38 | C11: Agustus | E11: Aang Gunawan S, S.Kom., M.T. | F11: Interaksi Manusia-Komputer dan Visualisasi (Human Computer Interaction and Visualisation) | G11: S3 | H11: National Central University | I11: Tugas Belajar LN | J11: Sudah menerima email admitted dari kampus, menunggu LoA dan LoG beasiswa dari NCU | K11: SDM Iptek | L11: https://1drv.ms/b/c/98c65c5114051101/EXv2lH8gaItIv9jYnkWSSwkBKXA5FVta2ccx1AinP-Vu6A?e=dSdSFL | M11: Sudah | N11: Sudah menerima email admitted dari kampus, menunggu LoA dan LoG beasiswa dari NCU, setelah itu baru mengajukan SK Tubel LN
A12: 7 | B12: =IF(OR(E12<>"",F12<>""),IF(B12="",NOW(),B12),"") -> 45856.49 | C12: Agustus | E12: Ariani Indrawati, M.TI | F12: Rekayasa Pengetahuan dan Data (Knowledge and Data Engineering) | G12: S3 | H12: Universitas Indonesia | I12: Tugas Belajar Dalam Negeri non DBR | J12: Lulus Pengumuman hasil seleksi akhir | K12: SDM Iptek | L12: https://drive.google.com/file/d/1WXui1Lm70DSKo4Fv9Ns85l_aJMa92zNO/view?usp=drive_link | M12: Sudah
A13: 9 | B13: =IF(OR(E13<>"",F13<>""),IF(B13="",NOW(),B13),"") | K13: SDM Iptek
A14: 10 | B14: =IF(OR(E14<>"",F14<>""),IF(B14="",NOW(),B14),"") | K14: SDM Iptek
A15: 11 | B15: =IF(OR(E15<>"",F15<>""),IF(B15="",NOW(),B15),"") | K15: SDM Iptek
A16: 12 | B16: =IF(OR(E16<>"",F16<>""),IF(B16="",NOW(),B16),"") | K16: SDM Iptek
A17: 13 | B17: =IF(OR(E17<>"",F17<>""),IF(B17="",NOW(),B17),"") | K17: SDM Iptek
A18: 14 | B18: =IF(OR(E18<>"",F18<>""),IF(B18="",NOW(),B18),"") | K18: SDM Iptek
A19: 15 | B19: =IF(OR(E19<>"",F19<>""),IF(B19="",NOW(),B19),"") | K19: SDM Iptek
A20: 16 | B20: =IF(OR(E20<>"",F20<>""),IF(B20="",NOW(),B20),"") | K20: SDM Iptek
A21: 17 | B21: =IF(OR(E21<>"",F21<>""),IF(B21="",NOW(),B21),"") | K21: SDM Iptek
A22: 18 | B22: =IF(OR(E22<>"",F22<>""),IF(B22="",NOW(),B22),"") | K22: SDM Iptek
A23: 19 | B23: =IF(OR(E23<>"",F23<>""),IF(B23="",NOW(),B23),"") | K23: SDM Iptek
A24: 20 | B24: =IF(OR(E24<>"",F24<>""),IF(B24="",NOW(),B24),"") | K24: SDM Iptek
... A61: 57 | B61: =IF(OR(E61<>"",F61<>""),IF(B61="",NOW(),B61),"") | K61: SDM Iptek

Sheet POSTDOCVR
A1: POSTDOC/VISITING RESEARCH/PELATIHAN SDM KE LUAR NEGERI
A4: DIISI OLEH PJ MONEV | E4: PUSAT RISET SAINS DATA DAN INFORMASI | J4: OUTPUT | L4: PUBLIKASI INTERNASIONAL
A5: NO | B5: Periode Input | C5: Periode Stamp | E5: NAMA SDM PRSDI | F5: NON SDM PRSDI | G5: KELOMPOK RISET | H5: STATUS | I5: JENIS | J5: VOLUME | K5: SATUAN | L5: 1 | M5: 2 | N5: 3 | O5: KEKAYAAN INTELEKTUAL | P5: DANA EKSTERNAL | Q5: KETERANGAN | R5: UPLOAD DAKUNG | S5: STATUS UPLOAD | T5: CATATAN
A6: 1 | B6: =IF(OR(E6<>"",F6<>""),IF(B6="",NOW(),B6),"") -> 45736.405 | C6: Triwulan I | E6: Andria Arisal, M. Eng. | G6: Temu Kembali Informasi (Information Retrieval) | H6: PESERTA PELATIHAN INTERNASIONAL | I6: Luar Negeri | P6: ACM ASEAN School on HPC and AI | Q6: https://drive.google.com/drive/folders/1G3L4xSzBFN-e5PExfv21tmzgkSmXabNK?usp=drive_link | R6: SDM Postdoc/VR | S6: Sudah
A7: 2 | B7: =IF(OR(E7<>"",F7<>""),IF(B7="",NOW(),B7),"") -> 45736.483 | C7: Triwulan I | E7: Iftitahu Ni'mah, S.Kom., M.I.T. | G7: Pengolahan Bahasa Alami (Natural Language Processing) | H7: PESERTA PELATIHAN INTERNASIONAL | I7: Luar Negeri | P7: ASEAN-Korea Cooperation Fund (AKCF) - Korea Institute of Science and Technology Information (KISTI) | Q7: https://drive.google.com/drive/folders/1STeg-PXLaFxrd8YyzrZFABdpaBzs85gX?usp=drive_link | R7: SDM Postdoc/VR | S7: Sudah | T7: sertifikat menyusul
A8: 3 | B8: =IF(OR(E8<>"",F8<>""),IF(B8="",NOW(),B8),"") -> 45787.795 | C8: Mei | E8: Lindung Parningotan Manik, PDEng. | G8: Rekayasa Pengetahuan dan Data (Knowledge and Data Engineering) | H8: PESERTA PELATIHAN INTERNASIONAL | I8: Luar Negeri | P8: International Conference on “Science and Technolocy Information Management System: Practice and Experiences” | R8: SDM Postdoc/VR | S8: Sudah | T8: Dalam rangka memperkuat kompetensi di forum internasional (mohon sertifikat di upload)
A9: 4 | B9: =IF(OR(E9<>"",F9<>""),IF(B9="",NOW(),B9),"") -> 45787.814 | C9: Juli | E9: Siska Pebiana S.Kom., M.Kom. | G9: Pengolahan Bahasa Alami (Natural Language Processing) | H9: PESERTA PELATIHAN INTERNASIONAL | I9: Luar Negeri | P9: Course on Digital Governance, Cybersecurity and A.I. Adoption for Public Service. | R9: SDM Postdoc/VR | S9: Sudah | T9: - Penyeleggaraan 26 Mei 2025 s.d. 30 Mei 2025 - Mohon sertifikat pelatihan, dokumentasi, jadwal materi
A10: 5 | B10: =IF(OR(E10<>"",F10<>""),IF(B10="",NOW(),B10),"") -> 45805.683 | C10: Juli | E10: Dr. Kokoy Siti Komariah S.Kom., M.T., M.Eng. | G10: Pengolahan Bahasa Alami (Natural Language Processing) | H10: VISITING RESEARCH | I10: Luar Negeri | P10: Visiting Researcher ke Pukyong National University dengan tema "Exploring Food Computing" | Q10: https://drive.google.com/drive/folders/1KU_HSviyY7GwOFnq5jRG36JTwG2jEh8z?usp=sharing | R10: SDM Postdoc/VR | S10: Sudah
A11: 6 | B11: =IF(OR(E11<>"",F11<>""),IF(B11="",NOW(),B11),"") -> 45805.872 | C11: Juli | E11: Andria Arisal, M. Eng. | G11: Temu Kembali Informasi (Information Retrieval) | H11: VISITING RESEARCH | I11: Luar Negeri | P11: ACM Europe Summer School on HPC Computer Architectures for AI and Dedicated Applications | Q11: https://drive.google.com/drive/folders/1doPlC0r5yxcWI-vP26eycRFARQBaiPgH?usp=sharing | R11: SDM Postdoc/VR | S11: Sudah
A12: 7 | B12: =IF(OR(E12<>"",F12<>""),IF(B12="",NOW(),B12),"") -> 45851.27 | C12: Juli | F12: Dr Quang Vinh BUV Vietnam | G12: Rekayasa Pengetahuan dan Data (Knowledge and Data Engineering) | H12: VISITING RESEARCH | I12: Luar Negeri | Q12: Knowledge Graphs & LLMs for Intrusion Detection | R12: SDM Postdoc/VR | S12: Sudah
A13: 8 | B13: =IF(OR(E13<>"",F13<>""),IF(B13="",NOW(),B13),"") -> 45851.271 | C13: Juli | F13: Dr Andino Maselano | G13: Pengolahan Bahasa Alami (Natural Language Processing) | H13: VISITING RESEARCH | I13: Luar Negeri | Q13: https://drive.google.com/drive/folders/19SFg3rXH-s4XqqJhv9TeF0I57m8dFUIg?usp=drive_link | R13: SDM Postdoc/VR | S13: Sudah
A14: 9 | B14: =IF(OR(E14<>"",F14<>""),IF(B14="",NOW(),B14),"") -> 45854.575 | C14: Agustus | E14: Rio Nurtantyana, S.Pd., M.Pd., M.Sc., Ph.D. | F14: Prof. Hwang (Taiwan) | G14: Interaksi Manusia-Komputer dan Visualisasi (Human Computer Interaction and Visualisation) | H14: VISITING RESEARCH | I14: Luar Negeri | Q14: https://awan.brin.go.id/s/KnPsbC3WqPW65d2 | R14: SDM Postdoc/VR | S14: Sudah
A15: 10 | B15: =IF(OR(E15<>"",F15<>""),IF(B15="",NOW(),B15),"") -> 45880.385 | F15: VR, Prof Abel, Australia KelRis IR (akhir Agustus) | H15: VISITING RESEARCH | I15: Luar Negeri | R15: SDM Postdoc/VR
A16: 11 | B16: =IF(OR(E16<>"",F16<>""),IF(B16="",NOW(),B16),"") -> 45880.385 | C16: Triwulan IV | F16: Prof Bong-Kee Sin, Korea | G16: Pengolahan Bahasa Alami (Natural Language Processing) | H16: VISITING RESEARCH | I16: Luar Negeri | Q16: Digital Health Service Platform for Everyone and Everywhere | R16: SDM Postdoc/VR | S16: Sudah
A17: 12 | B17: =IF(OR(E17<>"",F17<>""),IF(B17="",NOW(),B17),"") -> 45880.385 | C17: Oktober | E17: Arafat Febriandirza, Ph.D | G17: Interaksi Manusia-Komputer dan Visualisasi (Human Computer Interaction and Visualisation) | H17: PESERTA PELATIHAN INTERNASIONAL | I17: Luar Negeri | Q17: BRICS New Industry “Golden Egret” Excellence Scholarship 2025 BPIC Training Program on Industrial Green Development and Digitalization | R17: SDM Postdoc/VR | S17: Sudah
A18: 13 | B18: =IF(OR(E18<>"",F18<>""),IF(B18="",NOW(),B18),"") -> 45880.387 | E18: Talenta Riset, Pak Andria ke Jepang | H18: PESERTA PELATIHAN INTERNASIONAL | I18: Luar Negeri | R18: SDM Postdoc/VR
A19: 14 | B19: =IF(OR(E19<>"",F19<>""),IF(B19="",NOW(),B19),"") -> 45989.574 | C19: November | E19: M. Yudhi Rezaldi, Ph.D | F19: Associate. Prof. Dr. Nazlena Mohamad Ali | G19: Interaksi Manusia-Komputer dan Visualisasi (Human Computer Interaction and Visualisation) | H19: VISITING RESEARCH | I19: Luar Negeri | Q19: Visiting Researcher on 14th – 17th October 2025 | R19: SDM Postdoc/VR | S19: Sudah
A20: 15 | B20: =IF(OR(E20<>"",F20<>""),IF(B20="",NOW(),B20),"") -> 45993.693 | C20: Triwulan IV | E20: Rezzy Eko Caraka ,S.Si.,M.Sc(RES).,PhD. | G20: Pemerintahan Digital (Digital Government) | H20: VISITING RESEARCH | I20: Luar Negeri | Q20: Â 2025 Alumni Workshop on Local Actions for Disaster Risk Reduction and Climate Change Adaptation (Thailand) | R20: SDM Postdoc/VR | S20: Sudah
A21: 16 | B21: =IF(OR(E21<>"",F21<>""),IF(B21="",NOW(),B21),"") -> 45999.602 | C21: Triwulan IV | E21: Dr. Eng. Ir Yuyun, S.Kom., M.T | G21: Pengolahan Bahasa Alami (Natural Language Processing) | H21: PESERTA PELATIHAN INTERNASIONAL | I21: Luar Negeri | Q21: The first workshop on Asian Multi-Cultural LLM by National Institute of Information and Communications Technology (NICT). Kegiatan ini dilaksanakan pada tanggal 4-5 Desember 2025 di Kyoto, Japan. Workshop di bidang AI ini membahas tentang: Bagaimana LLM global saat ini juga dapat memahami dan mengcover konteks multibudaya di Asia. Selain itu Sensitif terhadap perbedaan budaya, konteks sosial, dan nilai-nilai lokal LLM menjadi issue global yg menjadi perhatian pada saat workshop. | R21: SDM Postdoc/VR | S21: Sudah
A22: 17 | B22: =IF(OR(E22<>"",F22<>""),IF(B22="",NOW(),B22),"") | R22: SDM Postdoc/VR
A23: 18 | B23: =IF(OR(E23<>"",F23<>""),IF(B23="",NOW(),B23),"") | R23: SDM Postdoc/VR
A24: 19 | B24: =IF(OR(E24<>"",F24<>""),IF(B24="",NOW(),B24),"") | R24: SDM Postdoc/VR
A25: 20 | B25: =IF(OR(E25<>"",F25<>""),IF(B25="",NOW(),B25),"") | R25: SDM Postdoc/VR
A26: 21 | B26: =IF(OR(E26<>"",F26<>""),IF(B26="",NOW(),B26),"") | R26: SDM Postdoc/VR
A27: 22 | B27: =IF(OR(E27<>"",F27<>""),IF(B27="",NOW(),B27),"") | R27: SDM Postdoc/VR
A28: 23 | B28: =IF(OR(E28<>"",F28<>""),IF(B28="",NOW(),B28),"") | R28: SDM Postdoc/VR
A29: 24 | B29: =IF(OR(E29<>"",F29<>""),IF(B29="",NOW(),B29),"") | R29: SDM Postdoc/VR
A30: 25 | B30: =IF(OR(E30<>"",F30<>""),IF(B30="",NOW(),B30),"") | R30: SDM Postdoc/VR
A31: 26 | B31: =IF(OR(E31<>"",F31<>""),IF(B31="",NOW(),B31),"") | R31: SDM Postdoc/VR
H33: 3

Sheet KI
A1: KEKAYAAN INTELEKTUAL
A2: DIISI OLEH PJ MONEV | E2: PUSAT RISET SAINS DATA DAN INFORMASI | G2: INVENTOR SIVITAS PRSDI | T2: PENDAFTARAN | V2: SERTIFIKAT | X2: EVIDEN/DAKUNG
A3: NO | B3: Periode Input | C3: Periode Stamp | E3: JUDUL | F3: KELOMPOK RISET | G3: 1 | H3: 2 | I3: 3 | J3: 4 | K3: 5 | L3: 6 | M3: 7 | N3: 8 | O3: 9 | P3: 10 | Q3: NON SIVITAS PRSDI | R3: STATUS | S3: JENIS | T3: NO | U3: TANGGAL | V3: NO | W3: TANGGAL | X3: LINK UPLOAD | Y3: STATUS UPLOAD | Z3: CATATAN
A4: 1 | B4: =IF(E4<>"",IF(B4="",NOW(),B4),"") -> 45742.433 | E4: Sistem Manajemen Warehouse dan Point of Sales (POS) E-commerce | F4: Interaksi Manusia-Komputer dan Visualisasi (Human Computer Interaction and Visualisation) | G4: Arafat Febriandirza, Ph.D | H4: Dr. Eng. Budi Nugroho | I4: Dr. Ambar Yoganingrum | J4: M. Yudhi Rezaldi, Ph.D | K4: Abdurrakhman Prasetyadi, M.P | L4: Christine Cecylia Munthe, S.Kom. | Q4: Marcellito Vido Triwibowo, Dery Andrian Pratama | R4: Terdaftar DJKI | S4: Hak Cipta | T4: EC002024249615 | U4: 45637 | V4: 000822047 | W4: 45637 | X4: KI | Y4: Sudah | Z4: Capaian tahun 2024 yang belum diklaim (Sudah diklaim pada di Tw 4 Th. 2024) | AB4: =IFERROR(__xludf.DUMMYFUNCTION("IMPORTRANGE(""https://docs.google.com/spreadsheets/d/1uREY05dC3v6oTR1bLI-b3VlRJk1GrRaib0uwUj-1r_A/edit"", ""KI!B3:E800"")"),"#REF!") -> #REF!
A5: 2 | B5: =IF(E5<>"",IF(B5="",NOW(),B5),"") -> 45739.71 | E5: Desain Industri Dispenser Sistem Pengisian Kendaraan Listrik Roda 4 Arus Bolak Balik | F5: Rekayasa Pengetahuan dan Data (Knowledge and Data Engineering) | S5: Desain Industri | T5: A00202201124 | U5: 44658 | V5: IDD000072843 | X5: KI | Y5: Sudah | Z5: diklaim nomor 33 | AB5: SISTEM MULTI-SENSOR UNTUK AKUAKULTUR BERBASIS INTERNET OF THINGS LORA | AC5: Terdaftar DJKI | AD5: P00202314662 | AE5: PRT
A6: 3 | B6: =IF(E6<>"",IF(B6="",NOW(),B6),"") -> 45805.672 | C6: Mei | E6: Chatbot Lisa (Hemodialisa) versi 2.0 berbasis LLM+RAG | F6: Pengolahan Bahasa Alami (Natural Language Processing) | G6: Elvira Nurfadhilah, S.Komp., M. Kom | H6: Agung Santosa, BSEE, M.Kom | I6: Prabu Kresna Putra, S.T., M.T.I. | J6: Siska Pebiana S.Kom., M.Kom. | K6: Radhiyatul Fajri, S.Kom, M.Pd.T, M.Kom. | L6: M. Teduh Uliniansyah, B.Eng., M.Sc., Ph.D. | M6: Lyla Ruslana Aini | R6: Terdaftar DJKI | S6: Hak Cipta | T6: EC002025048065 | U6: 45786 | X6: KI | Y6: Sudah | Z6: https://pdki-indonesia.dgip.go.id/detail/e3b0c44298fc1c149afbf4c8996fb92427ae41e4649b934ca495991b7852b855 | AB6: KOMPOSIT MAGNETIK BERBASIS LOGAM TANAH JARANG DAN PROSES PEMBUATANNYA | AC6: Tersertifikasi | AD6: P00202104099
A7: 4 | B7: =IF(E7<>"",IF(B7="",NOW(),B7),"") -> 45807.403 | D7: ☑️ | E7: Chatbot Lisa (Hemodialisa) versi 2.0 berbasis LLM+RAG | F7: Interaksi Manusia-Komputer dan Visualisasi (Human Computer Interaction and Visualisation) | G7: Dr. Esa Prakasa, MT | R7: Terdaftar DJKI | S7: Hak Cipta | T7: EC002025048065 | U7: 45786 | X7: KI | Y7: Sudah | Z7: https://pdki-indonesia.dgip.go.id/detail/e3b0c44298fc1c149afbf4c8996fb92427ae41e4649b934ca495991b7852b855 | AB7: SINTESIS KOMPOSIT Fe3O4NPs/rGO BERBASIS BAHAN ALAMPASIR BESI | AC7: Tersertifikasi | AD7: EC00202419546
A8: 5 | B8: =IF(E8<>"",IF(B8="",NOW(),B8),"") -> 45811.353 | C8: Triwulan II | E8: Sistem Big Data Bahasa dan Sastra Lisan Perbatasan (BAHASAN) | F8: Rekayasa Pengetahuan dan Data (Knowledge and Data Engineering) | G8: Dr. Foni Agus Setiawan, M.Kom. | Q8: Yusup Irawan, Dedy Ari Asfar, Irmayani, Herpanus, Muhammad Pramulya, Lilian Slow | R8: Tersertifikasi | S8: Hak Cipta | T8: EC002025055955 | U8: 27 Mei 2025 | X8: KI | Y8: Sudah | AB8: Mobile Smart Farm Monitoring | AC8: Tersertifikasi | AD8: EC00202455902
A9: 6 | B9: =IF(E9<>"",IF(B9="",NOW(),B9),"") -> 45811.358 | C9: Triwulan II | E9: Aset Game 2D/3D Indonesia Timur | F9: Interaksi Manusia-Komputer dan Visualisasi (Human Computer Interaction and Visualisation) | G9: M. Yudhi Rezaldi, Ph.D | H9: Dr. Esa Prakasa, MT | I9: Abdurrakhman Prasetyadi, M.P | J9: Ridwan Suhud, S.Kom., M.T. | K9: Rio Nurtantyana, S.Pd., M.Pd., M.Sc., Ph.D. | L9: Aang Gunawan S, S.Kom., M.T. | Q9: Dian Andriana, Riky Taufik Afif, Yayat Sudaryat, Arief Budiman, Nisrina Qatrunnada, Adya Saladina Athaya, Moh. Reffy Aditya Dharma, Gian Daffa Sonjaya, Nurhidayani Sulfiany, Arief Aflah, Agus Setiawan, Purmaningrum Maeni, Erna Nurmalinda, Muammar Mochtar, Boy Irwan Budiman, Rakha Fadilah, Sarah Faradiba, Firas Shaquille Zharfan, Muhammad Fadhil Hamdani | R9: Tersertifikasi | S9: Hak Cipta | T9: EC002025055947 | U9: 27 Mei 2025 | V9: 000896208 | W9: 45804 | X9: KI | Y9: Sudah | AB9: SISTEM MULTISENSOR BERBASIS JARINGAN LoRa UNTUK PENGENDALIAN DAN MONITORING OTOMATIS PADA SISTEM HIDROPONIK DAN PERIKANAN PINTAR | AC9: Terdaftar DJKI | AD9: P00202403775
A10: 7 | B10: 45882 | C10: Agustus | E10: PLATFORM KTP ELEKTRONIK BERBASIS JAVA CARD DAN METODE PEMBUATAN APPLET JAVA CARD YANG TERKANDUNG PADANYA | F10: Pengolahan Bahasa Alami (Natural Language Processing) | G10: Ir. Andi Djalal Latief, M.S. | Q10: Dwidharma Priyasta Tasurun, Yudi Purwantoro, Wahyu Cesar, Rully Kusumajaya, Afrias Sarotama, Fito Wigunanto Herminawan, Yanti Susanti, Widyanti, Melyana, Eka Setianingsih, Juliati Junde, Michael Andreas Purwoadi, Gembong Wibowanto, Firson Satriasta. | R10: Tersertifikasi | S10: Paten | T10: P00201800779 | U10: 43132 | V10: IDP000097336 B | W10: 45680 | X10: KI | Y10: Sudah | AB10: DICOM AUTOMATION RECOVERY MANAGER | AC10: Terdaftar DJKI | AD10: EC00202455897
A11: 8 | B11: =IF(E11<>"",IF(B11="",NOW(),B11),"") -> 45894.381 | E11: Alat pengidentifikasi Wereng Batang Coklat (YUKE-WBC) | F11: Temu Kembali Informasi (Information Retrieval) | G11: Dr. Wiwin Suwarningsih, M.T. | Q11: Arlyna Budi Pustika, Efendi Zaenudin, Sutomo, Hendra Helmanto, Ani Mugiasih, Setyorini Widyayanti, Rahmini, Raden Heru Praptana, Gagad Restu Pratiwi, Sudarmaji, Kristamtini, Sigid Handoko, Wawan Sulistiono, Sugeng Widodo, Rizki Pradana, Chimayatus Solichah, Legi Kuswandi | R11: Submit MKI | S11: Hak Cipta | X11: KI | AB11: RADAR APERTUR SINTETIS MENGGUNAKAN REPEATER DIGITAL UNTUK APLIKASI PESAWAT TANPA AWAK | AC11: Terdaftar DJKI | AD11: P00202405995
A12: 9 | B12: =IF(E12<>"",IF(B12="",NOW(),B12),"") -> 45894.443 | E12: Animasi Hemodialisis | F12: Interaksi Manusia-Komputer dan Visualisasi (Human Computer Interaction and Visualisation) | G12: M. Yudhi Rezaldi, Ph.D | Q12: IRFAN DWI RAHADIANTO, RAFI ADRI DINAN. MUHAMMAD ARSYAMSUHENTRI, MUHAMMAD AMMARRAMADHANA, MOHAMMAD RAFLIHARDIANSYAH | R12: Tersertifikasi | S12: Hak Cipta | T12: EC002025107177 | U12: 45876 | V12: 000947438 | W12: 45876 | X12: KI | Y12: Sudah | Z12: Mohon lampirkan PKS dg Telkom University (Sdh direvisi dengan melampirkan PKS) | AB12: PERANGKAT PEMANTAUAN DAN KENDALI OTOMATIS UNTUK HIDROPONIK DAN PERIKANAN | AC12: Tersertifikasi | AD12: IDD000070688
A13: 10 | B13: =IF(E13<>"",IF(B13="",NOW(),B13),"") -> 45926.901 | C13: Oktober | E13: Dataset Prediksi Parameter Keselamatan Termal-Hidraulik Kritis pada Peristiwa Station Blackout (SBO) di PLTN AP1000 | F13: Rekayasa Pengetahuan dan Data (Knowledge and Data Engineering) | G13: Dr. Arya Adhyaksa Waskita, M.Si | Q13: Andi Sofrany Ekariansyah, Sudarno, Deswandri, Anggraini Ratih Kumaraningrum, Ratih Luhuring Tyas, Restu Maerani | R13: Terdaftar DJKI | S13: Hak Cipta | T13: EC002025132934 | U13: 16-09-2025 | X13: KI | Y13: Sudah | Z13: https://pdki-indonesia.dgip.go.id/detail/e3b0c44298fc1c149afbf4c8996fb92427ae41e4649b934ca495991b7852b855 | AB13: KOTAK STERILISASI MENGGUNAKAN SINAR UV-C YANG DILENGKAPI PENGGERAK PENUTUP | AC13: Tersertifikasi | AD13: IDP000092217
A14: 11 | B14: =IF(E14<>"",IF(B14="",NOW(),B14),"") -> 45928.361 | C14: Oktober | E14: HortiHeat Tracker | F14: Rekayasa Pengetahuan dan Data (Knowledge and Data Engineering) | G14: Satrio Adi Priyambada, S.Kom., M.Kom., Ph.D. | Q14: Mathias Prathama | R14: Terdaftar DJKI | S14: Hak Cipta | T14: EC002025132930 | U14: 04-07-2025 | X14: KI | Y14: Sudah | Z14: https://pdki-indonesia.dgip.go.id/detail/e3b0c44298fc1c149afbf4c8996fb92427ae41e4649b934ca495991b7852b855 | AB14: RADAR APERTUR SINTETIS DENGAN DURASI WAKTU SINYAL CHIRP BERUBAH SECARA OTOMATIS MENGIKUTI KETINGGIAN PESAWAT UDARA | AC14: Terdaftar DJKI | AD14: P00202406442
A15: 12 | B15: =IF(E15<>"",IF(B15="",NOW(),B15),"") -> 45928.4 | C15: Oktober | E15: Aset Game 2D/3D Indonesia Timur Seri 2 | F15: Interaksi Manusia-Komputer dan Visualisasi (Human Computer Interaction and Visualisation) | G15: M. Yudhi Rezaldi, Ph.D | H15: Dr. Ambar Yoganingrum | I15: Dr. Esa Prakasa, MT | J15: Abdurrakhman Prasetyadi, M.P | K15: Ridwan Suhud, S.Kom., M.T. | L15: Rio Nurtantyana, S.Pd., M.Pd., M.Sc., Ph.D. | M15: Aang Gunawan S, S.Kom., M.T. | N15: Prof. Dr. Ana Hadiana, M.Eng.Sc. | O15: Aria Bisri, S.Kom. M.T. | P15: Rumadi, S.T., M.T. | Q15: Dian Andriana, Muhammad Reza Pujiyanto, Ratu Berliana Nursabrina Shiddiq, Dayfa Sahla Azeeza, Lala Lailatul Badriah, Justin Zidane Chaniago, Siti Rahmani Wulandari, Malika Adilah Tatyana Usman, Bagas Ananta Mardjuki, Muhammad Angga Nabil Saputra, Sayid Muhammad Athaya Rahman, Mario, Tiara Radinska Deanda, Arief Budiman, Muhammad Adharamadinka, Yayat Sudaryat, Irfan Dwi Rahadianto. | R15: Terdaftar DJKI | S15: Hak Cipta | T15: EC002025132928 | U15: 11-06-2025 | X15: KI | Y15: Sudah | Z15: https://pdki-indonesia.dgip.go.id/detail/e3b0c44298fc1c149afbf4c8996fb92427ae41e4649b934ca495991b7852b855 | AB15: material penyerap gelombang radar berbasis nanokomposit Zno/polianilin/cat epoksi | AC15: Terdaftar DJKI | AD15: P00202406771
A16: 13 | B16: =IF(E16<>"",IF(B16="",NOW(),B16),"") -> 45928.41 | C16: Oktober | E16: LIKOE - A Simple Liquefaction Analysis Tool | F16: Pengolahan Bahasa Alami (Natural Language Processing) | G16: Dr. Kokoy Siti Komariah S.Kom., M.T., M.Eng. | H16: Satrio Adi Priyambada, S.Kom., M.Kom., Ph.D. | Q16: Wa Ode Sumartini, Volvariella Volvacea, Adi Susilo | R16: Terdaftar DJKI | S16: Hak Cipta | T16: EC002025132933 | U16: 45873 | X16: KI | Y16: Sudah | Z16: https://pdki-indonesia.dgip.go.id/detail/e3b0c44298fc1c149afbf4c8996fb92427ae41e4649b934ca495991b7852b855 | AB16: ANTENA HORN BERPITA LEBAR YANG DAPAT DIKONFIGURASI SEBAGAI TIGA JENIS ANTENA: ANTENA HORN KONVENSIONAL, DOUBLE RIDGED, DAN QUAD RIDGED | AC16: Terdaftar DJKI | AD16: P00202411129
A17: 14 | B17: =IF(E17<>"",IF(B17="",NOW(),B17),"") -> 45936.78 | C17: Oktober | E17: TerraClassify | F17: Pengolahan Bahasa Alami (Natural Language Processing) | G17: Lyla Ruslana Aini | Q17: Rachmawan Atmaji Perdana, S.Kom., Mohammad Hamdani, S.T., M.TI, Tanzi Mubaroq Santoso, S.Kom., Risnandar, Ph.D, Fara Ayuningtyas, S.Kom., Monica Dwi Wahyu Sumunaringrum, ST. | R17: Terdaftar DJKI | S17: Hak Cipta | T17: EC002025142803, | U17: 45929 | X17: KI | Y17: Sudah | Z17: https://pdki-indonesia.dgip.go.id/detail/e3b0c44298fc1c149afbf4c8996fb92427ae41e4649b934ca495991b7852b855 | AB17: METODE DEPOSISI LAPISAN TIPIS BiFeO3 TERSUBSTITUSI Gd DAN Ce SEBAGAI MATERIAL PENYERAP GELOMBANG ELEKTROMAGNETIK DAN PRODUK YANG DIHASILKANNYA | AC17: Terdaftar DJKI | AD17: P00202411155
A18: 15 | B18: =IF(E18<>"",IF(B18="",NOW(),B18),"") -> 45938.832 | C18: Oktober | E18: Aplikasi Pemrosesan Data SAR Sentinel-1 untuk Analysis Ready Data (ARD) Time Series dalam Pemantauan Periodik Lahan Sawah | F18: Pemerintahan Digital (Digital Government) | G18: Hengki Muradi, M.Si. | Q18: Dede Dirgahayu Domiri I Made Parsa Hilda Ayu Pratikasiwi Siti Nadia Nurhidayah R. Johannes Manalu Kurdianto Yanuar Ryan Irawan | R18: Terdaftar DJKI | S18: Hak Cipta | T18: EC002025142801 | U18: 29-09-2025 | X18: KI | Y18: Sudah | Z18: https://pdki-indonesia.dgip.go.id/detail/e3b0c44298fc1c149afbf4c8996fb92427ae41e4649b934ca495991b7852b855 | AB18: PLATFORM MOBILITAS PERORANGAN EMPAT RODA DENGAN SUSPENSI INDEPENDEN | AC18: Terdaftar DJKI | AD18: P00202412827
A19: 16 | B19: =IF(E19<>"",IF(B19="",NOW(),B19),"") -> 0 | C19: Oktober | E19: Collab Identifier | F19: Interaksi Manusia-Komputer dan Visualisasi (Human Computer Interaction and Visualisation) | G19: Rumadi, S.T., M.T. | H19: Dr. Ambar Yoganingrum | I19: Abdurrakhman Prasetyadi, M.P | J19: Aria Bisri, S.Kom. M.T. | Q19: Dimas Bratakusumah; Dian Raisa Gumilar; Diash Firdaus; Yusup Miftahuddin | R19: Tersertifikasi | S19: Hak Cipta | T19: EC002025156074 | U19: 45824 | V19: 000996335 | W19: 45946 | X19: KI | Y19: Sudah | Z19: https://pdki-indonesia.dgip.go.id/detail/e3b0c44298fc1c149afbf4c8996fb92427ae41e4649b934ca495991b7852b855 | AB19: PERANGKAT LAMPU PELAMPUNG SUAR PINTAR DENGAN PENGATURAN KODE KARAKTER CELANG LAMPU SECARA JARAK JAUH MENGGUNAKAN JARINGAN LORA | AC19: Terdaftar DJKI | AD19: P00202412810
A20: 17 | B20: =IF(E20<>"",IF(B20="",NOW(),B20),"") -> 45953.437 | C20: Triwulan IV | E20: Dataset Citra Satelit Sentinel-1 (VH dan RPI) Komposit 15 Harian untuk Pemodelan Fase Pertumbuhan Padi Nasional tahun 2025 | F20: Pemerintahan Digital (Digital Government) | G20: Hengki Muradi, M.Si. | R20: Terdaftar DJKI | S20: Hak Cipta | T20: EC002025209704 | U20: 10/12/2025 | X20: KI | Y20: Sudah | AB20: PROSES PEMBUATAN KOMPOSIT CS-RGO DENGAN PENAMBAHAN CEO2 DAN RESIN EPOKSI MENGGUNAKAN METODE HUMMER TERMODIFIKASI | AC20: Terdaftar DJKI | AD20: P00202412830
A21: 18 | B21: =IF(E21<>"",IF(B21="",NOW(),B21),"") -> 0 | E21: Warna Bumi: aplikasi konversi kode warna tanah Munsell ke nama dalam bahasa Inggris dan Indonesia dan sebaliknya | F21: Temu Kembali Informasi (Information Retrieval) | G21: Andria Arisal, M. Eng. | Q21: Destika Cahyana, Bambang Setiadi, Sukarman, Anny Mulyani, Muhammad Hikmat, Edi Yatno, Vicca Karolinoerita, Diah Puspita Hati, Rachmat Abdul Gani, Mira Media Pratamaningsih | R21: Terdaftar DJKI | S21: Hak Cipta | T21: EC002025209675 | U21: 10/12/2025 | X21: KI | Y21: Sudah | Z21: https://pdki-indonesia.dgip.go.id/detail/e3b0c44298fc1c149afbf4c8996fb92427ae41e4649b934ca495991b7852b855 | AB21: SISTEM PEMINDAIAN AREA TAMPAK MUKA PADA BENDA 3 DIMENSI MENGGUNAKAN LIDAR PUTAR DENGAN SUDUT GERAK TERBATAS | AC21: Terdaftar DJKI | AD21: P00202412801
A22: 19 | B22: =IF(E22<>"",IF(B22="",NOW(),B22),"") -> 45953.637 | C22: Oktober | E22: Sistem Prediksi Potensi Bullying melalui Pola Emosi berbasis SuaraMenggunakan Deep Learning | F22: Pengolahan Bahasa Alami (Natural Language Processing) | G22: Dr. Dipl.(FH) Ing Asril, M.Sc | H22: Agung Santosa, BSEE, M.Kom | Q22: PUTU HARRY GUNAWAN YESY DIAH ROSITA Yohana Wuri Satwika Arfin Nurma Halida RIFKI WIJAYA Insan Ramadhan TJOKORDA AGUNG BUDIWIRAYUDA Rully Kusumajaya I NYOMAN MANUTAMA SURYAJAGADHITA ANANDA ARTI WIDIGDO BRYAN DHANIEL | R22: Terdaftar DJKI | S22: Hak Cipta | T22: EC002025149137 | U22: 45938 | V22: 000989398 | W22: 45932 | X22: KI | Y22: Sudah | Z22: https://pdki-indonesia.dgip.go.id/detail/e3b0c44298fc1c149afbf4c8996fb92427ae41e4649b934ca495991b7852b855 | AB22: TAPIS LOLOS PITA (BANDPASS FILTER) MENGGUNAKAN KAPASITOR YANG DITALA | AC22: Tersertifikasi | AD22: S00201700696
A23: 20 | B23: 45953 | E23: Aset Game 2D/3D Indonesia Timur Seri 2 | F23: Interaksi Manusia-Komputer dan Visualisasi (Human Computer Interaction and Visualisation) | G23: M. Yudhi Rezaldi, Ph.D | H23: Dr. Ambar Yoganingrum | I23: Dr. Esa Prakasa, MT | J23: Abdurrakhman Prasetyadi, M.P | K23: Ridwan Suhud, S.Kom., M.T. | L23: Rio Nurtantyana, S.Pd., M.Pd., M.Sc., Ph.D. | M23: Aang Gunawan S, S.Kom., M.T. | N23: Prof. Dr. Ana Hadiana, M.Eng.Sc. | O23: Aria Bisri, S.Kom. M.T. | P23: Rumadi, S.T., M.T. | Q23: Dian Andriana, Muhammad Reza Pujiyanto, Ratu Berliana Nursabrina Shiddiq, Dayfa Sahla Azeeza, Lala Lailatul Badriah, Justin Zidane Chaniago, Siti Rahmani Wulandari, Malika Adilah Tatyana Usman, Bagas Ananta Mardjuki, Muhammad Angga Nabil Saputra, Sayid Muhammad Athaya Rahman, Mario, Tiara Radinska Deanda, Arief Budiman, Muhammad Adharamadinka, Yayat Sudaryat, Irfan Dwi Rahadianto | R23: Terdaftar DJKI | S23: Hak Cipta | T23: EC002025132928 | U23: 45916 | V23: 000973189 | W23: 45819 | X23: KI | Y23: Sudah | Z23: Sudah di Klain Nomor 12 | AB23: METODE SINKRONISASI WAKTU SIMBOL YANG DIKOMBINASIKAN DENGAN MESIN PEMBELAJARAN EKSTREM | AC23: Terdaftar DJKI | AD23: P00202414490
A24: 21 | B24: =IF(E24<>"",IF(B24="",NOW(),B24),"") -> 45953.819 | C24: Oktober | E24: METODE PELAPISAN Ni-P-La UNTUK MENINGKATKAN KETAHANAN KOROSI PADA PADUAN ALUMINIUM | F24: Rekayasa Pengetahuan dan Data (Knowledge and Data Engineering) | G24: Dr. Arya Adhyaksa Waskita, M.Si | Q24: Rahayu Kusumastuti; Gadang Priyotomo; Arini Nikitasari; Siska Prifiharni; Siti Musabikha; Yulinda Lestari; Ahmad Royani; Sriyono; Jan Setiawan; Joko Triwardono | R24: Terdaftar DJKI | S24: Paten | T24: S00202508941 | U24: 45916 | X24: KI | Y24: Sudah | Z24: https://pdki-indonesia.dgip.go.id/detail/e3b0c44298fc1c149afbf4c8996fb92427ae41e4649b934ca495991b7852b855 | AB24: METODE DAN SISTEM KENDALI GERAK RODA UNTUK KENDARAAN LISTRIK RINGAN MENGGUNAKAN MIKROKONTROLER DAN MOTOR BLDC | AC24: Terdaftar DJKI | AD24: P00202414645
A25: 22 | B25: =IF(E25<>"",IF(B25="",NOW(),B25),"") -> 45953.828 | C25: Oktober | E25: Program Komputer Perangkat Spatial Decision Support System (SDSS) Site Selection Rumah Tahan Gempa, Tahan Api, Cepat Bangun, dan Murah (SDSS Site-RTM) | F25: Pengolahan Bahasa Alami (Natural Language Processing) | G25: Prabu Kresna Putra, S.T., M.T.I. | Q25: Dewayany Sutrisno Robby Arifandri Hari Prayogi Muhammad Iqbal Habibie Ati Rahadiati Udrekh Trevi Jayanti Puspasari Sukahar Eka Adi Saputra Amien Widodo | R25: Terdaftar DJKI | S25: Hak Cipta | T25: EC002025119060 | U25: 09/03/2025 | X25: KI | Y25: Sudah | Z25: https://pdki-indonesia.dgip.go.id/detail/e3b0c44298fc1c149afbf4c8996fb92427ae41e4649b934ca495991b7852b855 | AB25: Bat Identification | AC25: Tersertifikasi | AD25: EC00202474472 | AE25: PRSDI
A26: 23 | B26: =IF(E26<>"",IF(B26="",NOW(),B26),"") -> 45953.855 | C26: Oktober | E26: Software Simulasi Pendeteksian Teletsunami Berbasis Algoritma DLPT (Detection with Lengthening Prediction Time) | F26: Pengolahan Bahasa Alami (Natural Language Processing) | G26: Ir. Tri Sampurno, M.Sc | H26: Agung Santosa, BSEE, M.Kom | Q26: Fara Ayuningtyas Miranti Jatnika Riski Siti Shaleha Monica Dwi Wahyu | R26: Terdaftar DJKI | S26: Hak Cipta | T26: EC002025156084 | U26: 16 Oktober 2025 | X26: KI | Z26: https://pdki-indonesia.dgip.go.id/detail/e3b0c44298fc1c149afbf4c8996fb92427ae41e4649b934ca495991b7852b855 | AB26: A VRKom | AC26: Tersertifikasi | AD26: EC002024214042
A27: 24 | B27: =IF(A27<>"",IF(B27="",NOW(),B27),"") -> 45957.559 | C27: Oktober | E27: DESAIN ASET VISUAL GAME 2D MANGGARAI NUSA TENGGARA TIMUR | F27: Interaksi Manusia-Komputer dan Visualisasi (Human Computer Interaction and Visualisation) | G27: Aang Gunawan S, S.Kom., M.T. | Q27: 1 MOH. REFFY ADITYA DHARMA (TelU) 2 ARIEF BUDIMAN (TelU) 3 RIKY TAUFIK AFIF (TelU) | R27: Tersertifikasi | S27: Hak Cipta | T27: EC002025068412 | U27: 45825 | V27: 000908673 | W27: 45803 | X27: KI | Y27: Sudah | AB27: GANA (Game Asset Nusantara) | AC27: Tersertifikasi | AD27: EC00202496180
A28: 25 | B28: =IF(E28<>"",IF(B28="",NOW(),B28),"") -> 45964.739 | E28: Korpus Suara Bahasa Bugis | F28: Pengolahan Bahasa Alami (Natural Language Processing) | G28: M. Teduh Uliniansyah, B.Eng., M.Sc., Ph.D. | H28: Dr. Eng. Ir Yuyun, S.Kom., M.T | I28: Ir. Andi Djalal Latief, M.S. | J28: Radhiyatul Fajri, S.Kom, M.Pd.T, M.Kom. | K28: Elvira Nurfadhilah, S.Komp., M. Kom | L28: Nuraisa Novia Hidayati, S.Kom., M.Kom. | M28: Siska Pebiana S.Kom., M.Kom. | N28: Lyla Ruslana Aini | O28: Nuryani | Q28: Gusnawaty Hazriani Pammuda Mutahharah Nemin Kaharuddin Ita Rosvita Nurfaedah Jufri Munawirah | R28: Submit MKI | S28: Hak Cipta | X28: KI | AB28: Aplikasi Pemodelan Topik untuk Ekstraksi Informasi Menggunakan Parameter Bertopic Optimal | AC28: Tersertifikasi | AD28: EC00202490269
A29: 26 | B29: =IF(OR(E29<>"",F29<>""),IF(B29="",NOW(),B29),"") -> 45965.353 | E29: Dataset Kamus Elektronik Bahasa Indonesia untuk Pemrosesan Bahasa Alami | F29: Pengolahan Bahasa Alami (Natural Language Processing) | G29: Ir. Gunarso | H29: M. Teduh Uliniansyah, B.Eng., M.Sc., Ph.D. | I29: Agung Santosa, BSEE, M.Kom | J29: Dr. Dipl.(FH) Ing Asril, M.Sc | K29: Lyla Ruslana Aini | L29: Elvira Nurfadhilah, S.Komp., M. Kom | Q29: Dr. Hammam Riza | R29: Submit MKI | S29: Hak Cipta | X29: KI | AB29: Sistem pengolahan data sitasi dalam teks | AC29: Tersertifikasi | AD29: EC00202495435
A30: 27 | B30: 45965 | C30: Oktober | E30: POSLingua-IDEN | F30: Pengolahan Bahasa Alami (Natural Language Processing) | G30: Dr. Eng. Ir Yuyun, S.Kom., M.T | H30: Siska Pebiana S.Kom., M.Kom. | I30: Radhiyatul Fajri, S.Kom, M.Pd.T, M.Kom. | J30: M. Teduh Uliniansyah, B.Eng., M.Sc., Ph.D. | K30: Agung Santosa, BSEE, M.Kom | R30: Terdaftar DJKI | S30: Hak Cipta | T30: EC002025187798 | U30: 45950 | V30: 1028058 | W30: 45981 | X30: KI | Y30: Sudah | Z30: https://pdki-indonesia.dgip.go.id/detail/e3b0c44298fc1c149afbf4c8996fb92427ae41e4649b934ca495991b7852b855 | AB30: Bi-Project Aplikasi Penerjemahan Bahasa Isyarat Indonesia (BISINDO) Berbasis Web | AC30: Tersertifikasi | AD30: EC00202442772
A31: 28 | B31: 45965 | E31: IndoBugis 10K[2] - Dataset Korpus Paralel Bahasa Indonesia - Bugis | F31: Pengolahan Bahasa Alami (Natural Language Processing) | G31: Ir. Andi Djalal Latief, M.S. | H31: M. Teduh Uliniansyah, B.Eng., M.Sc., Ph.D. | I31: Dr. Eng. Ir Yuyun, S.Kom., M.T | J31: Agung Santosa, BSEE, M.Kom | K31: Elvira Nurfadhilah, S.Komp., M. Kom | L31: Nuraisa Novia Hidayati, S.Kom., M.Kom. | M31: Siska Pebiana S.Kom., M.Kom. | N31: Radhiyatul Fajri, S.Kom, M.Pd.T, M.Kom. | Q31: Gusnawaty Hazriani Nurfaedah Mutahharah Nemin Kaharuddin Itarosvita Pammuda | R31: Submit MKI | S31: Hak Cipta | X31: KI | AB31: DCPC: drug candidates for the prevention of COVID-19 | AC31: Tersertifikasi | AD31: EC00202455899
A32: 29 | B32: =IF(OR(E32<>"",F32<>""),IF(B32="",NOW(),B32),"") -> 45965.396 | C32: Triwulan IV | E32: Sistem Deteksi Berita Palsu dengan XAI dan Model Transformer Bahasa Indonesia | F32: Pengolahan Bahasa Alami (Natural Language Processing) | G32: Dr. Rini Wijayanti, S.Kom., M.Kom. | H32: Iftitahu Ni'mah, S.Kom., M.I.T. | I32: M. Teduh Uliniansyah, B.Eng., M.Sc., Ph.D. | J32: Dr. Eng. Ir Yuyun, S.Kom., M.T | Q32: Nakhwa Azizah Syifa Putri Fadhilla Timotius Devin Jansen | R32: Tersertifikasi | S32: Hak Cipta | T32: EC002025209700 | U32: 45915 | V32: 1049960 | W32: 46001 | X32: KI | Y32: Sudah | AB32: Watershed Health Assessment System (WHAS) | AC32: Tersertifikasi | AD32: EC002024249614
A33: 30 | B33: =IF(OR(E33<>"",F33<>""),IF(B33="",NOW(),B33),"") -> 45970.437 | E33: BugisLingua: Sistem Penerjemahan Multi-Bahasa ke Bahasa Bugis | F33: Pengolahan Bahasa Alami (Natural Language Processing) | G33: Dr. Eng. Ir Yuyun, S.Kom., M.T | H33: M. Teduh Uliniansyah, B.Eng., M.Sc., Ph.D. | I33: Ir. Andi Djalal Latief, M.S. | J33: Agung Santosa, BSEE, M.Kom | K33: Elvira Nurfadhilah, S.Komp., M. Kom | L33: Nuraisa Novia Hidayati, S.Kom., M.Kom. | M33: Siska Pebiana S.Kom., M.Kom. | N33: Radhiyatul Fajri, S.Kom, M.Pd.T, M.Kom. | O33: Nuryani | P33: Lyla Ruslana Aini | Q33: Gusnawaty Hazriani Nurfaedah Pammuda | R33: Submit MKI | S33: Hak Cipta | X33: KI | AB33: AViRSinami (Applikasi Virtual Reality SImulasi Tsunami) | AC33: Tersertifikasi | AD33: EC002024196831
A34: 31 | B34: =IF(OR(E34<>"",F34<>""),IF(B34="",NOW(),B34),"") -> 45973.498 | C34: Triwulan IV | E34: Sinkron-AIR: Chatbot Berbasis Large Language Model (LLM) untuk Sinkronisasi Dokumen Hukum Keamanan Laut | F34: Pengolahan Bahasa Alami (Natural Language Processing) | G34: Iftitahu Ni'mah, S.Kom., M.I.T. | H34: Nuraisa Novia Hidayati, S.Kom., M.Kom. | I34: Lyla Ruslana Aini | J34: Radhiyatul Fajri, S.Kom, M.Pd.T, M.Kom. | K34: Siska Pebiana S.Kom., M.Kom. | L34: Dr. Rini Wijayanti, S.Kom., M.Kom. | M34: M. Teduh Uliniansyah, B.Eng., M.Sc., Ph.D. | Q34: Emilia Yustiningrum, Sri Gilang Muhammad Sultan Rahma Putra, Amelya Gustina, Sutan Sorik, Rifki Sadikin, Amarulla Octavian | R34: Terdaftar DJKI | S34: Hak Cipta | T34: EC002025206593 | U34: 08-12-2025 | X34: KI | Y34: Sudah | AB34: IndoBugis 10K - Dataset Korpus Paralel Bahasa Indonesia - Bugis | AC34: Tersertifikasi | AD34: EC002024244160,
A35: 32 | B35: =IF(OR(E35<>"",F35<>""),IF(B35="",NOW(),B35),"") -> 45973.567 | C35: Triwulan IV | E35: Program Antarmuka untuk Klasifikasi Tingkatan Agtron Biji Kopi Panggang | F35: Temu Kembali Informasi (Information Retrieval) | G35: Irfan Asfy Fakhry Anto S.Kom., M.T | Q35: Taufik Ibnu Salim; Jony Winaryo Wibowo; Aris Munandar | R35: Tersertifikasi | S35: Hak Cipta | T35: EC002025187808 | U35: 45932 | V35: 1028068 | W35: 45981 | X35: KI | Y35: Sudah | AB35: Dataset VR Lab Komputer | AC35: Tersertifikasi | AD35: EC002024214033
A36: 33 | B36: =IF(OR(E36<>"",F36<>""),IF(B36="",NOW(),B36),"") -> 45973.578 | C36: November | E36: Dispenser Sistem Pengisian Kendaraan Listrik Roda 4 Arus Bolak Balik | F36: Rekayasa Pengetahuan dan Data (Knowledge and Data Engineering) | G36: Rahardito Dio Prastowo, S.T. | Q36: Dr. Khotimatul Fauziah ST, MT; Dr. Eka Rakhman Priandana, ST, MT; Adisa Larasati, ST; Yuli Astriani, ST, M.Phil; Dionysius Aldion Renata, S.Kom, M.Sc; Prasetyo Aji, S.Si, M.Inf; Munadiyan Nurhuda, ST; Hafsah Halidah, ST, M.Sc; Agus Suhendra, A.Md; Dony Damara, ST; Rahardito Dio Prastowo, ST; Dhea Amelia Rianjani, A.Md.; Zaenudin, SE; Zulramadhanie, ST; Fariz Maulana Rizanulhaq, ST; Ir. Ario Witjakso, MT; Ir. Riza, M.Eng; Ir. Ganesha Tri Chandrasa, M.Phil, M.Sc; Ir. Sudirman, MT; Suhraeni Syafei, ST; Dr. Ir. Barman Tambunan, IPU, APU | R36: Terdaftar DJKI | S36: Desain Industri | T36: A00202201124 | U36: 44658 | V36: IDD000072843 | W36: 45642 | X36: KI | Y36: Sudah | Z36: https://pdki-indonesia.dgip.go.id/detail/e3b0c44298fc1c149afbf4c8996fb92427ae41e4649b934ca495991b7852b855 | AB36: PosTagBugis3K - Dataset Part-of-Speech Tag Korpus Bahasa Bugis | AC36: Tersertifikasi | AD36: EC002024249616
A37: 34 | B37: =IF(OR(E37<>"",F37<>""),IF(B37="",NOW(),B37),"") -> 45973.591 | C37: Triwulan IV | E37: SDGs Mapping Tools | F37: Interaksi Manusia-Komputer dan Visualisasi (Human Computer Interaction and Visualisation) | G37: Rumadi, S.T., M.T. | H37: Dr. Ambar Yoganingrum | I37: Abdurrakhman Prasetyadi, M.P | J37: Aria Bisri, S.Kom. M.T. | Q37: Bimo Kusumo Putro Wicaksono, Evan Adkara Christian Putra, Yusry Anandita Yulianti | R37: Tersertifikasi | S37: Hak Cipta | T37: EC002025206582 | U37: 45899 | V37: 1046842 | W37: 45999 | X37: KI | Y37: Sudah | Z37: https://pdki-indonesia.dgip.go.id/detail/e3b0c44298fc1c149afbf4c8996fb92427ae41e4649b934ca495991b7852b855 | AB37: Chatbot Lisa (Hemodialisa) versi 1.0 | AC37: Tersertifikasi | AD37: EC00202490266
A38: 35 | B38: =IF(OR(E38<>"",F38<>""),IF(B38="",NOW(),B38),"") -> 45980.557 | C38: Triwulan IV | E38: Pemodelan 3D KST Samaun Samadikun | F38: Interaksi Manusia-Komputer dan Visualisasi (Human Computer Interaction and Visualisation) | G38: Abdurrakhman Prasetyadi, M.P | H38: Ridwan Suhud, S.Kom., M.T. | I38: M. Yudhi Rezaldi, Ph.D | Q38: Ayung Candra P., Raden Muhammad, Hariz Riski (UPI) | R38: Tersertifikasi | S38: Hak Cipta | T38: EC002025187861 | U38: 45981 | V38: 1028121 | W38: 45982 | X38: KI | Y38: Sudah | AB38: Dataset Berita Palsu Bahasa Indonesia Dengan Penelusuran Fakta Berbasis LLM | AC38: Tersertifikasi | AD38: EC002024214047
A39: 36 | B39: =IF(OR(E39<>"",F39<>""),IF(B39="",NOW(),B39),"") -> 45987.487 | C39: Triwulan IV | E39: Kalponik (Kalkulator Nutrisi Hidroponik) Digital kalkulator untuk penghitungan pupuk hidroponik AB Mix berdasarkan nilai N-total yang berbasis aplikasi Android | F39: Interaksi Manusia-Komputer dan Visualisasi (Human Computer Interaction and Visualisation) | G39: Rio Nurtantyana, S.Pd., M.Pd., M.Sc., Ph.D. | Q39: Mathias Prathama, Arief Nurrahman, Aristyo Hadikusuma, Tonny K. Moekasan, Wiwin Setiawati, Nikardi Gunadi, Neni Gunaeni, Eli Korlina Edisaputra, Yadi Suryadi, Bagus Kukuh Udiarto, Irna Surya Bidara | R39: Terdaftar DJKI | S39: Hak Cipta | T39: EC002025187800 | U39: 45981 | V39: 1028060 | W39: 45987 | X39: KI | Y39: Sudah | Z39: https://pdki-indonesia.dgip.go.id/detail/e3b0c44298fc1c149afbf4c8996fb92427ae41e4649b934ca495991b7852b855 | AB39: Sistem Pengenalan Wicara Otomatis Pendiktean Medis Bahasa Indonesia di Lingkungan Komputasi Awan | AC39: Terdaftar DJKI | AD39: P 00202315112
A40: 37 | B40: =IF(OR(E40<>"",F40<>""),IF(B40="",NOW(),B40),"") -> 45989.614 | C40: Triwulan IV | E40: DESAIN ASET VISUAL GAME 3D RUMAH ADAT NUSA TENGGARA TIMUR | F40: Interaksi Manusia-Komputer dan Visualisasi (Human Computer Interaction and Visualisation) | G40: M. Yudhi Rezaldi, Ph.D | Q40: ARIEF AFLAH, ARIEF BUDIMAN, RIKY TAUFIK AFIF | R40: Terdaftar DJKI | S40: Hak Cipta | T40: EC002025068377 | U40: 45825 | V40: 908638 | W40: 45805 | X40: KI | Y40: Sudah | AB40: IndoCia-Cia 60K Dataset Korpus Paralel Bahasa Indonesia ke Bahasa Cia-Cia | AC40: Tersertifikasi | AD40: EC002024244147,
A41: 38 | B41: =IF(OR(E41<>"",F41<>""),IF(B41="",NOW(),B41),"") -> 45989.637 | C41: Triwulan IV | E41: WebLabFon-ID versi 1.0 | F41: Pengolahan Bahasa Alami (Natural Language Processing) | G41: Agung Santosa, BSEE, M.Kom | H41: Dr. Dipl.(FH) Ing Asril, M.Sc | I41: M. Teduh Uliniansyah, B.Eng., M.Sc., Ph.D. | J41: Ir. Gunarso | K41: Lyla Ruslana Aini | L41: Elvira Nurfadhilah, S.Komp., M. Kom | M41: Siska Pebiana S.Kom., M.Kom. | R41: Tersertifikasi | S41: Hak Cipta | T41: EC002025187790 | U41: 45898 | V41: 001028050 | W41: 45989 | X41: KI | Y41: Sudah | AB41: IndoMakassar 9K - Dataset Kalimat Paralel Bahasa Indonesia dan Bahasa Makassar | AC41: Tersertifikasi | AD41: EC002024244148
A42: 39 | B42: =IF(OR(E42<>"",F42<>""),IF(B42="",NOW(),B42),"") -> 45992.386 | C42: Triwulan IV | E42: Backend-LabFon-ID versi 1.0 | F42: Pengolahan Bahasa Alami (Natural Language Processing) | G42: Agung Santosa, BSEE, M.Kom | H42: Dr. Dipl.(FH) Ing Asril, M.Sc | I42: M. Teduh Uliniansyah, B.Eng., M.Sc., Ph.D. | J42: Ir. Gunarso | K42: Lyla Ruslana Aini | L42: Elvira Nurfadhilah, S.Komp., M. Kom | M42: Siska Pebiana S.Kom., M.Kom. | R42: Terdaftar DJKI | S42: Hak Cipta | T42: EC002025187830 | U42: 45981 | X42: KI | Y42: Sudah | Z42: https://pdki-indonesia.dgip.go.id/detail/e3b0c44298fc1c149afbf4c8996fb92427ae41e4649b934ca495991b7852b855 | AB42: APLIKASI SISTEM PENDUKUNG KEPUTUSAN (DSS) SEMAR REBORN: PERIKANAN | AC42: Tersertifikasi | AD42: EC00202480381
A43: 40 | B43: =IF(OR(E43<>"",F43<>""),IF(B43="",NOW(),B43),"") -> 46002.463 | C43: Triwulan IV | E43: InaCOVED (Indonesian Corpus for COVID-19 Event Detection) on Online News 2.0 | F43: Temu Kembali Informasi (Information Retrieval) | G43: Dr. Purnomo Husnul Khotimah, M.T | H43: Andri Fachrur Rozie, M. Eng. | I43: Andria Arisal, M. Eng. | J43: Ekasari Nugraheni, M.T. | K43: Ir. Dianadewi Riswantini, M. Sc., M.B.A. | L43: Dr. Wiwin Suwarningsih, M.T. | M43: Nungki Dian Sulistyo Darmayanti | Q43: Nur Annisa Putri Rezkia, Nazla Dzaalika Ainaya, Erin Elfitriani, Anita Caroline Gunawan, Dian Kurniasari, Aang Nuryaman, Netti Herawati | R43: Tersertifikasi | S43: Hak Cipta | T43: EC002025209705 | U43: 46001 | V43: 1049965 | W43: 46001 | X43: KI | Y43: Sudah | AB43: BASIS DATA OSEANOGRAFI METEOROLOGI PERAIRAN PULAU MANTANG UNTUK DSS SEMAR REBORN | AC43: Tersertifikasi | AD43: EC00202482436
A44: 41 | B44: =IF(OR(E44<>"",F44<>""),IF(B44="",NOW(),B44),"") -> 46002.518 | C44: Triwulan IV | E44: iHoya Versi Mobile : Aplikasi Identifikasi Spesies Tanaman Hoya Indonesia | F44: Rekayasa Pengetahuan dan Data (Knowledge and Data Engineering) | G44: Siti Kania Kushadiani, S.T., M.Kom. | H44: Dr. Foni Agus Setiawan, M.Kom. | I44: Tedy Mutakin, S.T. | J44: Lindung Parningotan Manik, PDEng. | K44: Wawan Hendriawan Nur, S.Si., M.T. | L44: Muhamad Jafar Elly | R44: Tersertifikasi | S44: Hak Cipta | T44: EC002025187802 | U44: 20 November 2025 | X44: KI | Y44: Sudah | Z44: https://pdki-indonesia.dgip.go.id/detail/e3b0c44298fc1c149afbf4c8996fb92427ae41e4649b934ca495991b7852b855 | AB44: Indonesian News Aggregator | AC44: Tersertifikasi | AD44: EC002024223227
A45: 42 | B45: =IF(OR(E45<>"",F45<>""),IF(B45="",NOW(),B45),"") -> 46002.53 | C45: Triwulan IV | E45: Aplikasi Analisis Pengaruh Iklim terhadap Sebaran Tuberkulosis | F45: Temu Kembali Informasi (Information Retrieval) | G45: Devi Munandar, S.Kom., M.Mat. | H45: Dr. Purnomo Husnul Khotimah, M.T | I45: Ir. Dianadewi Riswantini, M. Sc., M.B.A. | Q45: Rifani Bhakti Natari, Muhammad Hafizh Izzaturrahim | R45: Tersertifikasi | S45: Hak Cipta | T45: EC002025187795 | U45: 10 Oktober 2025 | X45: KI | Y45: Sudah | Z45: https://pdki-indonesia.dgip.go.id/detail/e3b0c44298fc1c149afbf4c8996fb92427ae41e4649b934ca495991b7852b855 | AB45: Sistem Manajemen Warehouse dan Point of Sales (POS) E-commerce | AC45: Tersertifikasi | AD45: EC002024249615
A46: 43 | B46: =IF(OR(E46<>"",F46<>""),IF(B46="",NOW(),B46),"") -> 46002.537 | C46: Triwulan IV | E46: AUDITIN: Aplikasi Penilaian Keamanan Informasi Berdasarkan ISO 27001 | G46: Nungki Dian Sulistyo Darmayanti | Q46: Samsudiat Cahyono Nugroho Raden Muhammad Taufik Yuniantoro Andri Saputra Yudi Adityawarman Budhi Riyanto Lakmi Makarti Al Hafiz Akbar Maulana Siagian Shidiq Al Hakim | R46: Tersertifikasi | S46: Hak Cipta | T46: EC002025187825 | X46: KI | Y46: Sudah | Z46: https://pdki-indonesia.dgip.go.id/detail/e3b0c44298fc1c149afbf4c8996fb92427ae41e4649b934ca495991b7852b855 | AB46: Dashboard OSL (Observatorium Sesar Lembang) | AC46: Tersertifikasi | AD46: EC002024196836
A47: 44 | B47: =IF(OR(E47<>"",F47<>""),IF(B47="",NOW(),B47),"") -> 46005.726 | C47: Triwulan IV | E47: PlanktoScan | F47: Interaksi Manusia-Komputer dan Visualisasi (Human Computer Interaction and Visualisation) | G47: Dr. Esa Prakasa, MT | H47: Aria Bisri, S.Kom. M.T. | R47: Tersertifikasi | S47: Hak Cipta | T47: EC002025209701 | U47: 45894 | V47: 001049961 | W47: 45894 | X47: KI | Y47: Sudah | Z47: https://drive.google.com/file/d/1RYfxpVBJw2_BOuDxt3mR5aoSxzqMLeMn/view?usp=sharing | AB47: Fotogrametri Udara Daerah Gudangkahuripan - Lembang, Kabupaten Bandung Barat | AC47: Tersertifikasi | AD47: EC002024214034
A48: 45 | B48: 46005 | C48: Triwulan IV | E48: Avatar Pedagogis berbasis budaya | F48: Interaksi Manusia-Komputer dan Visualisasi (Human Computer Interaction and Visualisation) | G48: Dr. Ambar Yoganingrum | H48: Abdurrakhman Prasetyadi, M.P | Q48: Ratu Berliana Nursabrina Shiddiq, Tiara Radinska Deanda | R48: Tersertifikasi | S48: Hak Cipta | T48: EC002025206594 | U48: 45999 | V48: 1046854 | W48: 45999 | X48: KI | Y48: Sudah | Z48: https://drive.google.com/drive/folders/1PJhRr8JWP1ImktOjanI8MVrFzyEoPnTb | AB48: Aplikasi COI Sebagai Alat Deteksi Beban Ekonomi Akibat Leptospirosis | AC48: Tersertifikasi | AD48: EC002024196777
A49: 46 | B49: =IF(OR(E49<>"",F49<>""),IF(B49="",NOW(),B49),"") -> 46006.361 | C49: Triwulan IV | E49: Sistem Informasi Antisipasi Penyebaran Penyakit (SIAPP) | F49: Temu Kembali Informasi (Information Retrieval) | G49: Dr. Purnomo Husnul Khotimah, M.T | H49: Andri Fachrur Rozie, M. Eng. | I49: Andria Arisal, M. Eng. | J49: Ekasari Nugraheni, M.T. | K49: Ir. Dianadewi Riswantini, M. Sc., M.B.A. | L49: Dr. Wiwin Suwarningsih, M.T. | M49: Devi Munandar, S.Kom., M.Mat. | R49: Terdaftar DJKI | S49: Hak Cipta | T49: EC002025212503 | U49: 46003 | X49: KI | Y49: Sudah | AB49: Sistem Penilaian Kesiapan Research Data Management | AC49: Tersertifikasi | AD49: EC002024247596
A50: 47 | B50: =IF(OR(E50<>"",F50<>""),IF(B50="",NOW(),B50),"") -> 46006.396 | C50: Triwulan IV | E50: RekomendasiMenu: Aplikasi Rekomendasi Menu Makanan Sesuai Kebutuhan Nutrisi Masyarakat Indonesia | F50: Rekayasa Pengetahuan dan Data (Knowledge and Data Engineering) | G50: Siti Kania Kushadiani, S.T., M.Kom. | H50: Dr. Ekawati Marlina, S.T., M.T. | Q50: Al Hafiz Akbar Maulana Siagian, Ph.D. Ammar Widhianta, S.Kom. Dr. Diana Tri Susetianingtias, S.Kom., MMSI Dr. Rodiah, ST., MMSI. Dr. Shidiq Al Hakim, M.Eng. Dr. Trini Saptariani, S.Kom., MMSI. Niken Fitria Apriani, S.Kom., M.Kom. | R50: Terdaftar DJKI | S50: Hak Cipta | T50: EC002025209715 | U50: 10/12/2025 | X50: KI | Y50: Sudah | AB50: Jakarta Slum Area Segmentation Dataset | AC50: Tersertifikasi | AD50: EC002024245563
A51: 48 | B51: =IF(OR(E51<>"",F51<>""),IF(B51="",NOW(),B51),"") -> 46006.406 | C51: Triwulan IV | E51: Hydrological Modeling - Based Decision Support System (HMB-DSS) versi 1.0 | F51: Rekayasa Pengetahuan dan Data (Knowledge and Data Engineering) | G51: Dr. Foni Agus Setiawan, M.Kom. | Q51: Dr. Apip, M.Eng Dewi Verawati, S.T. Atiqotun Fitriyah, S.TP., M.Agr, PhD Siti Aisyah, S.Si, M.Si Widya Ningrum, M.Si Hendro Wibowo, M.Sc Dr. Luki Subehi, M.Sc | R51: Terdaftar DJKI | S51: Hak Cipta | T51: EC002025206578 | U51: 08/12/2025 | X51: KI | Y51: Sudah | Z51: https://pdki-indonesia.dgip.go.id/detail/e3b0c44298fc1c149afbf4c8996fb92427ae41e4649b934ca495991b7852b855 | AB51: AR-Deni: aplikasi interaktif berbasis mobile dengan teknologi augmented reality (AR) dan retrieval-augmented generation (RAG) untuk pembelajaran topik pembangkit listrik tenaga nuklir di Indonesia | AC51: Tersertifikasi | AD51: EC002024244155
A52: 49 | B52: =IF(OR(E52<>"",F52<>""),IF(B52="",NOW(),B52),"") | X52: KI | AB52: Aplikasi Penilaian Keamanan Aplikasi Berbasis Web | AC52: Tersertifikasi | AD52: EC002024214035
A53: 50 | B53: =IF(OR(E53<>"",F53<>""),IF(B53="",NOW(),B53),"") | X53: KI | AB53: Aplikasi Analisis Profil Pola Pengambilan Mata Kuliah Mahasiswa Berdasarkan Kesesuaiannya dengan Pedoman Kurikulum | AC53: Tersertifikasi | AD53: EC002024244161
A54: 51 | B54: =IF(OR(E54<>"",F54<>""),IF(B54="",NOW(),B54),"") | X54: KI | AB54: Aplikasi Penghapusan Awan dari Citra Satelit Sentinel-2 pada Band RGB dengan Metode Multi-Temporal Cloud Removal (MTCR) | AC54: Tersertifikasi | AD54: EC002024244180
A55: 52 | B55: =IF(OR(E55<>"",F55<>""),IF(B55="",NOW(),B55),"") | X55: KI | AB55: IHoya, Aplikasi Identifikasi Spesies Tanaman Hoya Indonesia | AC55: Tersertifikasi | AD55: EC002024233564
A56: 53 | B56: =IF(OR(E56<>"",F56<>""),IF(B56="",NOW(),B56),"") | X56: KI | AB56: Plugins TRIGRSMap | AC56: Tersertifikasi | AD56: EC002024245566
A57: 54 | B57: =IF(OR(E57<>"",F57<>""),IF(B57="",NOW(),B57),"") | X57: KI | AB57: Dataset Segmentasi Fitoplankton Perairan Belitung | AC57: Tersertifikasi | AD57: EC002024244169
A58: 55 | B58: =IF(OR(E58<>"",F58<>""),IF(B58="",NOW(),B58),"") | X58: KI | AB58: Dataset Data Training dan Testing untuk Klasifikasi Tutupan Lahan di Kabupaten Indramayu Berbasis Citra Satelit Sentinel-2A | AC58: Tersertifikasi | AD58: EC002024247600
A59: 56 | B59: =IF(OR(E59<>"",F59<>""),IF(B59="",NOW(),B59),"") | X59: KI | AB59: Dataset Lahan Tanaman Ilegal | AC59: Tersertifikasi | AD59: EC002024247590
A60: 57 | B60: =IF(OR(E60<>"",F60<>""),IF(B60="",NOW(),B60),"") | X60: KI | AB60: Aplikasi Audit Tools LATIK | AC60: Tersertifikasi | AD60: EC002024249617
A61: 58 | B61: =IF(OR(E61<>"",F61<>""),IF(B61="",NOW(),B61),"") | X61: KI | AB61: Aplikasi Pembelajaran Mesin Untuk Evaluasi Model Fase Padi (MODEPADI) | AC61: Tersertifikasi | AD61: EC002024245569
A62: 59 | B62: =IF(OR(E62<>"",F62<>""),IF(B62="",NOW(),B62),"") | X62: KI | AB62: GSS – (Gripper Sensor Simulator) Aplikasi untuk mengontrol gripper lengan robot dan visualisasi tactile sensor | AC62: Tersertifikasi | AD62: EC00202429279 | AE62: PRMC
A63: 60 | B63: =IF(OR(E63<>"",F63<>""),IF(B63="",NOW(),B63),"") | X63: KI | AB63: ARDV – MIT BIH Arrythmia DataBase Visualization | AC63: Tersertifikasi | AD63: EC00202429277
A64: 61 | B64: =IF(OR(E64<>"",F64<>""),IF(B64="",NOW(),B64),"") | X64: KI | AB64: ALAT DAN METODE UNTUK MEMBANGKITKAN GELEMBUNG NANO | AC64: Terdaftar DJKI | AD64: P00202400964
A65: 62 | B65: =IF(OR(E65<>"",F65<>""),IF(B65="",NOW(),B65),"") | X65: KI | AB65: Sistem Bahan Bakar Hidrogen untuk Kendaraan Bermotor | AC65: Tersertifikasi | AD65: P00201708593
A66: 63 | B66: =IF(OR(E66<>"",F66<>""),IF(B66="",NOW(),B66),"") | X66: KI | AB66: ALAT PENGIKAT EKSOSKELETON KAKI PADA TUBUH PENGGUNA | AC66: Tersertifikasi | AD66: S00202203558
A67: 64 | B67: =IF(OR(E67<>"",F67<>""),IF(B67="",NOW(),B67),"") | X67: KI | AB67: Casing Pistol | AC67: Tersertifikasi | AD67: A00202301642
A68: 65 | B68: =IF(OR(E68<>"",F68<>""),IF(B68="",NOW(),B68),"") | X68: KI | AB68: PEDAL REM PADA KENDARAAN LISTRIK RODA EMPAT | AC68: Terdaftar DJKI | AD68: P00202402948
A69: 66 | B69: =IF(OR(E69<>"",F69<>""),IF(B69="",NOW(),B69),"") | X69: KI | AB69: PLATFORM ROBOT BERODA YANG MAMPU BERADAPTASI DENGAN PERMUKAAN YANG TIDAK RATA DAN BIDANG MIRING | AC69: Terdaftar DJKI | AD69: P00202404365
A70: 67 | B70: =IF(OR(E70<>"",F70<>""),IF(B70="",NOW(),B70),"") | X70: KI | AB70: Alat dan proses produksi larutan teraktivasi plasma menggunakan elektroda kaustik serta produk yang dihasilkannya | AC70: Terdaftar DJKI | AD70: P00202406515
A71: 69 | B71: =IF(OR(E71<>"",F71<>""),IF(B71="",NOW(),B71),"") | X71: KI | AB71: Pemanfaatan Air Gelembung Berukuran Nano Meter Dengan Gas Nitrogen Dalam Meningkatkan Mutu Brokoli | AC71: Terdaftar DJKI | AD71: P00202405198
A72: 70 | B72: =IF(OR(E72<>"",F72<>""),IF(B72="",NOW(),B72),"") | X72: KI | AB72: Sistem dan Metode Pengendali Temperatur Kolam pada Pemijahan Ikan Air Tawar | AC72: Terdaftar DJKI | AD72: P00202407750
A73: 71 | B73: =IF(OR(E73<>"",F73<>""),IF(B73="",NOW(),B73),"") | X73: KI | AB73: ALAT KONTROL DAN METODE PENGGERAK KECEPATAN KENDARAAN HIBRID | AC73: Terdaftar DJKI | AD73: P00202408112
A74: 72 | B74: =IF(OR(E74<>"",F74<>""),IF(B74="",NOW(),B74),"") | X74: KI | AB74: PRODUKSI STEVIOSIDA DENGAN EKSTRAKSI MENGGUNAKAN KAVITASI MICROBUBBLE | AC74: Terdaftar DJKI | AD74: P00202408432
A75: 73 | B75: =IF(OR(E75<>"",F75<>""),IF(B75="",NOW(),B75),"") | X75: KI | AB75: Casing alat Pembaca Meteran Air menggunakan Kamera | AC75: Tersertifikasi | AD75: A00202304323
X76: KI | AB76: Pengendali Saklar Lampu Pasang-Pakai | AC76: Tersertifikasi | AD76: A00202302003
X77: KI | AB77: TROLI DISINFEKSI DAN STERILISASI UNTUK PESAWAT UDARA DAN BANDARA | AC77: Tersertifikasi | AD77: P00202010052
X78: KI | AB78: Akuasih : Alat Pemantauan Kualitas Air Bersih | AC78: Tersertifikasi | AD78: EC00202467249
X79: KI | AB79: TURBIN PENANGKAP ANGIN BUANG KONDENSOR AC | AC79: Terdaftar DJKI | AD79: S00202404644
X80: KI | AB80: METODE DAN SISTEM PENCAMPUR LARUTAN NUTRISI TANAH SECARA OTOMATIS UNTUK TANAMAN | AC80: Terdaftar DJKI | AD80: P00202410225
X81: KI | AB81: HMI-GCS FertiSense | AC81: Tersertifikasi | AD81: EC002024196815
X82: KI | AB82: Casing Baterai Untuk Scooter | AC82: Terdaftar DJKI | AD82: 2024-1726706837-uczw
X83: KI | AB83: Suspensi | AC83: Tersertifikasi | AD83: A00202204704
X84: KI | AB84: SISTEM KOMUNIKASI DAN METODE KONVERSI KENDARAAN KONVENSIONAL MENJADI KENDARAAN OTONOM | AC84: Terdaftar DJKI | AD84: P00202411145
X85: KI | AB85: METODE DETEKSI ESTRUS PADA DOMBA BERBASIS DETAK JANTUNG DAN SUHU | AC85: Terdaftar DJKI | AD85: P00202411998
X86: KI | AB86: PLATFORM MOBILITAS PERORANGAN EMPAT RODA DENGAN SUSPENSI INDEPENDEN | AC86: Terdaftar DJKI | AD86: P00202412827
X87: KI | AB87: Roda kemudi untuk kendaraan listrik mikro atau micro electric vehicle (MEVI) | AC87: Terdaftar DJKI | AD87: A00202406617
... X91: KI | AB91: Alat Pembangkit Listrik Tenaga Gelombang Laut Frekuensi Rendah Menggunakan Piezoelectric Nanogenerator | AC91: Terdaftar DJKI | AD91: P00202411983
AB92: SISTEM SUSPENSI KENDARAAN RODA TIGA TILTING DENGAN MENGGUNAKAN BALL JOINT DAN TIE ROD
AB93: Alat Bantu Lengan Exoskeleton untuk pemanen kelapa sawit | AC93: Terdaftar DJKI | AD93: S00202314825
AB94: Terminal Pelepasan Daya Baterai Lithium-Ion | AC94: Terdaftar DJKI | AD94: 2024-1721995715-nyl2
AB95: Sistem dan Metode Untuk Mengendalikan Kendaraan Listrik Menggunakan Mode Manual dan Mode Otonom | AC95: Terdaftar DJKI | AD95: P00202414638
AB96: Alat Bantu Eksoskeleton untuk Pekerjaan Manual | AC96: Terdaftar DJKI | AD96: P00202414808
AB97: SISTEM PENGGERAK SEPEDA MOTOR LISTRIK KONVERSI KOMPAK | AC97: Terdaftar DJKI | AD97: S00202411987
AB98: Arsitektur Sistem Mind-Controlled Drone Dengan Pemrosesan Sinyal EEG Berbasis Lab Streaming Layer | AC98: Tersertifikasi | AD98: EC002024246093
AB99: Sistem Robot Lengan Dan Metode Sortasi Berdasarkan Kondisi Objek Didalamnya Melalui Eksplorasi Taktil Dinamis | AC99: Terdaftar DJKI | AD99: P00202414978
AB100: Muatan Sampling Udara Vertikal Dengan Spme Terkendali Dipasang Pada UAV | AC100: Terdaftar DJKI | AD100: P00202415000
AB101: Perangkat Pengukur Kecepatan Berjalan Manusia | AC101: Terdaftar DJKI | AD101: P00202414499
AB102: SISTEM DAN METODE UNTUK UJI KECEPATAN INFILTRASI AIR TERHADAP TANAH TIGA ARAH BERBASIS INTERNET OF THINGS | AC102: Terdaftar DJKI | AD102: P00202412803
AB103: Metode In Vitro Pembesaran Plantet Dendrobium Menggunakan Media Nutrisi Cair Kaya Ultrafine Bubble Oksigen dan Vermiculite Perlite | AC103: Terdaftar DJKI | AD103: P00202414981
...

Sheet PN
A4: DIISI OLEH PJ MONEV | E4: PUSAT RISET SAINS DATA DAN INFORMASI | G4: PENULIS (SIVITAS PRSDI) | V4: JENIS DAKUNG
A5: NO | B5: Periode Input | C5: Periode Stamp | E5: JUDUL | F5: KELOMPOK RISET | G5: 1 | H5: 2 | I5: 3 | J5: 4 | K5: 5 | L5: 6 | M5: 7 | N5: 8 | O5: 9 | P5: 10 | Q5: NON SIVITAS PRSDI | R5: JENIS | S5: STATUS | T5: NAMA JURNAL/PROSIDING | U5: REPUTASI | V5: UPLOAD GDRIVE | W5: URL | X5: DOI (Wajib Jika status Published) | Y5: CATATAN
A6: 1 | B6: =IF(OR(E6<>"",F6<>""),IF(B6="",NOW(),B6),"") -> 45729.464 | E6: Optimizing Multi-Layer Perceptron performance in sentiment classification through Neural Network feature extraction | F6: Temu Kembali Informasi (Information Retrieval) | G6: Dr. Purnomo Husnul Khotimah, M.T | H6: Dr. DIPL. ING (FH) Anne Parlina, M.P. | I6: Andre Sihombing, S.Kom., M.Sc. | Q6: Muhammad Fikri, Aang Nuryaman | R6: Jurnal | S6: Published | T6: Baca: Jurnal Dokumentasi dan Informasi | U6: S2 | V6: PN
A7: 2 | B7: =IF(OR(E7<>"",F7<>""),IF(B7="",NOW(),B7),"") -> 45800.193 | C7: Mei | E7: Digital Representation Of Women Politicians In Indonesia: Youth Perspectives And Self-Portrayal On Social Media | F7: Temu Kembali Informasi (Information Retrieval) | G7: Dr. DIPL. ING (FH) Anne Parlina, M.P. | Q7: Riri Kusumarani, Darmawati Majid, Ari Cahyo Nugroho | R7: Jurnal | S7: Published | T7: Jurnal Wacana Politik | U7: S2 | V7: PN | W7: https://www.researchgate.net/publication/391722086_DIGITAL_REPRESENTATION_OF_WOMEN_POLITICIANS_IN_INDONESIA_YOUTH_PERSPECTIVES_AND_SELF-PORTRAYAL_ON_SOCIAL_MEDIA | X7: https://doi.org/10.24198/jwp.v10i2.59148
A8: 3 | B8: =IF(OR(E8<>"",F8<>""),IF(B8="",NOW(),B8),"") -> 45832.468 | C8: Oktober | E8: Promosi Kebudayaan Rote Melalui Aset 3D | F8: Interaksi Manusia-Komputer dan Visualisasi (Human Computer Interaction and Visualisation) | G8: M. Yudhi Rezaldi, Ph.D | Q8: Arief Aflah, Arief Budiman | R8: Jurnal | S8: Published | T8: Jurnal Manajemen Pendidikan dan Ilmu Sosial (JMPIS) | V8: PN | W8: https://dinastirev.org/JMPIS/article/view/4780 | X8: https://doi.org/10.38035/jmpis.v6i3.4780
A9: 4 | B9: =IF(OR(E9<>"",F9<>""),IF(B9="",NOW(),B9),"") -> 45840.606 | E9: Sentiment Analysis and Topic Modeling of Public Opinion on Indonesia New Capital City Development Policies | F9: Pengolahan Bahasa Alami (Natural Language Processing) | G9: Prabu Kresna Putra, S.T., M.T.I. | Q9: Michael David Angelo, Indra Budi, Aris Budi, Reyhan Widyatna Harwenda | R9: Jurnal | S9: Published | T9: Journal of Universal Studies | V9: PN | W9: http://www.eduvest.greenvest.co.id.submitjurnal.id/index.php/edv/article/view/51234 | X9: https://doi.org/10.59188/eduvest.v5i5.51234 | Y9: Sinta3
A10: 5 | B10: =IF(OR(E10<>"",F10<>""),IF(B10="",NOW(),B10),"") -> 45875.625 | E10: Evaluasi Kinerja Website Digital Library Perbanas Institute menggunakan Metode PIECES dan GTmetrix | F10: Pemerintahan Digital (Digital Government) | G10: Dr. Ekawati Marlina, S.T., M.T. | Q10: Rafli Nofaldo, Mardiana Purwaningsih, Dwi Atmodjo Wismono Prapto | R10: Jurnal | S10: Published | T10: Jurnal Dokumentasi dan Informasi | U10: S2 | V10: PN | W10: https://ejournal.brin.go.id/baca/article/view/8966
A11: 6 | B11: =IF(OR(E11<>"",F11<>""),IF(B11="",NOW(),B11),"") -> 45875.628 | C11: Agustus | E11: Optimizing Multi-Layer Perceptron Performance in Sentiment Classification through Neural Network Feature Extraction | F11: Temu Kembali Informasi (Information Retrieval) | G11: Dr. Purnomo Husnul Khotimah, M.T | H11: Dr. DIPL. ING (FH) Anne Parlina, M.P. | I11: Andre Sihombing, S.Kom., M.Sc. | Q11: Muhammad Fikri Alam, Aang Nuryaman | R11: Jurnal | S11: Published | T11: Jurnal Dokumentasi dan Informasi | U11: S2 | V11: PN | W11: https://ejournal.brin.go.id/baca/article/view/8240
A12: 7 | B12: =IF(OR(E12<>"",F12<>""),IF(B12="",NOW(),B12),"") -> 45918.482 | C12: Triwulan III | E12: Pengembangan Front-End Aplikasi Mysre: Aplikasi Tinjauan Literatur Untuk Peneliti Pemula | F12: Interaksi Manusia-Komputer dan Visualisasi (Human Computer Interaction and Visualisation) | G12: Rio Nurtantyana, S.Pd., M.Pd., M.Sc., Ph.D. | Q12: Uun Hariyanti, Delisya Jayadi, Tri Afirianto, Prima Zulvarina | R12: Jurnal | S12: Published | T12: Jurnal Teknologi Informasi dan Ilmu Komputer (JTIIK) | U12: S2 | V12: PN | W12: https://jtiik.ub.ac.id/index.php/jtiik/article/view/9738 | X12: https://doi.org/10.25126/jtiik.124
A13: 8 | B13: =IF(OR(E13<>"",F13<>""),IF(B13="",NOW(),B13),"") -> 45952.249 | C13: Oktober | E13: Factors and Impacts of Knowledge Sharing in Digital Beauty Community: A Systematic Literature Review | F13: Interaksi Manusia-Komputer dan Visualisasi (Human Computer Interaction and Visualisation) | G13: Arafat Febriandirza, Ph.D | Q13: Shella Maria Vernanda, Christianto Vinsen, Dana Indra Sensuse, Nadya Safitri | R13: Jurnal | S13: Published | T13: Kesatria: Jurnal Penerapan Sistem Informasi (Komputer dan Manajemen) | V13: PN | W13: https://tunasbangsa.ac.id/pkm/index.php/kesatria/article/view/593/588 | X13: https://dx.doi.org/10.30645/kesatria.v6i2.593
A14: 9 | B14: =IF(OR(E14<>"",F14<>""),IF(B14="",NOW(),B14),"") -> 45952.253 | C14: Oktober | E14: Penelitian UX: Metode dan Praktik Terbaik | F14: Interaksi Manusia-Komputer dan Visualisasi (Human Computer Interaction and Visualisation) | G14: Arafat Febriandirza, Ph.D | R14: Bag Buku | S14: Published | T14: UI/UX Design: Teori, Proses, dan Karier (Kaizen Media Publishing) | U14: S2 | V14: PN | W14: https://books.google.co.id/books?id=LpWNEQAAQBAJ
A15: 10 | B15: =IF(OR(E15<>"",F15<>""),IF(B15="",NOW(),B15),"") -> 45953.543 | C15: Oktober | E15: Performance Evaluation of NAS Parallel and High-Performance Conjugate Gradient Benchmarks in Mahameru | F15: Temu Kembali Informasi (Information Retrieval) | G15: Andria Arisal, M. Eng. | Q15: Taufiq Wirahman, Arnida L Latifah, Furqon Hensan Muttaqien, I Wayan Aditya Swardiana, Syam Budi Iryanto, Rifki Sadikin | R15: Jurnal | S15: Published | T15: Jurnal Online Informatika | U15: S2 | V15: PN | X15: https://dx.doi.org/10.15575/join.v10i2.1557
A16: 11 | B16: =IF(OR(E16<>"",F16<>""),IF(B16="",NOW(),B16),"") -> 45994.439 | C16: Triwulan IV | E16: Analisis Sentimen Berdasarkan Data Media Sosial: Studi Kasus Pada Berbagai Domain di Indonesia | F16: Pengolahan Bahasa Alami (Natural Language Processing) | G16: Yaniasih | Q16: Indra Budi | R16: Buku | S16: Published | T16: UI Publishing | V16: PN | X16: ISBN: 978-634-244-051-3
Q17: Evi Yulianti | R17: Jurnal | S17: Published | T17: Jurnal Resti | U17: S2 | V17: PN | W17: https://jurnal.iaii.or.id/index.php/RESTI/article/view/6397/1060 | X17: https://doi.org/10.29207/resti.v9i3.6397
A18: 13 | B18: =IF(OR(E18<>"",F18<>""),IF(B18="",NOW(),B18),"") | V18: PN
A19: 14 | B19: =IF(OR(E19<>"",F19<>""),IF(B19="",NOW(),B19),"") | V19: PN
A20: 15 | B20: =IF(OR(E20<>"",F20<>""),IF(B20="",NOW(),B20),"") | V20: PN
A21: 16 | B21: =IF(OR(E21<>"",F21<>""),IF(B21="",NOW(),B21),"") | V21: PN
A22: 17 | B22: =IF(OR(E22<>"",F22<>""),IF(B22="",NOW(),B22),"") | V22: PN
A23: 18 | B23: =IF(OR(E23<>"",F23<>""),IF(B23="",NOW(),B23),"") | V23: PN
A24: 19 | B24: =IF(OR(E24<>"",F24<>""),IF(B24="",NOW(),B24),"") | V24: PN
A25: 20 | B25: =IF(OR(E25<>"",F25<>""),IF(B25="",NOW(),B25),"") | V25: PN
A26: 21 | B26: =IF(OR(E26<>"",F26<>""),IF(B26="",NOW(),B26),"") | V26: PN
A27: 22 | B27: =IF(OR(E27<>"",F27<>""),IF(B27="",NOW(),B27),"") | V27: PN
A28: 23 | B28: =IF(OR(E28<>"",F28<>""),IF(B28="",NOW(),B28),"") | V28: PN
A29: 24 | B29: =IF(OR(E29<>"",F29<>""),IF(B29="",NOW(),B29),"") | V29: PN
... A199: 195 | B199: =IF(OR(E199<>"",F199<>""),IF(B199="",NOW(),B199),"") | V199: PN
G201: Per 31/08/24 | H201: 2

Sheet Rekap Capaian Individu
E4: PURWARUPA | H4: KEKAYAAN INTELEKTUAL | K4: PUBLIKASI INTERNASIONAL | N4: SDM STUDI LANJUT | Q4: POSTDOC/VISITING RSRCH | T4: DANA EKS | W4: SITASI | Z4: PUBLIKASI NASIONAL | AC4: KERJASAMA DALAM NEGERI | AF4: KERJASAMA LUAR NEGERI | AI4: TALENTA RISET
A5: No | B5: KELOMPOK RISET | C5: =IFERROR(__xludf.DUMMYFUNCTION("IMPORTRANGE(""https://docs.google.com/spreadsheets/d/1YXbkUPS13wPU8Dscegl2VkhWtKARm3NYP21WfoO0JNs/edit"", ""Rekap Capaian Individu!C5:C120"")"),"NAMA") -> NAMA | D5: PEND | E5: TARGET | F5: =IFERROR(__xludf.DUMMYFUNCTION("IMPORTRANGE(""https://docs.google.com/spreadsheets/d/1YXbkUPS13wPU8Dscegl2VkhWtKARm3NYP21WfoO0JNs/edit"", ""Rekap Capaian Individu!F5:G120"")"),"CAPAIAN") -> CAPAIAN | G5: =IFERROR(__xludf.DUMMYFUNCTION("""COMPUTED_VALUE"""),"%") -> % | H5: TARGET | I5: =IFERROR(__xludf.DUMMYFUNCTION("IMPORTRANGE(""https://docs.google.com/spreadsheets/d/1YXbkUPS13wPU8Dscegl2VkhWtKARm3NYP21WfoO0JNs/edit"", ""Rekap Capaian Individu!I5:J120"")"),"CAPAIAN") -> CAPAIAN | J5: =IFERROR(__xludf.DUMMYFUNCTION("""COMPUTED_VALUE"""),"%") -> % | K5: TARGET | L5: =IFERROR(__xludf.DUMMYFUNCTION("IMPORTRANGE(""https://docs.google.com/spreadsheets/d/1YXbkUPS13wPU8Dscegl2VkhWtKARm3NYP21WfoO0JNs/edit"", ""Rekap Capaian Individu!L5:M120"")"),"CAPAIAN") -> CAPAIAN | M5: =IFERROR(__xludf.DUMMYFUNCTION("""COMPUTED_VALUE"""),"%") -> % | N5: TARGET | O5: =IFERROR(__xludf.DUMMYFUNCTION("IMPORTRANGE(""https://docs.google.com/spreadsheets/d/1YXbkUPS13wPU8Dscegl2VkhWtKARm3NYP21WfoO0JNs/edit"", ""Rekap Capaian Individu!O5:P120"")"),"CAPAIAN") -> CAPAIAN | P5: =IFERROR(__xludf.DUMMYFUNCTION("""COMPUTED_VALUE"""),"%") -> % | Q5: TARGET | R5: =IFERROR(__xludf.DUMMYFUNCTION("IMPORTRANGE(""https://docs.google.com/spreadsheets/d/1YXbkUPS13wPU8Dscegl2VkhWtKARm3NYP21WfoO0JNs/edit"", ""Rekap Capaian Individu!R5:S120"")"),"CAPAIAN") -> CAPAIAN | S5: =IFERROR(__xludf.DUMMYFUNCTION("""COMPUTED_VALUE"""),"%") -> % | T5: TARGET | U5: =IFERROR(__xludf.DUMMYFUNCTION("IMPORTRANGE(""https://docs.google.com/spreadsheets/d/1YXbkUPS13wPU8Dscegl2VkhWtKARm3NYP21WfoO0JNs/edit"", ""Rekap Capaian Individu!U5:V120"")"),"CAPAIAN") -> CAPAIAN | V5: =IFERROR(__xludf.DUMMYFUNCTION("""COMPUTED_VALUE"""),"%") -> % | W5: TARGET | X5: =IFERROR(__xludf.DUMMYFUNCTION("IMPORTRANGE(""https://docs.google.com/spreadsheets/d/1YXbkUPS13wPU8Dscegl2VkhWtKARm3NYP21WfoO0JNs/edit"", ""Rekap Capaian Individu!X5:Y120"")"),"CAPAIAN") -> CAPAIAN | Y5: =IFERROR(__xludf.DUMMYFUNCTION("""COMPUTED_VALUE"""),"%") -> % | Z5: =IFERROR(__xludf.DUMMYFUNCTION("IMPORTRANGE(""https://docs.google.com/spreadsheets/d/1NVRWh9Q82kqv2wKrTSDtCaEqsS16ROGSicN7AZKpmUA/edit"", ""Rekap Capaian Individu!Z5:Z120"")"),"TARGET") -> TARGET | AA5: =IFERROR(__xludf.DUMMYFUNCTION("IMPORTRANGE(""https://docs.google.com/spreadsheets/d/1YXbkUPS13wPU8Dscegl2VkhWtKARm3NYP21WfoO0JNs/edit"", ""Rekap Capaian Individu!AA5:AB120"")"),"CAPAIAN") -> CAPAIAN | AB5: =IFERROR(__xludf.DUMMYFUNCTION("""COMPUTED_VALUE"""),"%") -> % | AC5: =IFERROR(__xludf.DUMMYFUNCTION("IMPORTRANGE(""https://docs.google.com/spreadsheets/d/1NVRWh9Q82kqv2wKrTSDtCaEqsS16ROGSicN7AZKpmUA/edit"", ""Rekap Capaian Individu!Z5:Z120"")"),"TARGET") -> TARGET | AD5: =IFERROR(__xludf.DUMMYFUNCTION("IMPORTRANGE(""https://docs.google.com/spreadsheets/d/1YXbkUPS13wPU8Dscegl2VkhWtKARm3NYP21WfoO0JNs/edit"", ""Rekap Capaian Individu!AD5:AE120"")"),"CAPAIAN") -> CAPAIAN | AE5: =IFERROR(__xludf.DUMMYFUNCTION("""COMPUTED_VALUE"""),"%") -> % | AF5: =IFERROR(__xludf.DUMMYFUNCTION("IMPORTRANGE(""https://docs.google.com/spreadsheets/d/1NVRWh9Q82kqv2wKrTSDtCaEqsS16ROGSicN7AZKpmUA/edit"", ""Rekap Capaian Individu!Z5:Z120"")"),"TARGET") -> TARGET | AG5: =IFERROR(__xludf.DUMMYFUNCTION("IMPORTRANGE(""https://docs.google.com/spreadsheets/d/1YXbkUPS13wPU8Dscegl2VkhWtKARm3NYP21WfoO0JNs/edit"", ""Rekap Capaian Individu!AG5:AH120"")"),"CAPAIAN") -> CAPAIAN | AH5: =IFERROR(__xludf.DUMMYFUNCTION("""COMPUTED_VALUE"""),"%") -> % | AI5: =IFERROR(__xludf.DUMMYFUNCTION("IMPORTRANGE(""https://docs.google.com/spreadsheets/d/1NVRWh9Q82kqv2wKrTSDtCaEqsS16ROGSicN7AZKpmUA/edit"", ""Rekap Capaian Individu!Z5:Z120"")"),"TARGET") -> TARGET | AJ5: =IFERROR(__xludf.DUMMYFUNCTION("IMPORTRANGE(""https://docs.google.com/spreadsheets/d/1YXbkUPS13wPU8Dscegl2VkhWtKARm3NYP21WfoO0JNs/edit"", ""Rekap Capaian Individu!AJ5:AK120"")"),"CAPAIAN") -> CAPAIAN | AK5: =IFERROR(__xludf.DUMMYFUNCTION("""COMPUTED_VALUE"""),"%") -> %
A6: 1 | B6: Interaksi Manusia-Komputer dan Visualisasi (Human Computer Interaction and Visualisation) | C6: =IFERROR(__xludf.DUMMYFUNCTION("""COMPUTED_VALUE"""),"Dr. Esa Prakasa, MT") -> Dr. Esa Prakasa, MT | F6: =IFERROR(__xludf.DUMMYFUNCTION("""COMPUTED_VALUE"""),0) -> 0 | I6: =IFERROR(__xludf.DUMMYFUNCTION("""COMPUTED_VALUE"""),3) -> 3 | L6: =IFERROR(__xludf.DUMMYFUNCTION("""COMPUTED_VALUE"""),7) -> 7 | O6: =IFERROR(__xludf.DUMMYFUNCTION("""COMPUTED_VALUE"""),0) -> 0 | R6: =IFERROR(__xludf.DUMMYFUNCTION("""COMPUTED_VALUE"""),0) -> 0 | U6: =IFERROR(__xludf.DUMMYFUNCTION("""COMPUTED_VALUE"""),"#VALUE!") -> #VALUE! | X6: =IFERROR(__xludf.DUMMYFUNCTION("""COMPUTED_VALUE"""),72) -> 72 | AA6: =IFERROR(__xludf.DUMMYFUNCTION("""COMPUTED_VALUE"""),0) -> 0 | AD6: =IFERROR(__xludf.DUMMYFUNCTION("""COMPUTED_VALUE"""),11) -> 11 | AG6: =IFERROR(__xludf.DUMMYFUNCTION("""COMPUTED_VALUE"""),2) -> 2 | AJ6: =IFERROR(__xludf.DUMMYFUNCTION("""COMPUTED_VALUE"""),0) -> 0
A7: 2 | B7: Interaksi Manusia-Komputer dan Visualisasi (Human Computer Interaction and Visualisation) | C7: =IFERROR(__xludf.DUMMYFUNCTION("""COMPUTED_VALUE"""),"Abdurrakhman Prasetyadi, M.P") -> Abdurrakhman Prasetyadi, M.P | F7: =IFERROR(__xludf.DUMMYFUNCTION("""COMPUTED_VALUE"""),0) -> 0 | I7: =IFERROR(__xludf.DUMMYFUNCTION("""COMPUTED_VALUE"""),6) -> 6 | L7: =IFERROR(__xludf.DUMMYFUNCTION("""COMPUTED_VALUE"""),4) -> 4 | O7: =IFERROR(__xludf.DUMMYFUNCTION("""COMPUTED_VALUE"""),0) -> 0 | R7: =IFERROR(__xludf.DUMMYFUNCTION("""COMPUTED_VALUE"""),0) -> 0 | U7: =IFERROR(__xludf.DUMMYFUNCTION("""COMPUTED_VALUE"""),"#VALUE!") -> #VALUE! | X7: =IFERROR(__xludf.DUMMYFUNCTION("""COMPUTED_VALUE"""),16) -> 16 | AA7: =IFERROR(__xludf.DUMMYFUNCTION("""COMPUTED_VALUE"""),0) -> 0 | AD7: =IFERROR(__xludf.DUMMYFUNCTION("""COMPUTED_VALUE"""),4) -> 4 | AG7: =IFERROR(__xludf.DUMMYFUNCTION("""COMPUTED_VALUE"""),1) -> 1 | AJ7: =IFERROR(__xludf.DUMMYFUNCTION("""COMPUTED_VALUE"""),0) -> 0
A8: 3 | B8: Pengolahan Bahasa Alami (Natural Language Processing) | C8: =IFERROR(__xludf.DUMMYFUNCTION("""COMPUTED_VALUE"""),"Agung Santosa, BSEE, M.Kom") -> Agung Santosa, BSEE, M.Kom | F8: =IFERROR(__xludf.DUMMYFUNCTION("""COMPUTED_VALUE"""),0) -> 0 | I8: =IFERROR(__xludf.DUMMYFUNCTION("""COMPUTED_VALUE"""),6) -> 6 | L8: =IFERROR(__xludf.DUMMYFUNCTION("""COMPUTED_VALUE"""),3) -> 3 | O8: =IFERROR(__xludf.DUMMYFUNCTION("""COMPUTED_VALUE"""),0) -> 0 | R8: =IFERROR(__xludf.DUMMYFUNCTION("""COMPUTED_VALUE"""),0) -> 0 | U8: =IFERROR(__xludf.DUMMYFUNCTION("""COMPUTED_VALUE"""),"#VALUE!") -> #VALUE! | X8: =IFERROR(__xludf.DUMMYFUNCTION("""COMPUTED_VALUE"""),25) -> 25 | AA8: =IFERROR(__xludf.DUMMYFUNCTION("""COMPUTED_VALUE"""),0) -> 0 | AD8: =IFERROR(__xludf.DUMMYFUNCTION("""COMPUTED_VALUE"""),1) -> 1 | AG8: =IFERROR(__xludf.DUMMYFUNCTION("""COMPUTED_VALUE"""),0) -> 0 | AJ8: =IFERROR(__xludf.DUMMYFUNCTION("""COMPUTED_VALUE"""),0) -> 0
A9: 4 | B9: Interaksi Manusia-Komputer dan Visualisasi (Human Computer Interaction and Visualisation) | C9: =IFERROR(__xludf.DUMMYFUNCTION("""COMPUTED_VALUE"""),"Dr. Ambar Yoganingrum") -> Dr. Ambar Yoganingrum | F9: =IFERROR(__xludf.DUMMYFUNCTION("""COMPUTED_VALUE"""),0) -> 0 | I9: =IFERROR(__xludf.DUMMYFUNCTION("""COMPUTED_VALUE"""),4) -> 4 | L9: =IFERROR(__xludf.DUMMYFUNCTION("""COMPUTED_VALUE"""),5) -> 5 | O9: =IFERROR(__xludf.DUMMYFUNCTION("""COMPUTED_VALUE"""),0) -> 0 | R9: =IFERROR(__xludf.DUMMYFUNCTION("""COMPUTED_VALUE"""),0) -> 0 | U9: =IFERROR(__xludf.DUMMYFUNCTION("""COMPUTED_VALUE"""),"#VALUE!") -> #VALUE! | X9: =IFERROR(__xludf.DUMMYFUNCTION("""COMPUTED_VALUE"""),18) -> 18 | AA9: =IFERROR(__xludf.DUMMYFUNCTION("""COMPUTED_VALUE"""),0) -> 0 | AD9: =IFERROR(__xludf.DUMMYFUNCTION("""COMPUTED_VALUE"""),3) -> 3 | AG9: =IFERROR(__xludf.DUMMYFUNCTION("""COMPUTED_VALUE"""),1) -> 1 | AJ9: =IFERROR(__xludf.DUMMYFUNCTION("""COMPUTED_VALUE"""),0) -> 0
